Workbook

Sheet README
A1: RMBS cash-flow valuation model — senior tranches, issuer-reported history
A3: Purpose
A4: Values a senior RMBS tranche from projected cash flows anchored on the last issuer-reported IPD, not on Bloomberg's factor/payment history.
A5: Collateral: quarterly step. Defaults (CDR), scheduled amortisation (level annuity, remaining term implied from the last reported scheduled principal), prepayments (CPR), recoveries after a lag.
A6: Liabilities: Class A vs aggregated subordinate notes; pro-rata / sequential switch on the prospectus tests; excess spread cures a Principal Deficiency Ledger (PDL); optional clean-up call; legal-final sweep.
A7: Pricing: price <-> discount margin (Newton on the projected index curve, ACT/360 simple per period), yield by XIRR, WAL, spread duration.
A9: Colour code
A10: Blue text = hard input · Yellow fill = key assumption / cell to fill · Black = formula · Green = link to another sheet.
A12: Workflow
A13: 1. Run rmbs_harvester.py (internet machine) -> out/<ISIN>.csv. Paste rows into 'History' (same column order).
A14: 2. In 'Deals', update the selected ISIN's row from the latest report (balances, margins, pool, WAC, scheduled principal, fixing).
A15: 3. In 'Inputs', pick the ISIN, set settlement (must fall before the next IPD), CPR/CDR/severity/lag, call mode, curve.
... A24: Model acceptance per ISIN: out/champion_models.csv (NO_RELIABLE_MODEL = price only under an explicit scenario).

Sheet Inputs
B1: RMBS senior tranche — cash-flow valuation
B3: Selected ISIN | C3: XS0222684655
B5: Deal data (linked from Deals) | F5: Scenario & pricing assumptions | J5: Valuation outputs
B6: Ticker | C6: =INDEX(Deals!$B$2:$B$18,MATCH($C$3,Deals!$A$2:$A$18,0)) -> MAGEL 3 A | F6: Settlement date | G6: 46289 | J6: Clean price | K6: =IF($G$7="DM",Engine!AO8/C11*100-G26/C11*100,G8) -> 98.5
B7: Last IPD | C7: =INDEX(Deals!$G$2:$G$18,MATCH($C$3,Deals!$A$2:$A$18,0)) -> 46251 | F7: Mode: PRICE (price→DM) or DM (DM→price) | G7: PRICE | J7: Accrued (per 100) | K7: =G26/C11*100 -> 0.26515556
B8: Next IPD (unadjusted) | C8: =INDEX(Deals!$H$2:$H$18,MATCH($C$3,Deals!$A$2:$A$18,0)) -> 46341 | F8: Clean price (per 100 current face) | G8: 98.5 | J8: Dirty price | K8: =K6+K7 -> 98.765156
B9: Legal final | C9: =INDEX(Deals!$I$2:$I$18,MATCH($C$3,Deals!$A$2:$A$18,0)) -> 57845 | F9: Input discount margin (bp) — used in DM mode | G9: 60 | J9: Discount margin (bp) | K9: =IF($G$7="DM",G9,Engine!BC9*10000) -> 59.498049
B10: A original (€) | C10: =INDEX(Deals!$J$2:$J$18,MATCH($C$3,Deals!$A$2:$A$18,0)) -> 1413750000 | F10: CPR (annual) | G10: 0.0424 | J10: Yield, annual effective (XIRR, ACT/365) | K10: =XIRR(Engine!BL10:BL190,Engine!BK10:BK190) -> 0.029180592
B11: A current (€) | C11: =INDEX(Deals!$K$2:$K$18,MATCH($C$3,Deals!$A$2:$A$18,0)) -> 1.1084507e+08 | F11: CDR (annual) | G11: 0.001 | J11: Yield, quarterly compounded | K11: =4*((1+K10)^0.25-1) -> 0.028866606
B12: Subordinate current (€) | C12: =INDEX(Deals!$L$2:$L$18,MATCH($C$3,Deals!$A$2:$A$18,0)) -> 8507872.5 | F12: Loss severity | G12: 0.2 | J12: WAL (years, ACT/365) | K12: =SUMPRODUCT(Engine!AD11:AD190,Engine!AJ11:AJ190)/SUM(Engine!AD11:AD190) -> 4.8676881
B13: A margin | C13: =INDEX(Deals!$M$2:$M$18,MATCH($C$3,Deals!$A$2:$A$18,0)) -> 0.0026 | F13: Recovery lag (quarters) | G13: 8 | J13: Spread duration (±10bp DM) | K13: =(Engine!BG8-Engine!BI8)/(2*G27*0.001) -> 4.4801644
B14: Sub WA margin | C14: =INDEX(Deals!$N$2:$N$18,MATCH($C$3,Deals!$A$2:$A$18,0)) -> 0.0070626087 | F14: 90d+ arrears ratio for pro-rata test | G14: =C29 -> 5.3028846e-05 | J14: Time to next reset (years) | K14: =(Engine!C11-G6)/365 -> 0.14520548
B15: Current-period index fixing | C15: =INDEX(Deals!$O$2:$O$18,MATCH($C$3,Deals!$A$2:$A$18,0)) -> 0.02252 | F15: Call mode: 0 none · 1 first eligible IPD · 2 on/after date | G15: 0 | J15: Last principal date | K15: =SUMPRODUCT(MAX((Engine!AD11:AD190>0.005)*Engine!C11:C190)) -> 50175
B16: Pool current, net (€) | C16: =INDEX(Deals!$P$2:$P$18,MATCH($C$3,Deals!$A$2:$A$18,0)) -> 1.1935638e+08 | F16: Call date (mode 2) | G16: 46433 | J16: Projected principal loss, Class A (€) | K16: =SUMPRODUCT((Engine!E11:E190=TRUE())*(Engine!O11:O190-Engine!AD11:AD190)) -> 0
B17: Pool at cut-off (€) | C17: =INDEX(Deals!$Q$2:$Q$18,MATCH($C$3,Deals!$A$2:$A$18,0)) -> 1.5e+09 | F17: Flat EUR 3M forward (if no curve) | G17: 0.02252 | J17: Call date used | K17: =IFERROR(INDEX(Engine!C11:C190,MATCH(TRUE(),Engine!AB11:AB190,0)),"no call") -> no call
B18: WAC | C18: =INDEX(Deals!$R$2:$R$18,MATCH($C$3,Deals!$A$2:$A$18,0)) -> 0.03174 | F18: Use Curve sheet (1/0) | G18: 0 | J18: DM solver residual (€) | K18: =IF($G$7="DM",0,Engine!BC8-G27) -> 0
B19: Pool ref. for sched. (€) | C19: =INDEX(Deals!$S$2:$S$18,MATCH($C$3,Deals!$A$2:$A$18,0)) -> 1.2339789e+08 | F19: Class A coupon floor (blank = none) | G19: 0 | J19: Freshness check | K19: =IF(G6>=Engine!C11,"STALE: settlement on/after next IPD — harvest the newer report",IF(G6<C7,"ERROR: settlement before last IPD","OK")) -> OK
B20: Observed sched. principal (€/qtr) | C20: =INDEX(Deals!$T$2:$T$18,MATCH($C$3,Deals!$A$2:$A$18,0)) -> 2257065.1 | F20: Class A principal paid / due (1 = no shortfall; Hipocat 11 option) | G20: 1 | J20: Class A principal conservation (should be 0) | K20: =C11-SUM(Engine!AD11:AD190)-K16 -> 0
B21: Pro-rata allowed (1/0) | C21: =INDEX(Deals!$W$2:$W$18,MATCH($C$3,Deals!$A$2:$A$18,0)) -> 1 | F21: Quarterly prepay rate 1-(1-CPR)^0.25 | G21: =1-(1-G10)^0.25 -> 0.010772834 | J21: Class A total cash flow (€) | K21: =SUM(Engine!AI11:AI190) -> 1.2488095e+08
B22: Pro-rata: A/A_orig <= | C22: =INDEX(Deals!$X$2:$X$18,MATCH($C$3,Deals!$A$2:$A$18,0)) -> 0.75 | F22: Quarterly default rate 1-(1-CDR)^0.25 | G22: =1-(1-G11)^0.25 -> 0.0002500938 | J22: Projected A factor in 1y | K22: =INDEX(Engine!AG11:AG190,4)/C10 -> 0.069451934
B23: Pro-rata: arrears < | C23: =INDEX(Deals!$Y$2:$Y$18,MATCH($C$3,Deals!$A$2:$A$18,0)) -> 0.018 | F23: Quarterly WAC | G23: =C18/4 -> 0.007935
B24: Clean-up call threshold | C24: =INDEX(Deals!$Z$2:$Z$18,MATCH($C$3,Deals!$A$2:$A$18,0)) -> 0.1 | F24: Implied remaining term (quarters) | G24: =IFERROR(LN(1+G23*C19/C20)/LN(1+G23),0) -> 45.59177 | J24: Legend: blue = input, yellow = assumption to set, green = link to Deals, black = formula.
B25: Fees fixed (€/qtr) | C25: =INDEX(Deals!$AA$2:$AA$18,MATCH($C$3,Deals!$A$2:$A$18,0)) -> 100000 | F25: Implied remaining term (years) | G25: =G24/4 -> 11.397943
B26: Fees (bp p.a.) | C26: =INDEX(Deals!$AB$2:$AB$18,MATCH($C$3,Deals!$A$2:$A$18,0)) -> 0.001 | F26: Accrued (€) | G26: =C11*(C15+C13)*(G6-C7)/360 -> 293911.86
B27: Reported CPR last qtr | C27: =INDEX(Deals!$U$2:$U$18,MATCH($C$3,Deals!$A$2:$A$18,0)) -> 0.0424 | F27: Dirty amount target (€) | G27: =K6/100*C11+G26 -> 1.094763e+08
B28: Data status | C28: =INDEX(Deals!$AC$2:$AC$18,MATCH($C$3,Deals!$A$2:$A$18,0)) -> History 23 IPDs to 2026-08-17; gate INCOMPLETE; model NO_RELIABLE_MODEL; CONFIG_INCOMPLETE: fees,swap
B29: 90d+ arrears ratio (reported) | C29: =INDEX(Deals!$V$2:$V$18,MATCH($C$3,Deals!$A$2:$A$18,0)) -> 5.3028846e-05
F36: History calibration (selected ISIN)
F37: IPDs in History | G37: =COUNTIF(History!A4:A2003,$C$3) -> 23
F38: Latest IPD in History | G38: =_xlfn.MAXIFS(History!E4:E2003,History!A4:A2003,$C$3) -> 46251
F39: Mean realised CPR (prepay only), last 12m | G39: =IFERROR(AVERAGEIFS(History!BC4:BC2003,History!A4:A2003,$C$3,History!E4:E2003,">"&EDATE(G38,-12)),"n/a") -> 0.048467283
F40: Rows not 'ok' after validation (count) | G40: =SUMPRODUCT((History!A4:A2003=$C$3)*(LEFT(History!AR4:AR2003,6)="review")) -> 0
F41: Last IPD in History = Deals last IPD? | G41: =IF(G38=C7,"consistent","CHECK: Deals row older/newer than History") -> consistent

Sheet Deals
A1: ISIN | B1: Ticker | C1: Deal | D1: Country | E1: Reporting entity | F1: As-of IPD (last report) | G1: Last IPD | H1: Next IPD (unadj.) | I1: Legal final | J1: A original (€) | K1: A current (€) | L1: Subordinate current (€) | M1: A margin | N1: Sub WA margin | O1: Current-period index fixing | P1: Pool current, net of deemed losses (€) | Q1: Pool at cut-off (€) | R1: WAC | S1: Pool ref. for sched. amort. (€) | T1: Observed sched. principal last qtr (€) | U1: Reported CPR last qtr | V1: 90-365d arrears ratio | W1: Pro-rata allowed (1/0) | X1: Pro-rata: A/A_orig <= | Y1: Pro-rata: arrears < | Z1: Clean-up call (% of cut-off pool) | AA1: Fees fixed (€/qtr) | AB1: Fees (bp p.a. of pool) | AC1: Data status | AD1: IPD rule | AE1: Margin step-ups | AF1: Coupon floor | AG1: Amortisation / triggers | AH1: Reserve | AI1: Issuer-stated call | AJ1: Principal shortfall option | AK1: Conflicts / unverified
A2: XS0222684655 | B2: MAGEL 3 A | C2: Magellan Mortgages No. 3 plc | D2: PT | E2: BCP | F2: 46251 | G2: 46251 | H2: 46341 | I2: 57845 | J2: 1413750000 | K2: 1.1084507e+08 | L2: 8507872.5 | M2: 0.0026 | N2: 0.0070626087 | O2: 0.02252 | P2: 1.1935638e+08 | Q2: 1.5e+09 | R2: 0.03174 | S2: 1.2339789e+08 | T2: 2257065.1 | U2: 0.0424 | V2: 5.3028846e-05 | W2: 1 | X2: 0.75 | Y2: 0.018 | Z2: 0.1 | AA2: 100000 | AB2: 0.001 | AC2: History 23 IPDs to 2026-08-17; gate INCOMPLETE; model NO_RELIABLE_MODEL; CONFIG_INCOMPLETE: fees,swap | AD2: {"months": [2, 5, 8, 11], "day": 15, "convention": "following", "calendar": "PT"} | AE2: 2012-08-15: 26bp | AF2: 0.0 from 2018-01-01 | AG2: {"amortisation": {"mode": "pro_rata_if_test_pass", "switch_to_sequential_if": ["Pro-Rata Test FAIL (report Sec.3)"]}, "triggers": {"prorata_A_over_A_orig_max": null, "arrears_90_365_ratio_max": null, "note": "test result is read from each report (Pro | AH2: {"observed": [{"date": "2009-02-16", "balance": 13500000}, {"date": "2026-08-17", "balance": 9000000}], "required_rule": null} | AJ2: no | AK2: legal_final day (Notes due 2058 per Euronext RIS; day from original model); coupon_floor_from: Aug-2017 coupon -0.069%, Nov-2017 not read; swap; fees
A3: XS0260784318 | B3: MAGEL 4 A | C3: Magellan Mortgages No. 4 plc | D3: PT | E3: BCP | F3: 46223 | G3: 46223 | H3: 46315 | I3: 58276 | J3: 1413750000 | K3: 1.3524357e+08 | L3: 10646700 | M3: 0.0028 | N3: 0.0069652174 | O3: 0.02238 | P3: 1.4588906e+08 | Q3: 1.5e+09 | R3: 0.02996 | S3: 1.5030128e+08 | T3: 2411455.1 | U3: 0.0522 | V3: 5.6418726e-05 | W3: 1 | X3: 0.75 | Y3: 0.018 | Z3: 0.1 | AA3: 40000 | AB3: 0.001 | AC3: History 10 IPDs to 2026-07-20; gate INCOMPLETE; model NO_RELIABLE_MODEL (THIN_HISTORY); CONFIG_INCOMPLETE: fees,swap | AD3: {"months": [1, 4, 7, 10], "day": 20, "convention": "following", "calendar": "PT"} | AE3: 2017-04-20: 28bp | AF3: 0.0 from 2017-04-20 | AG3: {"amortisation": {"mode": "pro_rata_if_test_pass", "note": "pro-rata since Jul-2008 (Moody's Feb-2021)"}, "triggers": {"note": "Pro-Rata Test read from each report; thresholds not transcribed"}} | AH3: {"observed": [{"date": "2021-02-01", "balance": 9000000, "note": "at floor (Moody's)"}], "required_rule": null} | AJ3: no | AK3: margin step-up IPD (bounded, see margin_steps); coupon_floor_from: first floored IPD observed is Apr-2017 (earlier reports not read); clean_up_call_pct (from original model, prospectus not read); legal_final day; swap; fees
A4: XS0230694233 | B4: LUSI 4 A | C4: Lusitano Mortgages No. 4 plc | D4: PT | E4: Citibank N.A. / novobanco | J4: 1134000000 | AC4: History 0 IPDs; gate MANUAL_REQUIRED; model MANUAL_REQUIRED; CONFIG_INCOMPLETE: amortisation,clean_up_call_pct,coupon_floor,denomination,fees,ipd_rule,legal_final,notes,reserve,swap,triggers | AD4: null | AE4: none known | AG4: {"amortisation": null, "triggers": null} | AH4: null | AJ4: no | AK4: legal final: ESFG 'December 2048' vs oblible 14-Sep-2048
A5: XS0268642161 | B5: LUSI 5 A | C5: Lusitano Mortgages No. 5 plc | D5: PT | E5: Citibank N.A. / novobanco | I5: 58271 | AC5: History 0 IPDs; gate MANUAL_REQUIRED; model MANUAL_REQUIRED; CONFIG_INCOMPLETE: amortisation,clean_up_call_pct,coupon_floor,denomination,fees,ipd_rule,margin_bp,notes,original_balance,reserve,swap,triggers | AD5: null | AE5: none known | AG5: {"amortisation": null, "triggers": null} | AH5: null | AJ5: no
A6: XS0312981649 | B6: LUSI 6 A | C6: Lusitano Mortgages No. 6 plc | D6: PT | E6: Citibank N.A. / novobanco | AC6: History 0 IPDs; gate MANUAL_REQUIRED; model MANUAL_REQUIRED; CONFIG_INCOMPLETE: amortisation,clean_up_call_pct,coupon_floor,denomination,fees,ipd_rule,legal_final,margin_bp,notes,original_balance,reserve,swap,triggers | AD6: null | AE6: none known | AG6: {"amortisation": null, "triggers": null} | AH6: null | AJ6: no
A7: ES0377992005 | B7: TDAC 5 A | C7: TDA CAM 5, FTA | D7: ES | E7: Titulizacion de Activos SGFT | F7: 44860 | G7: 44860 | H7: 44952 | I7: 52530 | J7: 1944000000 | K7: 210064000 | M7: 0.0012 | Z7: 0.1 | AC7: History 8 IPDs to 2022-10-26; gate INCOMPLETE; model NO_RELIABLE_MODEL (THIN_HISTORY); CONFIG_INCOMPLETE: fees,swap; pool/WAC/sched. principal not in the filings held | AD7: {"months": [1, 4, 7, 10], "day": 26, "convention": "following", "calendar": "TARGET"} | AE7: none known | AF7: 0.0 from 2016-01-01 to 2022-04-30 | AG7: {"amortisation": {"mode": "sequential", "note": "A then B"}, "triggers": {"note": "sequential; no pro-rata"}} | AH7: {"note": "non-amortising reserve fund (Moody's)"} | AJ7: no | AK7: fees; swap; first_ipd; reserve size
A8: ES0377993029 | B8: TDAC 6 A3 | C8: TDA CAM 6, FTA | D8: ES | E8: Titulizacion de Activos SGFT | I8: 52715 | AC8: History 0 IPDs; gate NO_HISTORY; model NO_RELIABLE_MODEL; CONFIG_INCOMPLETE: clean_up_call_pct,coupon_floor,fees,margin_bp,notes,original_balance,reserve,swap,triggers | AD8: {"months": [1, 4, 7, 10], "day": 28, "convention": "following", "calendar": "TARGET", "inferred": "from legal final 28-Apr-2044"} | AE8: none known | AG8: {"amortisation": {"mode": "sequential", "note": "Moody's: sequential, non-amortising reserve; Fitch: sequential once pool < 10%"}, "triggers": null} | AH8: null | AJ8: no | AK8: amortisation: Moody's sequential vs Fitch pro-rata until pool < 10%; ipd_rule (inferred from legal final date); denomination
A9: ES0377994019 | B9: TDAC 7 A2 | C9: TDA CAM 7, FTA | D9: ES | E9: Titulizacion de Activos SGFT | I9: 54480 | AC9: History 0 IPDs; gate NO_HISTORY; model NO_RELIABLE_MODEL; CONFIG_INCOMPLETE: clean_up_call_pct,coupon_floor,fees,margin_bp,notes,original_balance,reserve,swap,triggers | AD9: {"months": [2, 5, 8, 11], "day": 26, "convention": "following", "calendar": "TARGET", "inferred": "from legal final 26-Feb-2049"} | AE9: none known | AG9: {"amortisation": {"mode": "sequential", "note": "A1/A2/A3 order per prospectus not yet read; Moody's: sequential"}, "triggers": null} | AH9: null | AJ9: no | AK9: ipd_rule (inferred); denomination; A2/A3 sequencing
A10: ES0377994027 | B10: TDAC 7 A3 | C10: TDA CAM 7, FTA | D10: ES | E10: Titulizacion de Activos SGFT | I10: 54480 | AC10: History 0 IPDs; gate NO_HISTORY; model NO_RELIABLE_MODEL; CONFIG_INCOMPLETE: clean_up_call_pct,coupon_floor,fees,margin_bp,notes,original_balance,reserve,swap,triggers | AD10: {"months": [2, 5, 8, 11], "day": 26, "convention": "following", "calendar": "TARGET", "inferred": "from legal final 26-Feb-2049"} | AE10: none known | AG10: {"amortisation": {"mode": "sequential", "note": "A1/A2/A3 order per prospectus not yet read; Moody's: sequential"}, "triggers": null} | AH10: null | AJ10: no | AK10: ipd_rule (inferred); denomination; A2/A3 sequencing
A11: ES0377966009 | B11: TDAC 8 A | C11: TDA CAM 8, FTA | D11: ES | E11: Titulizacion de Activos SGFT | F11: 44161 | G11: 44161 | H11: 44253 | I11: 54480 | J11: 1635400000 | AC11: History 2 IPDs to 2020-11-26; gate NO_HISTORY; model NO_RELIABLE_MODEL; CONFIG_INCOMPLETE: clean_up_call_pct,coupon_floor,fees,margin_bp,swap,triggers; pool/WAC/sched. principal not in the filings held | AD11: {"months": [2, 5, 8, 11], "day": 26, "convention": "following", "calendar": "TARGET"} | AE11: none known | AG11: {"amortisation": {"mode": "pro_rata_while_pool_factor_ge", "threshold": 0.1, "note": "now irreversibly sequential (Fitch Dec-2025)"}, "triggers": null} | AH11: {"observed": [{"date": "2020-11-26", "balance": 8500000}], "note": "at floor (Fitch Dec-2025)"} | AJ11: no | AK11: margin
A12: ES0377955010 | B12: TDAC 9 A2 | C12: TDA CAM 9, FTA | D12: ES | E12: Titulizacion de Activos SGFT | I12: 54906 | AC12: History 0 IPDs; gate NO_HISTORY; model NO_RELIABLE_MODEL; CONFIG_INCOMPLETE: clean_up_call_pct,coupon_floor,fees,margin_bp,notes,original_balance,triggers | AD12: {"months": [1, 4, 7, 10], "day": 28, "convention": "following", "calendar": "TARGET", "inferred": "from legal final 28-Apr-2050"} | AE12: none known | AG12: {"amortisation": {"mode": "sequential", "note": "B/C/D interest-deferral triggers breached (Fitch Dec-2025)"}, "triggers": null} | AH12: {"note": "at floor since Oct-2025"} | AJ12: no | AK12: ipd_rule (inferred); closing day
A13: ES0359091016 | B13: CAJAM 2006-1 A2 | C13: MADRID RMBS I, FTA | D13: ES | E13: Titulizacion de Activos SGFT | I13: 54596 | AC13: History 0 IPDs; gate NO_HISTORY; model NO_RELIABLE_MODEL; CONFIG_INCOMPLETE: clean_up_call_pct,coupon_floor,fees,margin_bp,notes,original_balance,swap,triggers | AD13: {"months": [3, 6, 9, 12], "day": 22, "convention": "following", "calendar": "TARGET", "inferred": "from legal final 22-Jun-2049"} | AE13: none known | AG13: {"amortisation": {"mode": "sequential", "note": "pro-rata condition not met (S&P 2022)"}, "triggers": null} | AH13: {"note": "fully depleted Mar-2013..Apr-2019; ~11% of target in 2022 (S&P)"} | AJ13: no | AK13: ipd_rule (inferred); margin (only AAA weighted 13.44bp seen)
A14: ES0380957003 | B14: UCI 15 A | C14: F.T.A. U.C.I. 15 | D14: ES | E14: Santander de Titulizacion SGFT | F14: 46191 | G14: 46191 | H14: 46283 | I14: 53314 | J14: 1340600000 | K14: 81800463 | L14: 1.0084e+08 | M14: 0.0014 | N14: 0.004508449 | O14: 0.02408 | P14: 180964103 | Q14: 1.43e+09 | R14: 0.0326 | S14: 1.87982e+08 | T14: 3481000 | U14: 0.0745 | V14: 0.089946168 | W14: 1 | X14: 1 | Y14: 0.02 | Z14: 0.1 | AA14: 36500 | AB14: 0 | AC14: History 3 IPDs to 2026-06-18; gate INCOMPLETE; model NO_RELIABLE_MODEL; CONFIG_INCOMPLETE: coupon_floor,fees,swap | AD14: {"months": [3, 6, 9, 12], "day": 18, "convention": "following", "calendar": "TARGET"} | AE14: none known | AG14: {"amortisation": {"mode": "pro_rata_unless_trigger", "note": "90d+ arrears trigger reached -> B and C not amortised"}, "triggers": {"arrears_90d_ratio_max": 0.02, "observed_2026_06": 0.0899}} | AH14: {"observed": [{"date": "2026-06-18", "balance": 11440000}]} | AI14: 2027-12-20 | AJ14: no | AK14: legal final: santandermedia asset 18-Dec-2045 vs original workbook 18-Dec-2048
A15: ES0338186010 | B15: UCI 16 A2 | C15: F.T.A. U.C.I. 16 | D15: ES | E15: Santander de Titulizacion SGFT | AC15: History 0 IPDs; gate NO_HISTORY; model NO_RELIABLE_MODEL; CONFIG_INCOMPLETE: amortisation,clean_up_call_pct,coupon_floor,denomination,fees,ipd_rule,legal_final,margin_bp,notes,original_balance,reserve,swap,triggers | AD15: null | AE15: none known | AG15: {"amortisation": null, "triggers": null} | AH15: null | AJ15: no | AK15: IPD 16-Sep-2026 announced on BME (HANDOFF) - months not confirmed
A16: ES0345672010 | B16: HIPO 11 A2 | C16: HIPOCAT 11, FTA | D16: ES | E16: Europea de Titulizacion | F16: 43753 | G16: 43753 | H16: 43845 | I16: 54803 | J16: 1083200000 | K16: 217021000 | M16: 0.0013 | Q16: 1.6e+09 | Z16: 0.1 | AC16: History 16 IPDs to 2019-10-15; gate INCOMPLETE; model NO_RELIABLE_MODEL; CONFIG_INCOMPLETE: coupon_floor,fees,swap; pool/WAC/sched. principal not in the filings held | AD16: {"months": [1, 4, 7, 10], "day": 15, "convention": "following", "calendar": "TARGET"} | AE16: none known | AG16: {"amortisation": {"mode": "pro_rata_if_conditions", "note": "A1/A2/A3 split by date-dependent rule; conditions in accounts trigger annex (reserve at required, arrears<1%, pool>10%, C>=8%)"}, "triggers": {"arrears_3m_ratio_max": 0.01, "pool_factor_min | AH16: {"required": 28000000, "observed": [{"date": "2016-12-31", "note": "Fondo de Reserva dotado 40.87 (EUR) vs requerido 28,000,000"}]} | AJ16: YES (set Inputs!G20 = paid/due) | AK16: printed IPDs 2015-16 fall on the 21st-23rd, 2018-19 on the 15th (see calendar_checks)
A17: ES0345721015 | B17: HIPO 9 A2a | C17: HIPOCAT 9, FTA | D17: ES | E17: Europea de Titulizacion | J17: 500000000 | AC17: History 0 IPDs; gate NO_HISTORY; model NO_RELIABLE_MODEL; CONFIG_INCOMPLETE: amortisation,clean_up_call_pct,coupon_floor,fees,legal_final,reserve,swap,triggers | AD17: {"months": [1, 4, 7, 10], "day": 15, "convention": "following", "calendar": "TARGET"} | AE17: none known | AG17: {"amortisation": null, "triggers": null} | AH17: null | AJ17: no | AK17: notes (inferred: original / 100,000)
A18: ES0345721023 | B18: HIPO 9 A2b | C18: HIPOCAT 9, FTA | D18: ES | E18: Europea de Titulizacion | J18: 236200000 | AC18: History 0 IPDs; gate NO_HISTORY; model NO_RELIABLE_MODEL; CONFIG_INCOMPLETE: amortisation,clean_up_call_pct,coupon_floor,fees,legal_final,reserve,swap,triggers | AD18: {"months": [1, 4, 7, 10], "day": 15, "convention": "following", "calendar": "TARGET"} | AE18: none known | AG18: {"amortisation": null, "triggers": null} | AH18: null | AJ18: no | AK18: notes (inferred: original / 100,000)

Sheet Curve
A1: EUR 3M forward curve by IPD (paste forwards in column C, decimal; e.g. from Bloomberg FWCV / S0045 forward rates)
A3: k | B3: IPD date | C3: Forward 3M (paste) | D3: Rate used
A4: 1 | B4: =Engine!C11 -> 46342 | D4: =IF(AND(Inputs!$G$18=1,C4<>""),C4,Inputs!$G$17) -> 0.02252
A5: 2 | B5: =Engine!C12 -> 46433 | D5: =IF(AND(Inputs!$G$18=1,C5<>""),C5,Inputs!$G$17) -> 0.02252
A6: 3 | B6: =Engine!C13 -> 46524 | D6: =IF(AND(Inputs!$G$18=1,C6<>""),C6,Inputs!$G$17) -> 0.02252
A7: 4 | B7: =Engine!C14 -> 46615 | D7: =IF(AND(Inputs!$G$18=1,C7<>""),C7,Inputs!$G$17) -> 0.02252
A8: 5 | B8: =Engine!C15 -> 46706 | D8: =IF(AND(Inputs!$G$18=1,C8<>""),C8,Inputs!$G$17) -> 0.02252
A9: 6 | B9: =Engine!C16 -> 46798 | D9: =IF(AND(Inputs!$G$18=1,C9<>""),C9,Inputs!$G$17) -> 0.02252
A10: 7 | B10: =Engine!C17 -> 46888 | D10: =IF(AND(Inputs!$G$18=1,C10<>""),C10,Inputs!$G$17) -> 0.02252
A11: 8 | B11: =Engine!C18 -> 46980 | D11: =IF(AND(Inputs!$G$18=1,C11<>""),C11,Inputs!$G$17) -> 0.02252
A12: 9 | B12: =Engine!C19 -> 47072 | D12: =IF(AND(Inputs!$G$18=1,C12<>""),C12,Inputs!$G$17) -> 0.02252
A13: 10 | B13: =Engine!C20 -> 47164 | D13: =IF(AND(Inputs!$G$18=1,C13<>""),C13,Inputs!$G$17) -> 0.02252
A14: 11 | B14: =Engine!C21 -> 47253 | D14: =IF(AND(Inputs!$G$18=1,C14<>""),C14,Inputs!$G$17) -> 0.02252
A15: 12 | B15: =Engine!C22 -> 47345 | D15: =IF(AND(Inputs!$G$18=1,C15<>""),C15,Inputs!$G$17) -> 0.02252
... A183: 180 | B183: =Engine!C190 -> 62687 | D183: =IF(AND(Inputs!$G$18=1,C183<>""),C183,Inputs!$G$17) -> 0.02252

Sheet Engine
A1: Projection engine — quarterly IPD step (row 10 = state after last reported IPD)
AN6: Newton on DM: row 7 = DM tried, row 8 = PV(€) = Σ CF·Π 1/(1+(index+DM)τ'), row 9 = next DM | AO6: iter 0 | AQ6: iter 1 | AS6: iter 2 | AU6: iter 3 | AW6: iter 4 | AY6: iter 5 | BA6: iter 6 | BC6: final | BG6: DM -10bp | BI6: DM +10bp
AO7: =IF(Inputs!$G$7="DM",Inputs!$G$9/10000,Inputs!$C$13) -> 0.0026 | AP7: =AO7+0.0001 -> 0.0027 | AQ7: =AO9 -> 0.0059134629 | AR7: =AQ7+0.0001 -> 0.0060134629 | AS7: =AQ9 -> 0.0059498126 | AT7: =AS7+0.0001 -> 0.0060498126 | AU7: =AS9 -> 0.0059498049 | AV7: =AU7+0.0001 -> 0.0060498049 | AW7: =AU9 -> 0.0059498049 | AX7: =AW7+0.0001 -> 0.0060498049 | AY7: =AW9 -> 0.0059498049 | AZ7: =AY7+0.0001 -> 0.0060498049 | BA7: =AY9 -> 0.0059498049 | BB7: =BA7+0.0001 -> 0.0060498049 | BC7: =BA9 -> 0.0059498049 | BD7: =BC7+0.0001 -> 0.0060498049 | BG7: =IF(Inputs!$G$7="DM",Inputs!$G$9/10000,BC9)-0.001 -> 0.0049498049 | BI7: =IF(Inputs!$G$7="DM",Inputs!$G$9/10000,BC9)+0.001 -> 0.0069498049
AO8: =SUMPRODUCT($AI$11:$AI$190,EXP(-AO11:AO190)) -> 1.111379e+08 | AP8: =SUMPRODUCT($AI$11:$AI$190,EXP(-AP11:AP190)) -> 1.1108775e+08 | AQ8: =SUMPRODUCT($AI$11:$AI$190,EXP(-AQ11:AQ190)) -> 1.0949413e+08 | AR8: =SUMPRODUCT($AI$11:$AI$190,EXP(-AR11:AR190)) -> 1.0944509e+08 | AS8: =SUMPRODUCT($AI$11:$AI$190,EXP(-AS11:AS190)) -> 1.094763e+08 | AT8: =SUMPRODUCT($AI$11:$AI$190,EXP(-AT11:AT190)) -> 1.0942727e+08 | AU8: =SUMPRODUCT($AI$11:$AI$190,EXP(-AU11:AU190)) -> 1.094763e+08 | AV8: =SUMPRODUCT($AI$11:$AI$190,EXP(-AV11:AV190)) -> 1.0942727e+08 | ... BD8: =SUMPRODUCT($AI$11:$AI$190,EXP(-BD11:BD190)) -> 1.0942727e+08 | BG8: =SUMPRODUCT($AI$11:$AI$190,EXP(-BG11:BG190)) -> 1.0996842e+08 | BI8: =SUMPRODUCT($AI$11:$AI$190,EXP(-BI11:BI190)) -> 1.0898748e+08
A9: k | B9: IPD unadj. | C9: IPD | D9: Live | E9: Last live | F9: τ (ACT/360) | G9: Index | H9: Pool beg. | I9: Defaults | J9: n remaining | K9: Scheduled | L9: Prepay | M9: Recoveries | N9: Interest coll. | O9: A beg. | P9: Sub beg. | Q9: Fees | R9: Int. A | S9: Int. Sub | T9: Excess spread | U9: PDL open | V9: PDL cure | W9: PDL close | X9: Principal avail. | Y9: Pro-rata test | Z9: Call cond. | AA9: Called | AB9: Call IPD | AC9: A share | AD9: Prin. A | AE9: Prin. Sub | AF9: Pool end | AG9: A end | AH9: Sub end | AI9: CF A | AJ9: t (yrs) | AK9: A factor end | AM9: τ' settle-adj. | AO9: =IFERROR(AO7-(AO8-Inputs!$G$27)*0.0001/(AP8-AO8),AO7) -> 0.0059134629 | AQ9: =IFERROR(AQ7-(AQ8-Inputs!$G$27)*0.0001/(AR8-AQ8),AQ7) -> 0.0059498126 | AS9: =IFERROR(AS7-(AS8-Inputs!$G$27)*0.0001/(AT8-AS8),AS7) -> 0.0059498049 | AU9: =IFERROR(AU7-(AU8-Inputs!$G$27)*0.0001/(AV8-AU8),AU7) -> 0.0059498049 | AW9: =IFERROR(AW7-(AW8-Inputs!$G$27)*0.0001/(AX8-AW8),AW7) -> 0.0059498049 | AY9: =IFERROR(AY7-(AY8-Inputs!$G$27)*0.0001/(AZ8-AY8),AY7) -> 0.0059498049 | BA9: =IFERROR(BA7-(BA8-Inputs!$G$27)*0.0001/(BB8-BA8),BA7) -> 0.0059498049 | BC9: =IFERROR(BC7-(BC8-Inputs!$G$27)*0.0001/(BD8-BC8),BC7) -> 0.0059498049 | BE9: Prin. A due | BF9: A shortfall c/f | BK9: XIRR date | BL9: XIRR cash
C10: =Inputs!$C$7 -> 46251 | D10: =TRUE() -> TRUE | W10: 0 | AA10: =FALSE() -> FALSE | AF10: =Inputs!$C$16 -> 1.1935638e+08 | AG10: =Inputs!$C$11 -> 1.1084507e+08 | AH10: =Inputs!$C$12 -> 8507872.5 | BF10: 0 | BK10: =Inputs!$G$6 -> 46289 | BL10: =-Inputs!$K$8/100*Inputs!$C$11 -> -1.094763e+08
A11: 1 | B11: =EDATE(Inputs!$C$8,3*(A11-1)) -> 46341 | C11: =WORKDAY(B11-1,1) -> 46342 | D11: =C11<=Inputs!$C$9 -> TRUE | E11: =AND(D11,NOT(D12)) -> FALSE | F11: =(C11-C10)/360 -> 0.25277778 | G11: =Inputs!$C$15 -> 0.02252 | H11: =AF10 -> 1.1935638e+08 | I11: =IF(D11,H11*Inputs!$G$22,0) -> 29850.291 | J11: =MAX(Inputs!$G$24-(A11-1),1) -> 45.59177 | K11: =IF(D11,MIN(H11-I11,IF(J11>1,(H11-I11)*Inputs!$G$23/((1+Inputs!$G$23)^J11-1),H11-I11)),0) -> 2182596 | L11: =IF(D11,(H11-I11-K11)*Inputs!$G$21,0) -> 1261972.2 | M11: =IF(A11>Inputs!$G$13,(1-Inputs!$G$12)*INDEX($I$11:$I$190,A11-Inputs!$G$13),0) -> 0 | N11: =IF(D11,(H11-I11)*Inputs!$G$23,0) -> 946856.01 | O11: =AG10 -> 1.1084507e+08 | P11: =AH10 -> 8507872.5 | Q11: =IF(AND(D11,O11+P11>0),Inputs!$C$25+Inputs!$C$26*H11/4,0) -> 129839.09 | R11: =O11*IF(Inputs!$G$19="",G11+Inputs!$C$13,MAX(Inputs!$G$19,G11+Inputs!$C$13))*F11 -> 703841.55 | S11: =P11*(G11+Inputs!$C$14)*F11 -> 63620.391 | T11: =N11+M11-Q11-R11-S11 -> 49554.971 | U11: =W10 -> 0 | V11: =MIN(U11+I11,MAX(T11,0)) -> 29850.291 | W11: =U11+I11-V11 -> 0 | X11: =K11+L11+V11+IF(E11,H11-I11-K11-L11,0) -> 3474418.4 | Y11: =AND(Inputs!$C$21=1,O11/Inputs!$C$10<=Inputs!$C$22,Inputs!$G$14<Inputs!$C$23,W11<1) -> TRUE | Z11: =OR(AND(Inputs!$G$15=1,H11/Inputs!$C$17<=Inputs!$C$24),AND(Inputs!$G$15=2,C11>=Inputs!$G$16)) -> FALSE | AA11: =OR(AA10,Z11) -> FALSE | AB11: =AND(Z11,NOT(AA10),D11,O11>0) -> FALSE | AC11: =IF(AND(Y11,NOT(E11),O11+P11>0),O11/(O11+P11),1) -> 0.92871669 | AD11: =IF(AB11,O11,IF(D11,MIN(O11,IF(E11,AC11*X11+BF10,BE11*Inputs!$G$20)),0)) -> 3226750.4 | AE11: =IF(AB11,P11,IF(D11,MAX(MIN(P11,X11-MIN(O11,AC11*X11)),0),0)) -> 247668.04 | AF11: =IF(OR(AB11,E11),0,MAX(H11-I11-K11-L11,0)) -> 1.1588196e+08 | AG11: =IF(E11,0,O11-AD11) -> 1.0761832e+08 | AH11: =IF(OR(AB11,E11),0,P11-AE11) -> 8260204.5 | AI11: =IF(D11,R11+AD11,0) -> 3930591.9 | AJ11: =(C11-Inputs!$G$6)/365 -> 0.14520548 | AK11: =AG11/Inputs!$C$10 -> 0.076122595 | AM11: =(C11-Inputs!$G$6)/360 -> 0.14722222 | AO11: =0+LN(1+($G11+AO$7)*$AM11) -> 0.0036914006 | AP11: =0+LN(1+($G11+AP$7)*$AM11) -> 0.0037060685 | AQ11: =0+LN(1+($G11+AQ$7)*$AM11) -> 0.0041773005 | AR11: =0+LN(1+($G11+AR$7)*$AM11) -> 0.0041919613 | AS11: =0+LN(1+($G11+AS$7)*$AM11) -> 0.0041826297 | AT11: =0+LN(1+($G11+AT$7)*$AM11) -> 0.0041972903 | AU11: =0+LN(1+($G11+AU$7)*$AM11) -> 0.0041826285 | AV11: =0+LN(1+($G11+AV$7)*$AM11) -> 0.0041972892 | ... BD11: =0+LN(1+($G11+BD$7)*$AM11) -> 0.0041972892 | BE11: =IF(AB11,O11,IF(D11,MIN(O11,AC11*X11+BF10),0)) -> 3226750.4 | BF11: =IF(OR(AB11,E11),0,BE11-AD11) -> 0 | BG11: =0+LN(1+($G11+BG$7)*$AM11) -> 0.0040360101 | BI11: =0+LN(1+($G11+BI$7)*$AM11) -> 0.0043292255 | BK11: =C11 -> 46342 | BL11: =AI11 -> 3930591.9
A12: 2 | B12: =EDATE(Inputs!$C$8,3*(A12-1)) -> 46433 | C12: =WORKDAY(B12-1,1) -> 46433 | D12: =C12<=Inputs!$C$9 -> TRUE | E12: =AND(D12,NOT(D13)) -> FALSE | F12: =(C12-C11)/360 -> 0.25277778 | G12: =Curve!D5 -> 0.02252 | H12: =AF11 -> 1.1588196e+08 | I12: =IF(D12,H12*Inputs!$G$22,0) -> 28981.361 | J12: =MAX(Inputs!$G$24-(A12-1),1) -> 44.59177 | K12: =IF(D12,MIN(H12-I12,IF(J12>1,(H12-I12)*Inputs!$G$23/((1+Inputs!$G$23)^J12-1),H12-I12)),0) -> 2175671.3 | L12: =IF(D12,(H12-I12-K12)*Inputs!$G$21,0) -> 1224626.8 | M12: =IF(A12>Inputs!$G$13,(1-Inputs!$G$12)*INDEX($I$11:$I$190,A12-Inputs!$G$13),0) -> 0 | N12: =IF(D12,(H12-I12)*Inputs!$G$23,0) -> 919293.4 | O12: =AG11 -> 1.0761832e+08 | P12: =AH11 -> 8260204.5 | Q12: =IF(AND(D12,O12+P12>0),Inputs!$C$25+Inputs!$C$26*H12/4,0) -> 128970.49 | R12: =O12*IF(Inputs!$G$19="",G12+Inputs!$C$13,MAX(Inputs!$G$19,G12+Inputs!$C$13))*F12 -> 683352.41 | S12: =P12*(G12+Inputs!$C$14)*F12 -> 61768.372 | T12: =N12+M12-Q12-R12-S12 -> 45202.126 | U12: =W11 -> 0 | V12: =MIN(U12+I12,MAX(T12,0)) -> 28981.361 | W12: =U12+I12-V12 -> 0 | X12: =K12+L12+V12+IF(E12,H12-I12-K12-L12,0) -> 3429279.4 | Y12: =AND(Inputs!$C$21=1,O12/Inputs!$C$10<=Inputs!$C$22,Inputs!$G$14<Inputs!$C$23,W12<1) -> TRUE | Z12: =OR(AND(Inputs!$G$15=1,H12/Inputs!$C$17<=Inputs!$C$24),AND(Inputs!$G$15=2,C12>=Inputs!$G$16)) -> FALSE | AA12: =OR(AA11,Z12) -> FALSE | AB12: =AND(Z12,NOT(AA11),D12,O12>0) -> FALSE | AC12: =IF(AND(Y12,NOT(E12),O12+P12>0),O12/(O12+P12),1) -> 0.92871669 | AD12: =IF(AB12,O12,IF(D12,MIN(O12,IF(E12,AC12*X12+BF11,BE12*Inputs!$G$20)),0)) -> 3184829.1 | AE12: =IF(AB12,P12,IF(D12,MAX(MIN(P12,X12-MIN(O12,AC12*X12)),0),0)) -> 244450.38 | AF12: =IF(OR(AB12,E12),0,MAX(H12-I12-K12-L12,0)) -> 1.1245268e+08 | AG12: =IF(E12,0,O12-AD12) -> 1.0443349e+08 | AH12: =IF(OR(AB12,E12),0,P12-AE12) -> 8015754.1 | AI12: =IF(D12,R12+AD12,0) -> 3868181.5 | AJ12: =(C12-Inputs!$G$6)/365 -> 0.39452055 | AK12: =AG12/Inputs!$C$10 -> 0.073869842 | AM12: =F12 -> 0.25277778 | AO12: =AO11+LN(1+($G12+AO$7)*$AM12) -> 0.010021103 | AP12: =AP11+LN(1+($G12+AP$7)*$AM12) -> 0.010060889 | AQ12: =AQ11+LN(1+($G12+AQ$7)*$AM12) -> 0.011338942 | AR12: =AR11+LN(1+($G12+AR$7)*$AM12) -> 0.0113787 | AS12: =AS11+LN(1+($G12+AS$7)*$AM12) -> 0.011353394 | AT12: =AT11+LN(1+($G12+AT$7)*$AM12) -> 0.011393152 | AU12: =AU11+LN(1+($G12+AU$7)*$AM12) -> 0.011353391 | AV12: =AV11+LN(1+($G12+AV$7)*$AM12) -> 0.011393149 | ... BD12: =BD11+LN(1+($G12+BD$7)*$AM12) -> 0.011393149 | BE12: =IF(AB12,O12,IF(D12,MIN(O12,AC12*X12+BF11),0)) -> 3184829.1 | BF12: =IF(OR(AB12,E12),0,BE12-AD12) -> 0 | BG12: =BG11+LN(1+($G12+BG$7)*$AM12) -> 0.010955769 | BI12: =BI11+LN(1+($G12+BI$7)*$AM12) -> 0.011750928 | BK12: =C12 -> 46433 | BL12: =AI12 -> 3868181.5
A13: 3 | B13: =EDATE(Inputs!$C$8,3*(A13-1)) -> 46522 | C13: =WORKDAY(B13-1,1) -> 46524 | D13: =C13<=Inputs!$C$9 -> TRUE | E13: =AND(D13,NOT(D14)) -> FALSE | F13: =(C13-C12)/360 -> 0.25277778 | G13: =Curve!D6 -> 0.02252 | H13: =AF12 -> 1.1245268e+08 | I13: =IF(D13,H13*Inputs!$G$22,0) -> 28123.719 | J13: =MAX(Inputs!$G$24-(A13-1),1) -> 43.59177 | K13: =IF(D13,MIN(H13-I13,IF(J13>1,(H13-I13)*Inputs!$G$23/((1+Inputs!$G$23)^J13-1),H13-I13)),0) -> 2168768.6 | L13: =IF(D13,(H13-I13-K13)*Inputs!$G$21,0) -> 1187767.3 | M13: =IF(A13>Inputs!$G$13,(1-Inputs!$G$12)*INDEX($I$11:$I$190,A13-Inputs!$G$13),0) -> 0 | N13: =IF(D13,(H13-I13)*Inputs!$G$23,0) -> 892088.87 | O13: =AG12 -> 1.0443349e+08 | P13: =AH12 -> 8015754.1 | Q13: =IF(AND(D13,O13+P13>0),Inputs!$C$25+Inputs!$C$26*H13/4,0) -> 128113.17 | R13: =O13*IF(Inputs!$G$19="",G13+Inputs!$C$13,MAX(Inputs!$G$19,G13+Inputs!$C$13))*F13 -> 663129.45 | S13: =P13*(G13+Inputs!$C$14)*F13 -> 59940.415 | T13: =N13+M13-Q13-R13-S13 -> 40905.833 | U13: =W12 -> 0 | V13: =MIN(U13+I13,MAX(T13,0)) -> 28123.719 | W13: =U13+I13-V13 -> 0 | X13: =K13+L13+V13+IF(E13,H13-I13-K13-L13,0) -> 3384659.6 | Y13: =AND(Inputs!$C$21=1,O13/Inputs!$C$10<=Inputs!$C$22,Inputs!$G$14<Inputs!$C$23,W13<1) -> TRUE | Z13: =OR(AND(Inputs!$G$15=1,H13/Inputs!$C$17<=Inputs!$C$24),AND(Inputs!$G$15=2,C13>=Inputs!$G$16)) -> FALSE | AA13: =OR(AA12,Z13) -> FALSE | AB13: =AND(Z13,NOT(AA12),D13,O13>0) -> FALSE | AC13: =IF(AND(Y13,NOT(E13),O13+P13>0),O13/(O13+P13),1) -> 0.92871669 | AD13: =IF(AB13,O13,IF(D13,MIN(O13,IF(E13,AC13*X13+BF12,BE13*Inputs!$G$20)),0)) -> 3143389.9 | AE13: =IF(AB13,P13,IF(D13,MAX(MIN(P13,X13-MIN(O13,AC13*X13)),0),0)) -> 241269.74 | AF13: =IF(OR(AB13,E13),0,MAX(H13-I13-K13-L13,0)) -> 1.0906802e+08 | AG13: =IF(E13,0,O13-AD13) -> 1.012901e+08 | AH13: =IF(OR(AB13,E13),0,P13-AE13) -> 7774484.3 | AI13: =IF(D13,R13+AD13,0) -> 3806519.4 | AJ13: =(C13-Inputs!$G$6)/365 -> 0.64383562 | AK13: =AG13/Inputs!$C$10 -> 0.071646401 | AM13: =F13 -> 0.25277778 | AO13: =AO12+LN(1+($G13+AO$7)*$AM13) -> 0.016350806 | AP13: =AP12+LN(1+($G13+AP$7)*$AM13) -> 0.01641571 | AQ13: =AQ12+LN(1+($G13+AQ$7)*$AM13) -> 0.018500584 | AR13: =AR12+LN(1+($G13+AR$7)*$AM13) -> 0.018565439 | AS13: =AS12+LN(1+($G13+AS$7)*$AM13) -> 0.018524159 | AT13: =AT12+LN(1+($G13+AT$7)*$AM13) -> 0.018589013 | AU13: =AU12+LN(1+($G13+AU$7)*$AM13) -> 0.018524154 | AV13: =AV12+LN(1+($G13+AV$7)*$AM13) -> 0.018589008 | ... BD13: =BD12+LN(1+($G13+BD$7)*$AM13) -> 0.018589008 | BE13: =IF(AB13,O13,IF(D13,MIN(O13,AC13*X13+BF12),0)) -> 3143389.9 | BF13: =IF(OR(AB13,E13),0,BE13-AD13) -> 0 | BG13: =BG12+LN(1+($G13+BG$7)*$AM13) -> 0.017875529 | BI13: =BI12+LN(1+($G13+BI$7)*$AM13) -> 0.019172631 | BK13: =C13 -> 46524 | BL13: =AI13 -> 3806519.4
A14: 4 | B14: =EDATE(Inputs!$C$8,3*(A14-1)) -> 46614 | C14: =WORKDAY(B14-1,1) -> 46615 | D14: =C14<=Inputs!$C$9 -> TRUE | E14: =AND(D14,NOT(D15)) -> FALSE | F14: =(C14-C13)/360 -> 0.25277778 | G14: =Curve!D7 -> 0.02252 | H14: =AF13 -> 1.0906802e+08 | I14: =IF(D14,H14*Inputs!$G$22,0) -> 27277.237 | J14: =MAX(Inputs!$G$24-(A14-1),1) -> 42.59177 | K14: =IF(D14,MIN(H14-I14,IF(J14>1,(H14-I14)*Inputs!$G$23/((1+Inputs!$G$23)^J14-1),H14-I14)),0) -> 2161887.8 | L14: =IF(D14,(H14-I14-K14)*Inputs!$G$21,0) -> 1151388.2 | M14: =IF(A14>Inputs!$G$13,(1-Inputs!$G$12)*INDEX($I$11:$I$190,A14-Inputs!$G$13),0) -> 0 | N14: =IF(D14,(H14-I14)*Inputs!$G$23,0) -> 865238.31 | O14: =AG13 -> 1.012901e+08 | P14: =AH13 -> 7774484.3 | Q14: =IF(AND(D14,O14+P14>0),Inputs!$C$25+Inputs!$C$26*H14/4,0) -> 127267.01 | R14: =O14*IF(Inputs!$G$19="",G14+Inputs!$C$13,MAX(Inputs!$G$19,G14+Inputs!$C$13))*F14 -> 643169.62 | S14: =P14*(G14+Inputs!$C$14)*F14 -> 58136.242 | T14: =N14+M14-Q14-R14-S14 -> 36665.441 | U14: =W13 -> 0 | V14: =MIN(U14+I14,MAX(T14,0)) -> 27277.237 | W14: =U14+I14-V14 -> 0 | X14: =K14+L14+V14+IF(E14,H14-I14-K14-L14,0) -> 3340553.2 | Y14: =AND(Inputs!$C$21=1,O14/Inputs!$C$10<=Inputs!$C$22,Inputs!$G$14<Inputs!$C$23,W14<1) -> TRUE | Z14: =OR(AND(Inputs!$G$15=1,H14/Inputs!$C$17<=Inputs!$C$24),AND(Inputs!$G$15=2,C14>=Inputs!$G$16)) -> FALSE | AA14: =OR(AA13,Z14) -> FALSE | AB14: =AND(Z14,NOT(AA13),D14,O14>0) -> FALSE | AC14: =IF(AND(Y14,NOT(E14),O14+P14>0),O14/(O14+P14),1) -> 0.92871669 | AD14: =IF(AB14,O14,IF(D14,MIN(O14,IF(E14,AC14*X14+BF13,BE14*Inputs!$G$20)),0)) -> 3102427.5 | AE14: =IF(AB14,P14,IF(D14,MAX(MIN(P14,X14-MIN(O14,AC14*X14)),0),0)) -> 238125.68 | AF14: =IF(OR(AB14,E14),0,MAX(H14-I14-K14-L14,0)) -> 1.0572747e+08 | AG14: =IF(E14,0,O14-AD14) -> 98187672 | AH14: =IF(OR(AB14,E14),0,P14-AE14) -> 7536358.7 | AI14: =IF(D14,R14+AD14,0) -> 3745597.2 | AJ14: =(C14-Inputs!$G$6)/365 -> 0.89315068 | AK14: =AG14/Inputs!$C$10 -> 0.069451934 | AM14: =F14 -> 0.25277778 | AO14: =AO13+LN(1+($G14+AO$7)*$AM14) -> 0.022680509 | AP14: =AP13+LN(1+($G14+AP$7)*$AM14) -> 0.022770531 | AQ14: =AQ13+LN(1+($G14+AQ$7)*$AM14) -> 0.025662226 | AR14: =AR13+LN(1+($G14+AR$7)*$AM14) -> 0.025752178 | AS14: =AS13+LN(1+($G14+AS$7)*$AM14) -> 0.025694923 | AT14: =AT13+LN(1+($G14+AT$7)*$AM14) -> 0.025784874 | AU14: =AU13+LN(1+($G14+AU$7)*$AM14) -> 0.025694916 | AV14: =AV13+LN(1+($G14+AV$7)*$AM14) -> 0.025784867 | ... BD14: =BD13+LN(1+($G14+BD$7)*$AM14) -> 0.025784867 | BE14: =IF(AB14,O14,IF(D14,MIN(O14,AC14*X14+BF13),0)) -> 3102427.5 | BF14: =IF(OR(AB14,E14),0,BE14-AD14) -> 0 | BG14: =BG13+LN(1+($G14+BG$7)*$AM14) -> 0.024795288 | BI14: =BI13+LN(1+($G14+BI$7)*$AM14) -> 0.026594334 | BK14: =C14 -> 46615 | BL14: =AI14 -> 3745597.2
A15: 5 | B15: =EDATE(Inputs!$C$8,3*(A15-1)) -> 46706 | C15: =WORKDAY(B15-1,1) -> 46706 | D15: =C15<=Inputs!$C$9 -> TRUE | E15: =AND(D15,NOT(D16)) -> FALSE | F15: =(C15-C14)/360 -> 0.25277778 | G15: =Curve!D8 -> 0.02252 | H15: =AF14 -> 1.0572747e+08 | I15: =IF(D15,H15*Inputs!$G$22,0) -> 26441.785 | J15: =MAX(Inputs!$G$24-(A15-1),1) -> 41.59177 | K15: =IF(D15,MIN(H15-I15,IF(J15>1,(H15-I15)*Inputs!$G$23/((1+Inputs!$G$23)^J15-1),H15-I15)),0) -> 2155028.8 | L15: =IF(D15,(H15-I15-K15)*Inputs!$G$21,0) -> 1115483.9 | M15: =IF(A15>Inputs!$G$13,(1-Inputs!$G$12)*INDEX($I$11:$I$190,A15-Inputs!$G$13),0) -> 0 | N15: =IF(D15,(H15-I15)*Inputs!$G$23,0) -> 838737.65 | O15: =AG14 -> 98187672 | P15: =AH14 -> 7536358.7 | Q15: =IF(AND(D15,O15+P15>0),Inputs!$C$25+Inputs!$C$26*H15/4,0) -> 126431.87 | R15: =O15*IF(Inputs!$G$19="",G15+Inputs!$C$13,MAX(Inputs!$G$19,G15+Inputs!$C$13))*F15 -> 623469.9 | S15: =P15*(G15+Inputs!$C$14)*F15 -> 56355.579 | T15: =N15+M15-Q15-R15-S15 -> 32480.307 | U15: =W14 -> 0 | V15: =MIN(U15+I15,MAX(T15,0)) -> 26441.785 | W15: =U15+I15-V15 -> 0 | X15: =K15+L15+V15+IF(E15,H15-I15-K15-L15,0) -> 3296954.5 | Y15: =AND(Inputs!$C$21=1,O15/Inputs!$C$10<=Inputs!$C$22,Inputs!$G$14<Inputs!$C$23,W15<1) -> TRUE | Z15: =OR(AND(Inputs!$G$15=1,H15/Inputs!$C$17<=Inputs!$C$24),AND(Inputs!$G$15=2,C15>=Inputs!$G$16)) -> FALSE | AA15: =OR(AA14,Z15) -> FALSE | AB15: =AND(Z15,NOT(AA14),D15,O15>0) -> FALSE | AC15: =IF(AND(Y15,NOT(E15),O15+P15>0),O15/(O15+P15),1) -> 0.92871669 | AD15: =IF(AB15,O15,IF(D15,MIN(O15,IF(E15,AC15*X15+BF14,BE15*Inputs!$G$20)),0)) -> 3061936.6 | AE15: =IF(AB15,P15,IF(D15,MAX(MIN(P15,X15-MIN(O15,AC15*X15)),0),0)) -> 235017.82 | AF15: =IF(OR(AB15,E15),0,MAX(H15-I15-K15-L15,0)) -> 1.0243051e+08 | AG15: =IF(E15,0,O15-AD15) -> 95125735 | AH15: =IF(OR(AB15,E15),0,P15-AE15) -> 7301340.8 | AI15: =IF(D15,R15+AD15,0) -> 3685406.5 | AJ15: =(C15-Inputs!$G$6)/365 -> 1.1424658 | AK15: =AG15/Inputs!$C$10 -> 0.067286108 | AM15: =F15 -> 0.25277778 | AO15: =AO14+LN(1+($G15+AO$7)*$AM15) -> 0.029010212 | AP15: =AP14+LN(1+($G15+AP$7)*$AM15) -> 0.029125352 | AQ15: =AQ14+LN(1+($G15+AQ$7)*$AM15) -> 0.032823867 | AR15: =AR14+LN(1+($G15+AR$7)*$AM15) -> 0.032938916 | AS15: =AS14+LN(1+($G15+AS$7)*$AM15) -> 0.032865688 | AT15: =AT14+LN(1+($G15+AT$7)*$AM15) -> 0.032980736 | AU15: =AU14+LN(1+($G15+AU$7)*$AM15) -> 0.032865679 | AV15: =AV14+LN(1+($G15+AV$7)*$AM15) -> 0.032980727 | ... BD15: =BD14+LN(1+($G15+BD$7)*$AM15) -> 0.032980727 | BE15: =IF(AB15,O15,IF(D15,MIN(O15,AC15*X15+BF14),0)) -> 3061936.6 | BF15: =IF(OR(AB15,E15),0,BE15-AD15) -> 0 | BG15: =BG14+LN(1+($G15+BG$7)*$AM15) -> 0.031715048 | BI15: =BI14+LN(1+($G15+BI$7)*$AM15) -> 0.034016036 | BK15: =C15 -> 46706 | BL15: =AI15 -> 3685406.5
A16: 6 | B16: =EDATE(Inputs!$C$8,3*(A16-1)) -> 46798 | C16: =WORKDAY(B16-1,1) -> 46798 | D16: =C16<=Inputs!$C$9 -> TRUE | E16: =AND(D16,NOT(D17)) -> FALSE | F16: =(C16-C15)/360 -> 0.25555556 | G16: =Curve!D9 -> 0.02252 | H16: =AF15 -> 1.0243051e+08 | I16: =IF(D16,H16*Inputs!$G$22,0) -> 25617.237 | J16: =MAX(Inputs!$G$24-(A16-1),1) -> 40.59177 | K16: =IF(D16,MIN(H16-I16,IF(J16>1,(H16-I16)*Inputs!$G$23/((1+Inputs!$G$23)^J16-1),H16-I16)),0) -> 2148191.6 | L16: =IF(D16,(H16-I16-K16)*Inputs!$G$21,0) -> 1080048.9 | M16: =IF(A16>Inputs!$G$13,(1-Inputs!$G$12)*INDEX($I$11:$I$190,A16-Inputs!$G$13),0) -> 0 | N16: =IF(D16,(H16-I16)*Inputs!$G$23,0) -> 812582.86 | O16: =AG15 -> 95125735 | P16: =AH15 -> 7301340.8 | Q16: =IF(AND(D16,O16+P16>0),Inputs!$C$25+Inputs!$C$26*H16/4,0) -> 125607.63 | R16: =O16*IF(Inputs!$G$19="",G16+Inputs!$C$13,MAX(Inputs!$G$19,G16+Inputs!$C$13))*F16 -> 610664.94 | S16: =P16*(G16+Inputs!$C$14)*F16 -> 55198.137 | T16: =N16+M16-Q16-R16-S16 -> 21112.152 | U16: =W15 -> 0 | V16: =MIN(U16+I16,MAX(T16,0)) -> 21112.152 | W16: =U16+I16-V16 -> 4505.0847 | X16: =K16+L16+V16+IF(E16,H16-I16-K16-L16,0) -> 3249352.6 | Y16: =AND(Inputs!$C$21=1,O16/Inputs!$C$10<=Inputs!$C$22,Inputs!$G$14<Inputs!$C$23,W16<1) -> FALSE | Z16: =OR(AND(Inputs!$G$15=1,H16/Inputs!$C$17<=Inputs!$C$24),AND(Inputs!$G$15=2,C16>=Inputs!$G$16)) -> FALSE | AA16: =OR(AA15,Z16) -> FALSE | AB16: =AND(Z16,NOT(AA15),D16,O16>0) -> FALSE | AC16: =IF(AND(Y16,NOT(E16),O16+P16>0),O16/(O16+P16),1) -> 1 | AD16: =IF(AB16,O16,IF(D16,MIN(O16,IF(E16,AC16*X16+BF15,BE16*Inputs!$G$20)),0)) -> 3249352.6 | AE16: =IF(AB16,P16,IF(D16,MAX(MIN(P16,X16-MIN(O16,AC16*X16)),0),0)) -> 0 | AF16: =IF(OR(AB16,E16),0,MAX(H16-I16-K16-L16,0)) -> 99176657 | AG16: =IF(E16,0,O16-AD16) -> 91876383 | AH16: =IF(OR(AB16,E16),0,P16-AE16) -> 7301340.8 | AI16: =IF(D16,R16+AD16,0) -> 3860017.5 | AJ16: =(C16-Inputs!$G$6)/365 -> 1.3945205 | AK16: =AG16/Inputs!$C$10 -> 0.064987715 | AM16: =F16 -> 0.25555556 | AO16: =AO15+LN(1+($G16+AO$7)*$AM16) -> 0.03540925 | AP16: =AP15+LN(1+($G16+AP$7)*$AM16) -> 0.035549782 | AQ16: =AQ15+LN(1+($G16+AQ$7)*$AM16) -> 0.040063924 | AR16: =AR15+LN(1+($G16+AR$7)*$AM16) -> 0.040204344 | AS16: =AS15+LN(1+($G16+AS$7)*$AM16) -> 0.040114967 | AT16: =AT15+LN(1+($G16+AT$7)*$AM16) -> 0.040255385 | AU16: =AU15+LN(1+($G16+AU$7)*$AM16) -> 0.040114956 | AV16: =AV15+LN(1+($G16+AV$7)*$AM16) -> 0.040255375 | ... BD16: =BD15+LN(1+($G16+BD$7)*$AM16) -> 0.040255375 | BE16: =IF(AB16,O16,IF(D16,MIN(O16,AC16*X16+BF15),0)) -> 3249352.6 | BF16: =IF(OR(AB16,E16),0,BE16-AD16) -> 0 | BG16: =BG15+LN(1+($G16+BG$7)*$AM16) -> 0.038710583 | BI16: =BI15+LN(1+($G16+BI$7)*$AM16) -> 0.041518991 | BK16: =C16 -> 46798 | BL16: =AI16 -> 3860017.5
A17: 7 | B17: =EDATE(Inputs!$C$8,3*(A17-1)) -> 46888 | C17: =WORKDAY(B17-1,1) -> 46888 | D17: =C17<=Inputs!$C$9 -> TRUE | E17: =AND(D17,NOT(D18)) -> FALSE | F17: =(C17-C16)/360 -> 0.25 | G17: =Curve!D10 -> 0.02252 | H17: =AF16 -> 99176657 | I17: =IF(D17,H17*Inputs!$G$22,0) -> 24803.467 | J17: =MAX(Inputs!$G$24-(A17-1),1) -> 39.59177 | K17: =IF(D17,MIN(H17-I17,IF(J17>1,(H17-I17)*Inputs!$G$23/((1+Inputs!$G$23)^J17-1),H17-I17)),0) -> 2141376.1 | L17: =IF(D17,(H17-I17-K17)*Inputs!$G$21,0) -> 1045077.8 | M17: =IF(A17>Inputs!$G$13,(1-Inputs!$G$12)*INDEX($I$11:$I$190,A17-Inputs!$G$13),0) -> 0 | N17: =IF(D17,(H17-I17)*Inputs!$G$23,0) -> 786769.96 | O17: =AG16 -> 91876383 | P17: =AH16 -> 7301340.8 | Q17: =IF(AND(D17,O17+P17>0),Inputs!$C$25+Inputs!$C$26*H17/4,0) -> 124794.16 | R17: =O17*IF(Inputs!$G$19="",G17+Inputs!$C$13,MAX(Inputs!$G$19,G17+Inputs!$C$13))*F17 -> 576983.68 | S17: =P17*(G17+Inputs!$C$14)*F17 -> 53998.177 | T17: =N17+M17-Q17-R17-S17 -> 30993.932 | U17: =W16 -> 4505.0847 | V17: =MIN(U17+I17,MAX(T17,0)) -> 29308.552 | W17: =U17+I17-V17 -> 0 | X17: =K17+L17+V17+IF(E17,H17-I17-K17-L17,0) -> 3215762.4 | Y17: =AND(Inputs!$C$21=1,O17/Inputs!$C$10<=Inputs!$C$22,Inputs!$G$14<Inputs!$C$23,W17<1) -> TRUE | Z17: =OR(AND(Inputs!$G$15=1,H17/Inputs!$C$17<=Inputs!$C$24),AND(Inputs!$G$15=2,C17>=Inputs!$G$16)) -> FALSE | AA17: =OR(AA16,Z17) -> FALSE | AB17: =AND(Z17,NOT(AA16),D17,O17>0) -> FALSE | AC17: =IF(AND(Y17,NOT(E17),O17+P17>0),O17/(O17+P17),1) -> 0.92638124 | AD17: =IF(AB17,O17,IF(D17,MIN(O17,IF(E17,AC17*X17+BF16,BE17*Inputs!$G$20)),0)) -> 2979022 | AE17: =IF(AB17,P17,IF(D17,MAX(MIN(P17,X17-MIN(O17,AC17*X17)),0),0)) -> 236740.43 | AF17: =IF(OR(AB17,E17),0,MAX(H17-I17-K17-L17,0)) -> 95965399 | AG17: =IF(E17,0,O17-AD17) -> 88897361 | AH17: =IF(OR(AB17,E17),0,P17-AE17) -> 7064600.4 | AI17: =IF(D17,R17+AD17,0) -> 3556005.7 | AJ17: =(C17-Inputs!$G$6)/365 -> 1.6410959 | AK17: =AG17/Inputs!$C$10 -> 0.062880538 | AM17: =F17 -> 0.25 | AO17: =AO16+LN(1+($G17+AO$7)*$AM17) -> 0.041669613 | AP17: =AP16+LN(1+($G17+AP$7)*$AM17) -> 0.041834989 | AQ17: =AQ16+LN(1+($G17+AQ$7)*$AM17) -> 0.047147144 | AR17: =AR16+LN(1+($G17+AR$7)*$AM17) -> 0.047312388 | AS17: =AS16+LN(1+($G17+AS$7)*$AM17) -> 0.04720721 | AT17: =AT16+LN(1+($G17+AT$7)*$AM17) -> 0.047372452 | AU17: =AU16+LN(1+($G17+AU$7)*$AM17) -> 0.047207198 | AV17: =AV16+LN(1+($G17+AV$7)*$AM17) -> 0.047372439 | ... BD17: =BD16+LN(1+($G17+BD$7)*$AM17) -> 0.047372439 | BE17: =IF(AB17,O17,IF(D17,MIN(O17,AC17*X17+BF16),0)) -> 2979022 | BF17: =IF(OR(AB17,E17),0,BE17-AD17) -> 0 | BG17: =BG16+LN(1+($G17+BG$7)*$AM17) -> 0.045554561 | BI17: =BI16+LN(1+($G17+BI$7)*$AM17) -> 0.048859435 | BK17: =C17 -> 46888 | BL17: =AI17 -> 3556005.7
A18: 8 | B18: =EDATE(Inputs!$C$8,3*(A18-1)) -> 46980 | C18: =WORKDAY(B18-1,1) -> 46980 | D18: =C18<=Inputs!$C$9 -> TRUE | E18: =AND(D18,NOT(D19)) -> FALSE | F18: =(C18-C17)/360 -> 0.25555556 | G18: =Curve!D11 -> 0.02252 | H18: =AF17 -> 95965399 | I18: =IF(D18,H18*Inputs!$G$22,0) -> 24000.352 | J18: =MAX(Inputs!$G$24-(A18-1),1) -> 38.59177 | K18: =IF(D18,MIN(H18-I18,IF(J18>1,(H18-I18)*Inputs!$G$23/((1+Inputs!$G$23)^J18-1),H18-I18)),0) -> 2134582.2 | L18: =IF(D18,(H18-I18-K18)*Inputs!$G$21,0) -> 1010565.3 | M18: =IF(A18>Inputs!$G$13,(1-Inputs!$G$12)*INDEX($I$11:$I$190,A18-Inputs!$G$13),0) -> 0 | N18: =IF(D18,(H18-I18)*Inputs!$G$23,0) -> 761295 | O18: =AG17 -> 88897361 | P18: =AH17 -> 7064600.4 | Q18: =IF(AND(D18,O18+P18>0),Inputs!$C$25+Inputs!$C$26*H18/4,0) -> 123991.35 | R18: =O18*IF(Inputs!$G$19="",G18+Inputs!$C$13,MAX(Inputs!$G$19,G18+Inputs!$C$13))*F18 -> 570681.55 | S18: =P18*(G18+Inputs!$C$14)*F18 -> 53408.379 | T18: =N18+M18-Q18-R18-S18 -> 13213.728 | U18: =W17 -> 0 | V18: =MIN(U18+I18,MAX(T18,0)) -> 13213.728 | W18: =U18+I18-V18 -> 10786.624 | X18: =K18+L18+V18+IF(E18,H18-I18-K18-L18,0) -> 3158361.2 | Y18: =AND(Inputs!$C$21=1,O18/Inputs!$C$10<=Inputs!$C$22,Inputs!$G$14<Inputs!$C$23,W18<1) -> FALSE | Z18: =OR(AND(Inputs!$G$15=1,H18/Inputs!$C$17<=Inputs!$C$24),AND(Inputs!$G$15=2,C18>=Inputs!$G$16)) -> FALSE | AA18: =OR(AA17,Z18) -> FALSE | AB18: =AND(Z18,NOT(AA17),D18,O18>0) -> FALSE | AC18: =IF(AND(Y18,NOT(E18),O18+P18>0),O18/(O18+P18),1) -> 1 | AD18: =IF(AB18,O18,IF(D18,MIN(O18,IF(E18,AC18*X18+BF17,BE18*Inputs!$G$20)),0)) -> 3158361.2 | AE18: =IF(AB18,P18,IF(D18,MAX(MIN(P18,X18-MIN(O18,AC18*X18)),0),0)) -> 0 | AF18: =IF(OR(AB18,E18),0,MAX(H18-I18-K18-L18,0)) -> 92796252 | AG18: =IF(E18,0,O18-AD18) -> 85738999 | AH18: =IF(OR(AB18,E18),0,P18-AE18) -> 7064600.4 | AI18: =IF(D18,R18+AD18,0) -> 3729042.7 | AJ18: =(C18-Inputs!$G$6)/365 -> 1.8931507 | AK18: =AG18/Inputs!$C$10 -> 0.060646507 | AM18: =F18 -> 0.25555556 | AO18: =AO17+LN(1+($G18+AO$7)*$AM18) -> 0.048068651 | AP18: =AP17+LN(1+($G18+AP$7)*$AM18) -> 0.048259419 | AQ18: =AQ17+LN(1+($G18+AQ$7)*$AM18) -> 0.054387201 | AR18: =AR17+LN(1+($G18+AR$7)*$AM18) -> 0.054577815 | AS18: =AS17+LN(1+($G18+AS$7)*$AM18) -> 0.05445649 | AT18: =AT17+LN(1+($G18+AT$7)*$AM18) -> 0.054647102 | AU18: =AU17+LN(1+($G18+AU$7)*$AM18) -> 0.054456475 | AV18: =AV17+LN(1+($G18+AV$7)*$AM18) -> 0.054647087 | ... BD18: =BD17+LN(1+($G18+BD$7)*$AM18) -> 0.054647087 | BE18: =IF(AB18,O18,IF(D18,MIN(O18,AC18*X18+BF17),0)) -> 3158361.2 | BF18: =IF(OR(AB18,E18),0,BE18-AD18) -> 0 | BG18: =BG17+LN(1+($G18+BG$7)*$AM18) -> 0.052550096 | BI18: =BI17+LN(1+($G18+BI$7)*$AM18) -> 0.05636239 | BK18: =C18 -> 46980 | BL18: =AI18 -> 3729042.7
A19: 9 | B19: =EDATE(Inputs!$C$8,3*(A19-1)) -> 47072 | C19: =WORKDAY(B19-1,1) -> 47072 | D19: =C19<=Inputs!$C$9 -> TRUE | E19: =AND(D19,NOT(D20)) -> FALSE | F19: =(C19-C18)/360 -> 0.25555556 | G19: =Curve!D12 -> 0.02252 | H19: =AF18 -> 92796252 | I19: =IF(D19,H19*Inputs!$G$22,0) -> 23207.768 | J19: =MAX(Inputs!$G$24-(A19-1),1) -> 37.59177 | K19: =IF(D19,MIN(H19-I19,IF(J19>1,(H19-I19)*Inputs!$G$23/((1+Inputs!$G$23)^J19-1),H19-I19)),0) -> 2127809.8 | L19: =IF(D19,(H19-I19-K19)*Inputs!$G$21,0) -> 976506.07 | M19: =IF(A19>Inputs!$G$13,(1-Inputs!$G$12)*INDEX($I$11:$I$190,A19-Inputs!$G$13),0) -> 23880.233 | N19: =IF(D19,(H19-I19)*Inputs!$G$23,0) -> 736154.1 | O19: =AG18 -> 85738999 | P19: =AH18 -> 7064600.4 | Q19: =IF(AND(D19,O19+P19>0),Inputs!$C$25+Inputs!$C$26*H19/4,0) -> 123199.06 | R19: =O19*IF(Inputs!$G$19="",G19+Inputs!$C$13,MAX(Inputs!$G$19,G19+Inputs!$C$13))*F19 -> 550406.27 | S19: =P19*(G19+Inputs!$C$14)*F19 -> 53408.379 | T19: =N19+M19-Q19-R19-S19 -> 33020.624 | U19: =W18 -> 10786.624 | V19: =MIN(U19+I19,MAX(T19,0)) -> 33020.624 | W19: =U19+I19-V19 -> 973.76764 | X19: =K19+L19+V19+IF(E19,H19-I19-K19-L19,0) -> 3137336.5 | Y19: =AND(Inputs!$C$21=1,O19/Inputs!$C$10<=Inputs!$C$22,Inputs!$G$14<Inputs!$C$23,W19<1) -> FALSE | Z19: =OR(AND(Inputs!$G$15=1,H19/Inputs!$C$17<=Inputs!$C$24),AND(Inputs!$G$15=2,C19>=Inputs!$G$16)) -> FALSE | AA19: =OR(AA18,Z19) -> FALSE | AB19: =AND(Z19,NOT(AA18),D19,O19>0) -> FALSE | AC19: =IF(AND(Y19,NOT(E19),O19+P19>0),O19/(O19+P19),1) -> 1 | AD19: =IF(AB19,O19,IF(D19,MIN(O19,IF(E19,AC19*X19+BF18,BE19*Inputs!$G$20)),0)) -> 3137336.5 | AE19: =IF(AB19,P19,IF(D19,MAX(MIN(P19,X19-MIN(O19,AC19*X19)),0),0)) -> 0 | AF19: =IF(OR(AB19,E19),0,MAX(H19-I19-K19-L19,0)) -> 89668728 | AG19: =IF(E19,0,O19-AD19) -> 82601663 | AH19: =IF(OR(AB19,E19),0,P19-AE19) -> 7064600.4 | AI19: =IF(D19,R19+AD19,0) -> 3687742.8 | AJ19: =(C19-Inputs!$G$6)/365 -> 2.1452055 | AK19: =AG19/Inputs!$C$10 -> 0.058427348 | AM19: =F19 -> 0.25555556 | AO19: =AO18+LN(1+($G19+AO$7)*$AM19) -> 0.054467689 | AP19: =AP18+LN(1+($G19+AP$7)*$AM19) -> 0.054683849 | AQ19: =AQ18+LN(1+($G19+AQ$7)*$AM19) -> 0.061627258 | AR19: =AR18+LN(1+($G19+AR$7)*$AM19) -> 0.061843243 | AS19: =AS18+LN(1+($G19+AS$7)*$AM19) -> 0.061705769 | AT19: =AT18+LN(1+($G19+AT$7)*$AM19) -> 0.061921752 | AU19: =AU18+LN(1+($G19+AU$7)*$AM19) -> 0.061705752 | AV19: =AV18+LN(1+($G19+AV$7)*$AM19) -> 0.061921735 | ... BD19: =BD18+LN(1+($G19+BD$7)*$AM19) -> 0.061921735 | BE19: =IF(AB19,O19,IF(D19,MIN(O19,AC19*X19+BF18),0)) -> 3137336.5 | BF19: =IF(OR(AB19,E19),0,BE19-AD19) -> 0 | BG19: =BG18+LN(1+($G19+BG$7)*$AM19) -> 0.059545631 | BI19: =BI18+LN(1+($G19+BI$7)*$AM19) -> 0.063865344 | BK19: =C19 -> 47072 | BL19: =AI19 -> 3687742.8
A20: 10 | B20: =EDATE(Inputs!$C$8,3*(A20-1)) -> 47164 | C20: =WORKDAY(B20-1,1) -> 47164 | D20: =C20<=Inputs!$C$9 -> TRUE | E20: =AND(D20,NOT(D21)) -> FALSE | F20: =(C20-C19)/360 -> 0.25555556 | G20: =Curve!D13 -> 0.02252 | H20: =AF19 -> 89668728 | I20: =IF(D20,H20*Inputs!$G$22,0) -> 22425.593 | J20: =MAX(Inputs!$G$24-(A20-1),1) -> 36.59177 | K20: =IF(D20,MIN(H20-I20,IF(J20>1,(H20-I20)*Inputs!$G$23/((1+Inputs!$G$23)^J20-1),H20-I20)),0) -> 2121059 | L20: =IF(D20,(H20-I20-K20)*Inputs!$G$21,0) -> 942894.92 | M20: =IF(A20>Inputs!$G$13,(1-Inputs!$G$12)*INDEX($I$11:$I$190,A20-Inputs!$G$13),0) -> 23185.088 | N20: =IF(D20,(H20-I20)*Inputs!$G$23,0) -> 711343.41 | O20: =AG19 -> 82601663 | P20: =AH19 -> 7064600.4 | Q20: =IF(AND(D20,O20+P20>0),Inputs!$C$25+Inputs!$C$26*H20/4,0) -> 122417.18 | R20: =O20*IF(Inputs!$G$19="",G20+Inputs!$C$13,MAX(Inputs!$G$19,G20+Inputs!$C$13))*F20 -> 530265.96 | S20: =P20*(G20+Inputs!$C$14)*F20 -> 53408.379 | T20: =N20+M20-Q20-R20-S20 -> 28436.973 | U20: =W19 -> 973.76764 | V20: =MIN(U20+I20,MAX(T20,0)) -> 23399.361 | W20: =U20+I20-V20 -> 0 | X20: =K20+L20+V20+IF(E20,H20-I20-K20-L20,0) -> 3087353.3 | Y20: =AND(Inputs!$C$21=1,O20/Inputs!$C$10<=Inputs!$C$22,Inputs!$G$14<Inputs!$C$23,W20<1) -> TRUE | Z20: =OR(AND(Inputs!$G$15=1,H20/Inputs!$C$17<=Inputs!$C$24),AND(Inputs!$G$15=2,C20>=Inputs!$G$16)) -> FALSE | AA20: =OR(AA19,Z20) -> FALSE | AB20: =AND(Z20,NOT(AA19),D20,O20>0) -> FALSE | AC20: =IF(AND(Y20,NOT(E20),O20+P20>0),O20/(O20+P20),1) -> 0.92121228 | AD20: =IF(AB20,O20,IF(D20,MIN(O20,IF(E20,AC20*X20+BF19,BE20*Inputs!$G$20)),0)) -> 2844107.7 | AE20: =IF(AB20,P20,IF(D20,MAX(MIN(P20,X20-MIN(O20,AC20*X20)),0),0)) -> 243245.52 | AF20: =IF(OR(AB20,E20),0,MAX(H20-I20-K20-L20,0)) -> 86582349 | AG20: =IF(E20,0,O20-AD20) -> 79757555 | AH20: =IF(OR(AB20,E20),0,P20-AE20) -> 6821354.9 | AI20: =IF(D20,R20+AD20,0) -> 3374373.7 | AJ20: =(C20-Inputs!$G$6)/365 -> 2.3972603 | AK20: =AG20/Inputs!$C$10 -> 0.056415601 | AM20: =F20 -> 0.25555556 | AO20: =AO19+LN(1+($G20+AO$7)*$AM20) -> 0.060866727 | AP20: =AP19+LN(1+($G20+AP$7)*$AM20) -> 0.061108279 | AQ20: =AQ19+LN(1+($G20+AQ$7)*$AM20) -> 0.068867315 | AR20: =AR19+LN(1+($G20+AR$7)*$AM20) -> 0.069108671 | AS20: =AS19+LN(1+($G20+AS$7)*$AM20) -> 0.068955048 | AT20: =AT19+LN(1+($G20+AT$7)*$AM20) -> 0.069196401 | AU20: =AU19+LN(1+($G20+AU$7)*$AM20) -> 0.068955029 | AV20: =AV19+LN(1+($G20+AV$7)*$AM20) -> 0.069196383 | ... BD20: =BD19+LN(1+($G20+BD$7)*$AM20) -> 0.069196383 | BE20: =IF(AB20,O20,IF(D20,MIN(O20,AC20*X20+BF19),0)) -> 2844107.7 | BF20: =IF(OR(AB20,E20),0,BE20-AD20) -> 0 | BG20: =BG19+LN(1+($G20+BG$7)*$AM20) -> 0.066541167 | BI20: =BI19+LN(1+($G20+BI$7)*$AM20) -> 0.071368299 | BK20: =C20 -> 47164 | BL20: =AI20 -> 3374373.7
A21: 11 | B21: =EDATE(Inputs!$C$8,3*(A21-1)) -> 47253 | C21: =WORKDAY(B21-1,1) -> 47253 | D21: =C21<=Inputs!$C$9 -> TRUE | E21: =AND(D21,NOT(D22)) -> FALSE | F21: =(C21-C20)/360 -> 0.24722222 | G21: =Curve!D14 -> 0.02252 | H21: =AF20 -> 86582349 | I21: =IF(D21,H21*Inputs!$G$22,0) -> 21653.709 | J21: =MAX(Inputs!$G$24-(A21-1),1) -> 35.59177 | K21: =IF(D21,MIN(H21-I21,IF(J21>1,(H21-I21)*Inputs!$G$23/((1+Inputs!$G$23)^J21-1),H21-I21)),0) -> 2114329.5 | L21: =IF(D21,(H21-I21-K21)*Inputs!$G$21,0) -> 909726.68 | M21: =IF(A21>Inputs!$G$13,(1-Inputs!$G$12)*INDEX($I$11:$I$190,A21-Inputs!$G$13),0) -> 22498.975 | N21: =IF(D21,(H21-I21)*Inputs!$G$23,0) -> 686859.11 | O21: =AG20 -> 79757555 | P21: =AH20 -> 6821354.9 | Q21: =IF(AND(D21,O21+P21>0),Inputs!$C$25+Inputs!$C$26*H21/4,0) -> 121645.59 | R21: =O21*IF(Inputs!$G$19="",G21+Inputs!$C$13,MAX(Inputs!$G$19,G21+Inputs!$C$13))*F21 -> 495312.14 | S21: =P21*(G21+Inputs!$C$14)*F21 -> 49887.831 | T21: =N21+M21-Q21-R21-S21 -> 42512.529 | U21: =W20 -> 0 | V21: =MIN(U21+I21,MAX(T21,0)) -> 21653.709 | W21: =U21+I21-V21 -> 0 | X21: =K21+L21+V21+IF(E21,H21-I21-K21-L21,0) -> 3045709.9 | Y21: =AND(Inputs!$C$21=1,O21/Inputs!$C$10<=Inputs!$C$22,Inputs!$G$14<Inputs!$C$23,W21<1) -> TRUE | Z21: =OR(AND(Inputs!$G$15=1,H21/Inputs!$C$17<=Inputs!$C$24),AND(Inputs!$G$15=2,C21>=Inputs!$G$16)) -> FALSE | AA21: =OR(AA20,Z21) -> FALSE | AB21: =AND(Z21,NOT(AA20),D21,O21>0) -> FALSE | AC21: =IF(AND(Y21,NOT(E21),O21+P21>0),O21/(O21+P21),1) -> 0.92121228 | AD21: =IF(AB21,O21,IF(D21,MIN(O21,IF(E21,AC21*X21+BF20,BE21*Inputs!$G$20)),0)) -> 2805745.4 | AE21: =IF(AB21,P21,IF(D21,MAX(MIN(P21,X21-MIN(O21,AC21*X21)),0),0)) -> 239964.54 | AF21: =IF(OR(AB21,E21),0,MAX(H21-I21-K21-L21,0)) -> 83536639 | AG21: =IF(E21,0,O21-AD21) -> 76951810 | AH21: =IF(OR(AB21,E21),0,P21-AE21) -> 6581390.3 | AI21: =IF(D21,R21+AD21,0) -> 3301057.5 | AJ21: =(C21-Inputs!$G$6)/365 -> 2.6410959 | AK21: =AG21/Inputs!$C$10 -> 0.054430988 | AM21: =F21 -> 0.24722222 | AO21: =AO20+LN(1+($G21+AO$7)*$AM21) -> 0.067057745 | AP21: =AP20+LN(1+($G21+AP$7)*$AM21) -> 0.067323867 | AQ21: =AQ20+LN(1+($G21+AQ$7)*$AM21) -> 0.075872108 | AR21: =AR20+LN(1+($G21+AR$7)*$AM21) -> 0.076138013 | AS21: =AS20+LN(1+($G21+AS$7)*$AM21) -> 0.075968764 | AT21: =AT20+LN(1+($G21+AT$7)*$AM21) -> 0.076234667 | AU21: =AU20+LN(1+($G21+AU$7)*$AM21) -> 0.075968744 | AV21: =AV20+LN(1+($G21+AV$7)*$AM21) -> 0.076234647 | ... BD21: =BD20+LN(1+($G21+BD$7)*$AM21) -> 0.076234647 | BE21: =IF(AB21,O21,IF(D21,MIN(O21,AC21*X21+BF20),0)) -> 2805745.4 | BF21: =IF(OR(AB21,E21),0,BE21-AD21) -> 0 | BG21: =BG20+LN(1+($G21+BG$7)*$AM21) -> 0.073309357 | BI21: =BI20+LN(1+($G21+BI$7)*$AM21) -> 0.078627478 | BK21: =C21 -> 47253 | BL21: =AI21 -> 3301057.5
A22: 12 | B22: =EDATE(Inputs!$C$8,3*(A22-1)) -> 47345 | C22: =WORKDAY(B22-1,1) -> 47345 | D22: =C22<=Inputs!$C$9 -> TRUE | E22: =AND(D22,NOT(D23)) -> FALSE | F22: =(C22-C21)/360 -> 0.25555556 | G22: =Curve!D15 -> 0.02252 | H22: =AF21 -> 83536639 | I22: =IF(D22,H22*Inputs!$G$22,0) -> 20891.996 | J22: =MAX(Inputs!$G$24-(A22-1),1) -> 34.59177 | K22: =IF(D22,MIN(H22-I22,IF(J22>1,(H22-I22)*Inputs!$G$23/((1+Inputs!$G$23)^J22-1),H22-I22)),0) -> 2107621.4 | L22: =IF(D22,(H22-I22-K22)*Inputs!$G$21,0) -> 876996.22 | M22: =IF(A22>Inputs!$G$13,(1-Inputs!$G$12)*INDEX($I$11:$I$190,A22-Inputs!$G$13),0) -> 21821.789 | N22: =IF(D22,(H22-I22)*Inputs!$G$23,0) -> 662697.45 | O22: =AG21 -> 76951810 | P22: =AH21 -> 6581390.3 | Q22: =IF(AND(D22,O22+P22>0),Inputs!$C$25+Inputs!$C$26*H22/4,0) -> 120884.16 | R22: =O22*IF(Inputs!$G$19="",G22+Inputs!$C$13,MAX(Inputs!$G$19,G22+Inputs!$C$13))*F22 -> 493996.42 | S22: =P22*(G22+Inputs!$C$14)*F22 -> 49755.311 | T22: =N22+M22-Q22-R22-S22 -> 19883.35 | U22: =W21 -> 0 | V22: =MIN(U22+I22,MAX(T22,0)) -> 19883.35 | W22: =U22+I22-V22 -> 1008.646 | X22: =K22+L22+V22+IF(E22,H22-I22-K22-L22,0) -> 3004501 | Y22: =AND(Inputs!$C$21=1,O22/Inputs!$C$10<=Inputs!$C$22,Inputs!$G$14<Inputs!$C$23,W22<1) -> FALSE | Z22: =OR(AND(Inputs!$G$15=1,H22/Inputs!$C$17<=Inputs!$C$24),AND(Inputs!$G$15=2,C22>=Inputs!$G$16)) -> FALSE | AA22: =OR(AA21,Z22) -> FALSE | AB22: =AND(Z22,NOT(AA21),D22,O22>0) -> FALSE | AC22: =IF(AND(Y22,NOT(E22),O22+P22>0),O22/(O22+P22),1) -> 1 | AD22: =IF(AB22,O22,IF(D22,MIN(O22,IF(E22,AC22*X22+BF21,BE22*Inputs!$G$20)),0)) -> 3004501 | AE22: =IF(AB22,P22,IF(D22,MAX(MIN(P22,X22-MIN(O22,AC22*X22)),0),0)) -> 0 | AF22: =IF(OR(AB22,E22),0,MAX(H22-I22-K22-L22,0)) -> 80531129 | AG22: =IF(E22,0,O22-AD22) -> 73947309 | AH22: =IF(OR(AB22,E22),0,P22-AE22) -> 6581390.3 | AI22: =IF(D22,R22+AD22,0) -> 3498497.4 | AJ22: =(C22-Inputs!$G$6)/365 -> 2.8931507 | AK22: =AG22/Inputs!$C$10 -> 0.052305789 | AM22: =F22 -> 0.25555556 | AO22: =AO21+LN(1+($G22+AO$7)*$AM22) -> 0.073456783 | AP22: =AP21+LN(1+($G22+AP$7)*$AM22) -> 0.073748297 | AQ22: =AQ21+LN(1+($G22+AQ$7)*$AM22) -> 0.083112165 | AR22: =AR21+LN(1+($G22+AR$7)*$AM22) -> 0.083403441 | AS22: =AS21+LN(1+($G22+AS$7)*$AM22) -> 0.083218044 | AT22: =AT21+LN(1+($G22+AT$7)*$AM22) -> 0.083509317 | AU22: =AU21+LN(1+($G22+AU$7)*$AM22) -> 0.083218021 | AV22: =AV21+LN(1+($G22+AV$7)*$AM22) -> 0.083509294 | ... BD22: =BD21+LN(1+($G22+BD$7)*$AM22) -> 0.083509294 | BE22: =IF(AB22,O22,IF(D22,MIN(O22,AC22*X22+BF21),0)) -> 3004501 | BF22: =IF(OR(AB22,E22),0,BE22-AD22) -> 0 | BG22: =BG21+LN(1+($G22+BG$7)*$AM22) -> 0.080304892 | BI22: =BI21+LN(1+($G22+BI$7)*$AM22) -> 0.086130433 | BK22: =C22 -> 47345 | BL22: =AI22 -> 3498497.4
A23: 13 | B23: =EDATE(Inputs!$C$8,3*(A23-1)) -> 47437 | C23: =WORKDAY(B23-1,1) -> 47437 | D23: =C23<=Inputs!$C$9 -> TRUE | E23: =AND(D23,NOT(D24)) -> FALSE | F23: =(C23-C22)/360 -> 0.25555556 | G23: =Curve!D16 -> 0.02252 | H23: =AF22 -> 80531129 | I23: =IF(D23,H23*Inputs!$G$22,0) -> 20140.336 | J23: =MAX(Inputs!$G$24-(A23-1),1) -> 33.59177 | K23: =IF(D23,MIN(H23-I23,IF(J23>1,(H23-I23)*Inputs!$G$23/((1+Inputs!$G$23)^J23-1),H23-I23)),0) -> 2100934.6 | L23: =IF(D23,(H23-I23-K23)*Inputs!$G$21,0) -> 844698.5 | M23: =IF(A23>Inputs!$G$13,(1-Inputs!$G$12)*INDEX($I$11:$I$190,A23-Inputs!$G$13),0) -> 21153.428 | N23: =IF(D23,(H23-I23)*Inputs!$G$23,0) -> 638854.69 | O23: =AG22 -> 73947309 | P23: =AH22 -> 6581390.3 | Q23: =IF(AND(D23,O23+P23>0),Inputs!$C$25+Inputs!$C$26*H23/4,0) -> 120132.78 | R23: =O23*IF(Inputs!$G$19="",G23+Inputs!$C$13,MAX(Inputs!$G$19,G23+Inputs!$C$13))*F23 -> 474708.86 | S23: =P23*(G23+Inputs!$C$14)*F23 -> 49755.311 | T23: =N23+M23-Q23-R23-S23 -> 15411.172 | U23: =W22 -> 1008.646 | V23: =MIN(U23+I23,MAX(T23,0)) -> 15411.172 | W23: =U23+I23-V23 -> 5737.8102 | X23: =K23+L23+V23+IF(E23,H23-I23-K23-L23,0) -> 2961044.3 | Y23: =AND(Inputs!$C$21=1,O23/Inputs!$C$10<=Inputs!$C$22,Inputs!$G$14<Inputs!$C$23,W23<1) -> FALSE | Z23: =OR(AND(Inputs!$G$15=1,H23/Inputs!$C$17<=Inputs!$C$24),AND(Inputs!$G$15=2,C23>=Inputs!$G$16)) -> FALSE | AA23: =OR(AA22,Z23) -> FALSE | AB23: =AND(Z23,NOT(AA22),D23,O23>0) -> FALSE | AC23: =IF(AND(Y23,NOT(E23),O23+P23>0),O23/(O23+P23),1) -> 1 | AD23: =IF(AB23,O23,IF(D23,MIN(O23,IF(E23,AC23*X23+BF22,BE23*Inputs!$G$20)),0)) -> 2961044.3 | AE23: =IF(AB23,P23,IF(D23,MAX(MIN(P23,X23-MIN(O23,AC23*X23)),0),0)) -> 0 | AF23: =IF(OR(AB23,E23),0,MAX(H23-I23-K23-L23,0)) -> 77565355 | AG23: =IF(E23,0,O23-AD23) -> 70986264 | AH23: =IF(OR(AB23,E23),0,P23-AE23) -> 6581390.3 | AI23: =IF(D23,R23+AD23,0) -> 3435753.2 | AJ23: =(C23-Inputs!$G$6)/365 -> 3.1452055 | AK23: =AG23/Inputs!$C$10 -> 0.050211328 | AM23: =F23 -> 0.25555556 | AO23: =AO22+LN(1+($G23+AO$7)*$AM23) -> 0.079855821 | AP23: =AP22+LN(1+($G23+AP$7)*$AM23) -> 0.080172727 | AQ23: =AQ22+LN(1+($G23+AQ$7)*$AM23) -> 0.090352222 | AR23: =AR22+LN(1+($G23+AR$7)*$AM23) -> 0.090668868 | AS23: =AS22+LN(1+($G23+AS$7)*$AM23) -> 0.090467323 | AT23: =AT22+LN(1+($G23+AT$7)*$AM23) -> 0.090783967 | AU23: =AU22+LN(1+($G23+AU$7)*$AM23) -> 0.090467298 | AV23: =AV22+LN(1+($G23+AV$7)*$AM23) -> 0.090783942 | ... BD23: =BD22+LN(1+($G23+BD$7)*$AM23) -> 0.090783942 | BE23: =IF(AB23,O23,IF(D23,MIN(O23,AC23*X23+BF22),0)) -> 2961044.3 | BF23: =IF(OR(AB23,E23),0,BE23-AD23) -> 0 | BG23: =BG22+LN(1+($G23+BG$7)*$AM23) -> 0.087300428 | BI23: =BI22+LN(1+($G23+BI$7)*$AM23) -> 0.093633387 | BK23: =C23 -> 47437 | BL23: =AI23 -> 3435753.2
... A189: 179 | B189: =EDATE(Inputs!$C$8,3*(A189-1)) -> 62593 | C189: =WORKDAY(B189-1,1) -> 62593 | D189: =C189<=Inputs!$C$9 -> FALSE | E189: =AND(D189,NOT(D190)) -> FALSE | F189: =(C189-C188)/360 -> 0.24444444 | G189: =Curve!D182 -> 0.02252 | H189: =AF188 -> 0 | I189: =IF(D189,H189*Inputs!$G$22,0) -> 0 | J189: =MAX(Inputs!$G$24-(A189-1),1) -> 1 | K189: =IF(D189,MIN(H189-I189,IF(J189>1,(H189-I189)*Inputs!$G$23/((1+Inputs!$G$23)^J189-1),H189-I189)),0) -> 0 | L189: =IF(D189,(H189-I189-K189)*Inputs!$G$21,0) -> 0 | M189: =IF(A189>Inputs!$G$13,(1-Inputs!$G$12)*INDEX($I$11:$I$190,A189-Inputs!$G$13),0) -> 0 | N189: =IF(D189,(H189-I189)*Inputs!$G$23,0) -> 0 | O189: =AG188 -> 0 | P189: =AH188 -> 0 | Q189: =IF(AND(D189,O189+P189>0),Inputs!$C$25+Inputs!$C$26*H189/4,0) -> 0 | R189: =O189*IF(Inputs!$G$19="",G189+Inputs!$C$13,MAX(Inputs!$G$19,G189+Inputs!$C$13))*F189 -> 0 | S189: =P189*(G189+Inputs!$C$14)*F189 -> 0 | T189: =N189+M189-Q189-R189-S189 -> 0 | U189: =W188 -> 260422.42 | V189: =MIN(U189+I189,MAX(T189,0)) -> 0 | W189: =U189+I189-V189 -> 260422.42 | X189: =K189+L189+V189+IF(E189,H189-I189-K189-L189,0) -> 0 | Y189: =AND(Inputs!$C$21=1,O189/Inputs!$C$10<=Inputs!$C$22,Inputs!$G$14<Inputs!$C$23,W189<1) -> FALSE | Z189: =OR(AND(Inputs!$G$15=1,H189/Inputs!$C$17<=Inputs!$C$24),AND(Inputs!$G$15=2,C189>=Inputs!$G$16)) -> FALSE | AA189: =OR(AA188,Z189) -> FALSE | AB189: =AND(Z189,NOT(AA188),D189,O189>0) -> FALSE | AC189: =IF(AND(Y189,NOT(E189),O189+P189>0),O189/(O189+P189),1) -> 1 | AD189: =IF(AB189,O189,IF(D189,MIN(O189,IF(E189,AC189*X189+BF188,BE189*Inputs!$G$20)),0)) -> 0 | AE189: =IF(AB189,P189,IF(D189,MAX(MIN(P189,X189-MIN(O189,AC189*X189)),0),0)) -> 0 | AF189: =IF(OR(AB189,E189),0,MAX(H189-I189-K189-L189,0)) -> 0 | AG189: =IF(E189,0,O189-AD189) -> 0 | AH189: =IF(OR(AB189,E189),0,P189-AE189) -> 0 | AI189: =IF(D189,R189+AD189,0) -> 0 | AJ189: =(C189-Inputs!$G$6)/365 -> 44.668493 | AK189: =AG189/Inputs!$C$10 -> 0 | AM189: =F189 -> 0.24444444 | AO189: =AO188+LN(1+($G189+AO$7)*$AM189) -> 1.1340523 | AP189: =AP188+LN(1+($G189+AP$7)*$AM189) -> 1.1385525 | AQ189: =AQ188+LN(1+($G189+AQ$7)*$AM189) -> 1.2831043 | AR189: =AR188+LN(1+($G189+AR$7)*$AM189) -> 1.2876008 | AS189: =AS188+LN(1+($G189+AS$7)*$AM189) -> 1.2847388 | AT189: =AT188+LN(1+($G189+AT$7)*$AM189) -> 1.2892352 | AU189: =AU188+LN(1+($G189+AU$7)*$AM189) -> 1.2847384 | AV189: =AV188+LN(1+($G189+AV$7)*$AM189) -> 1.2892348 | ... BD189: =BD188+LN(1+($G189+BD$7)*$AM189) -> 1.2892348 | BE189: =IF(AB189,O189,IF(D189,MIN(O189,AC189*X189+BF188),0)) -> 0 | BF189: =IF(OR(AB189,E189),0,BE189-AD189) -> 0 | BG189: =BG188+LN(1+($G189+BG$7)*$AM189) -> 1.2397682 | BI189: =BI188+LN(1+($G189+BI$7)*$AM189) -> 1.3296974 | BK189: =C189 -> 62593 | BL189: =AI189 -> 0
A190: 180 | B190: =EDATE(Inputs!$C$8,3*(A190-1)) -> 62685 | C190: =WORKDAY(B190-1,1) -> 62687 | D190: =C190<=Inputs!$C$9 -> FALSE | E190: =D190 -> FALSE | F190: =(C190-C189)/360 -> 0.26111111 | G190: =Curve!D183 -> 0.02252 | H190: =AF189 -> 0 | I190: =IF(D190,H190*Inputs!$G$22,0) -> 0 | J190: =MAX(Inputs!$G$24-(A190-1),1) -> 1 | K190: =IF(D190,MIN(H190-I190,IF(J190>1,(H190-I190)*Inputs!$G$23/((1+Inputs!$G$23)^J190-1),H190-I190)),0) -> 0 | L190: =IF(D190,(H190-I190-K190)*Inputs!$G$21,0) -> 0 | M190: =IF(A190>Inputs!$G$13,(1-Inputs!$G$12)*INDEX($I$11:$I$190,A190-Inputs!$G$13),0) -> 0 | N190: =IF(D190,(H190-I190)*Inputs!$G$23,0) -> 0 | O190: =AG189 -> 0 | P190: =AH189 -> 0 | Q190: =IF(AND(D190,O190+P190>0),Inputs!$C$25+Inputs!$C$26*H190/4,0) -> 0 | R190: =O190*IF(Inputs!$G$19="",G190+Inputs!$C$13,MAX(Inputs!$G$19,G190+Inputs!$C$13))*F190 -> 0 | S190: =P190*(G190+Inputs!$C$14)*F190 -> 0 | T190: =N190+M190-Q190-R190-S190 -> 0 | U190: =W189 -> 260422.42 | V190: =MIN(U190+I190,MAX(T190,0)) -> 0 | W190: =U190+I190-V190 -> 260422.42 | X190: =K190+L190+V190+IF(E190,H190-I190-K190-L190,0) -> 0 | Y190: =AND(Inputs!$C$21=1,O190/Inputs!$C$10<=Inputs!$C$22,Inputs!$G$14<Inputs!$C$23,W190<1) -> FALSE | Z190: =OR(AND(Inputs!$G$15=1,H190/Inputs!$C$17<=Inputs!$C$24),AND(Inputs!$G$15=2,C190>=Inputs!$G$16)) -> FALSE | AA190: =OR(AA189,Z190) -> FALSE | AB190: =AND(Z190,NOT(AA189),D190,O190>0) -> FALSE | AC190: =IF(AND(Y190,NOT(E190),O190+P190>0),O190/(O190+P190),1) -> 1 | AD190: =IF(AB190,O190,IF(D190,MIN(O190,IF(E190,AC190*X190+BF189,BE190*Inputs!$G$20)),0)) -> 0 | AE190: =IF(AB190,P190,IF(D190,MAX(MIN(P190,X190-MIN(O190,AC190*X190)),0),0)) -> 0 | AF190: =IF(OR(AB190,E190),0,MAX(H190-I190-K190-L190,0)) -> 0 | AG190: =IF(E190,0,O190-AD190) -> 0 | AH190: =IF(OR(AB190,E190),0,P190-AE190) -> 0 | AI190: =IF(D190,R190+AD190,0) -> 0 | AJ190: =(C190-Inputs!$G$6)/365 -> 44.926027 | AK190: =AG190/Inputs!$C$10 -> 0 | AM190: =F190 -> 0.26111111 | AO190: =AO189+LN(1+($G190+AO$7)*$AM190) -> 1.14059 | AP190: =AP189+LN(1+($G190+AP$7)*$AM190) -> 1.1451162 | AQ190: =AQ189+LN(1+($G190+AQ$7)*$AM190) -> 1.2905012 | AR190: =AR189+LN(1+($G190+AR$7)*$AM190) -> 1.2950236 | AS190: =AS189+LN(1+($G190+AS$7)*$AM190) -> 1.2921451 | AT190: =AT189+LN(1+($G190+AT$7)*$AM190) -> 1.2966674 | AU190: =AU189+LN(1+($G190+AU$7)*$AM190) -> 1.2921447 | AV190: =AV189+LN(1+($G190+AV$7)*$AM190) -> 1.296667 | ... BD190: =BD189+LN(1+($G190+BD$7)*$AM190) -> 1.296667 | BE190: =IF(AB190,O190,IF(D190,MIN(O190,AC190*X190+BF189),0)) -> 0 | BF190: =IF(OR(AB190,E190),0,BE190-AD190) -> 0 | BG190: =BG189+LN(1+($G190+BG$7)*$AM190) -> 1.2469153 | BI190: =BI189+LN(1+($G190+BI$7)*$AM190) -> 1.3373628 | BK190: =C190 -> 62687 | BL190: =AI190 -> 0

Sheet History
A1: Issuer-reported payment history — every row of out/<ISIN>_<ticker>.csv (schema = rmbs_harvester.SCHEMA, refreshed by `python -m rmbs.workbook`). Columns AX.. are checks and Bloomberg paste/delta columns.
A3: isin | B3: deal | C3: tranche | D3: report_month | E3: payment_date | F3: accrual_start | G3: accrual_end | H3: accrual_days | I3: day_basis | J3: index_rate | K3: margin_bp | L3: coupon_rate | M3: original_balance | N3: beg_balance | O3: principal_paid | P3: end_balance | Q3: pool_factor | R3: interest_paid | S3: pdl_balance | T3: n_notes | U3: principal_per_note | V3: denom_beg | W3: denom_end | X3: coll_beg_balance | Y3: coll_sched_principal | Z3: coll_prepayments | AA3: coll_repurchases | AB3: coll_cpr_reported | AC3: coll_deemed_losses | AD3: coll_recoveries | AE3: coll_end_balance | AF3: coll_end_balance_net | AG3: wac | AH3: arrears_90_365 | AI3: cum_default_ratio | AJ3: prorata_test | AK3: reserve_balance | AL3: coll_principal_total | AM3: coll_cpr_12m | AN3: next_coupon_rate | AO3: next_index_rate | AP3: source_url | AQ3: source_section | AR3: parse_status | AS3: principal_due | AT3: principal_shortfall | AU3: sub_beg_balance | AV3: sub_end_balance | AW3: coll_beg_balance_net | AX3: chk: beg−prin−end | AY3: chk: factor | AZ3: chk: per-note×n − prin | BA3: chk: coupon − (index+margin) | BB3: chk: interest (rel.) | BC3: realised CPR (prepay only) | BD3: realised CPR (prepay+repurch.) | BE3: A share of collateral principal | BF3: BBG factor (paste) | BG3: Δ factor (issuer − BBG) | BH3: BBG principal (paste) | BI3: Δ principal (issuer − BBG) | BJ3: chk: due − paid − shortfall
A4: XS0222684655 | B4: Magellan Mortgages No. 3 | C4: A | D4: 2009-02 | E4: 39860 | F4: 39769 | G4: 39860 | H4: 91 | I4: Act/360 | J4: 0.04245 | K4: 13 | L4: 0.04375 | M4: 1413750000 | N4: 8.3210356e+08 | O4: 34219819 | P4: 7.9788374e+08 | Q4: 0.564374 | R4: 9202256.4 | S4: 0 | T4: 141375 | U4: 242.05 | V4: 5885.79 | W4: 5643.74 | X4: 9.0233403e+08 | Y4: 4199998.6 | Z4: 12534884 | AA4: 18607738 | AB4: 0.0558 | AC4: 2509441.6 | AD4: 356105.47 | AE4: 8.669914e+08 | AF4: 8.5847702e+08 | AG4: 0.0521898 | AH4: 22046043 | AI4: 0.0153 | AJ4: PASS | AK4: 13500000 | AP4: https://ind.millenniumbcp.pt/pt/Institucional/investidores/securitizacoes/Documents/Magellan3-InvestorReport/200902Magellan3_InvestorReport.pdf | AQ4: Sec.1/2/3/6 | AR4: ok: issuer report, 6 identities pass | AU4: 63870799 | AV4: 61244055 | AW4: 8.9597297e+08 | AX4: =IF(N4="","",N4-O4-P4) -> 0 | AY4: =IF(Q4="","",P4/M4-Q4) -> 0 | AZ4: =IF(U4="","",T4*U4-O4) -> 0 | BA4: =IF(L4="","",L4-(J4+K4/10000)) -> 0 | BB4: =IF(OR(R4="",R4=0,L4="",H4=""),"",N4*L4*H4/360/R4-1) -> -2.3346869e-10 | BC4: =IF(Z4="","",1-(1-Z4/(X4-Y4))^4) -> 0.05466846 | BD4: =IF(Z4="","",1-(1-(Z4+AA4)/(X4-Y4))^4) -> 0.13165049 | BE4: =IF(Y4="","",O4/(Y4+Z4+AA4)) -> 0.96823092 | BG4: =IF(BF4="","",Q4-BF4) | BI4: =IF(BH4="","",O4-BH4) | BJ4: =IF(AS4="","",AS4-O4-AT4)
A5: XS0222684655 | B5: Magellan Mortgages No. 3 | C5: A | D5: 2013-08 | E5: 41502 | F5: 41409 | G5: 41502 | H5: 93 | I5: Act/360 | J5: 0.00203 | K5: 26 | L5: 0.00463 | M5: 1413750000 | N5: 4.9980728e+08 | O5: 13915541 | P5: 4.8589174e+08 | Q5: 0.34369 | R5: 597811.16 | T5: 141375 | U5: 98.43 | V5: 3535.33 | W5: 3436.9 | X5: 5.6044392e+08 | AL5: 14433918 | AP5: https://ind.millenniumbcp.pt/pt/Institucional/investidores/securitizacoes/Documents/Magellan3-InvestorReport/201308Magellan3_InvestorReport.pdf | AQ5: Sec.1 Denomination / New Denomination / Accrual Rate; Sec.2 beginning balance & principal redemption | AR5: ok: issuer report Sec.1 (balances = denomination x 141,375; interest computed) | AX5: =IF(N5="","",N5-O5-P5) -> 0 | AY5: =IF(Q5="","",P5/M5-Q5) -> 0 | AZ5: =IF(U5="","",T5*U5-O5) -> 0 | BA5: =IF(L5="","",L5-(J5+K5/10000)) -> 0 | BB5: =IF(OR(R5="",R5=0,L5="",H5=""),"",N5*L5*H5/360/R5-1) -> -6.7051904e-09 | BC5: =IF(Z5="","",1-(1-Z5/(X5-Y5))^4) | BD5: =IF(Z5="","",1-(1-(Z5+AA5)/(X5-Y5))^4) | BE5: =IF(Y5="","",O5/(Y5+Z5+AA5)) | BG5: =IF(BF5="","",Q5-BF5) | BI5: =IF(BH5="","",O5-BH5) | BJ5: =IF(AS5="","",AS5-O5-AT5)
A6: XS0222684655 | B6: Magellan Mortgages No. 3 | C6: A | D6: 2017-08 | E6: 42963 | F6: 42870 | G6: 42963 | H6: 93 | I6: Act/360 | J6: -0.00329 | K6: 26 | L6: -0.00069 | M6: 1413750000 | N6: 354415815 | O6: 8742630 | P6: 345673185 | Q6: 0.244508 | R6: -63174.62 | T6: 141375 | U6: 61.84 | V6: 2506.92 | W6: 2445.08 | X6: 4.0371764e+08 | AL6: 10404855 | AP6: https://ind.millenniumbcp.pt/pt/Institucional/investidores/securitizacoes/Documents/Magellan3-InvestorReport/201708Magellan3_InvestorReport.pdf | AQ6: Sec.1 Denomination / New Denomination / Accrual Rate; Sec.2 beginning balance & principal redemption | AR6: ok: issuer report Sec.1 (balances = denomination x 141,375; interest computed) | AX6: =IF(N6="","",N6-O6-P6) -> 0 | AY6: =IF(Q6="","",P6/M6-Q6) -> 0 | AZ6: =IF(U6="","",T6*U6-O6) -> 0 | BA6: =IF(L6="","",L6-(J6+K6/10000)) -> 0 | BB6: =IF(OR(R6="",R6=0,L6="",H6=""),"",N6*L6*H6/360/R6-1) -> -1.5453199e-08 | BC6: =IF(Z6="","",1-(1-Z6/(X6-Y6))^4) | BD6: =IF(Z6="","",1-(1-(Z6+AA6)/(X6-Y6))^4) | BE6: =IF(Y6="","",O6/(Y6+Z6+AA6)) | BG6: =IF(BF6="","",Q6-BF6) | BI6: =IF(BH6="","",O6-BH6) | BJ6: =IF(AS6="","",AS6-O6-AT6)
A7: XS0222684655 | B7: Magellan Mortgages No. 3 | C7: A | D7: 2018-08 | E7: 43328 | F7: 43235 | G7: 43328 | H7: 93 | I7: Act/360 | J7: -0.00327 | K7: 26 | L7: 0 | M7: 1413750000 | N7: 3.1672807e+08 | O7: 9042345 | P7: 3.0768572e+08 | Q7: 0.217638 | R7: 0 | T7: 141375 | U7: 63.96 | V7: 2240.34 | W7: 2176.38 | X7: 3.5963557e+08 | AL7: 10397493 | AP7: https://ind.millenniumbcp.pt/pt/Institucional/investidores/securitizacoes/Documents/Magellan3-InvestorReport/201808Magellan3_InvestorReport.pdf | AQ7: Sec.1 Denomination / New Denomination / Accrual Rate; Sec.2 beginning balance & principal redemption | AR7: ok: issuer report Sec.1 (balances = denomination x 141,375; interest computed) | AX7: =IF(N7="","",N7-O7-P7) -> 0 | AY7: =IF(Q7="","",P7/M7-Q7) -> 0 | AZ7: =IF(U7="","",T7*U7-O7) -> 0 | BA7: =IF(L7="","",L7-(J7+K7/10000)) -> 0.00067 | BB7: =IF(OR(R7="",R7=0,L7="",H7=""),"",N7*L7*H7/360/R7-1) | BC7: =IF(Z7="","",1-(1-Z7/(X7-Y7))^4) | BD7: =IF(Z7="","",1-(1-(Z7+AA7)/(X7-Y7))^4) | BE7: =IF(Y7="","",O7/(Y7+Z7+AA7)) | BG7: =IF(BF7="","",Q7-BF7) | BI7: =IF(BH7="","",O7-BH7) | BJ7: =IF(AS7="","",AS7-O7-AT7)
A8: XS0222684655 | B8: Magellan Mortgages No. 3 | C8: A | D8: 2018-11 | E8: 43419 | F8: 43328 | G8: 43419 | H8: 91 | I8: Act/360 | J8: -0.00319 | K8: 26 | L8: 0 | M8: 1413750000 | N8: 3.0768572e+08 | O8: 8144613.8 | P8: 2.9954111e+08 | Q8: 0.211877 | R8: 0 | T8: 141375 | U8: 57.61 | V8: 2176.38 | W8: 2118.77 | X8: 3.4923808e+08 | AL8: 9239055.3 | AP8: https://ind.millenniumbcp.pt/pt/Institucional/investidores/securitizacoes/Documents/Magellan3-InvestorReport/201811Magellan3_InvestorReport.pdf | AQ8: Sec.1 Denomination / New Denomination / Accrual Rate; Sec.2 beginning balance & principal redemption | AR8: ok: issuer report Sec.1 (balances = denomination x 141,375; interest computed) | AX8: =IF(N8="","",N8-O8-P8) -> 0 | AY8: =IF(Q8="","",P8/M8-Q8) -> 0 | AZ8: =IF(U8="","",T8*U8-O8) -> 0 | BA8: =IF(L8="","",L8-(J8+K8/10000)) -> 0.00059 | BB8: =IF(OR(R8="",R8=0,L8="",H8=""),"",N8*L8*H8/360/R8-1) | BC8: =IF(Z8="","",1-(1-Z8/(X8-Y8))^4) | BD8: =IF(Z8="","",1-(1-(Z8+AA8)/(X8-Y8))^4) | BE8: =IF(Y8="","",O8/(Y8+Z8+AA8)) | BG8: =IF(BF8="","",Q8-BF8) | BI8: =IF(BH8="","",O8-BH8) | BJ8: =IF(AS8="","",AS8-O8-AT8)
A9: XS0222684655 | B9: Magellan Mortgages No. 3 | C9: A | D9: 2019-02 | E9: 43511 | F9: 43419 | G9: 43511 | H9: 92 | I9: Act/360 | J9: -0.00316 | K9: 26 | L9: 0 | M9: 1413750000 | N9: 2.9954111e+08 | O9: 8315677.5 | P9: 2.9122543e+08 | Q9: 0.205995 | R9: 0 | T9: 141375 | U9: 58.82 | V9: 2118.77 | W9: 2059.95 | X9: 3.3999902e+08 | AL9: 9846787.5 | AP9: https://ind.millenniumbcp.pt/pt/Institucional/investidores/securitizacoes/Documents/Magellan3-InvestorReport/Investor_Report_2019_02.pdf | AQ9: Sec.1 Denomination / New Denomination / Accrual Rate; Sec.2 beginning balance & principal redemption | AR9: ok: issuer report Sec.1 (balances = denomination x 141,375; interest computed) | AX9: =IF(N9="","",N9-O9-P9) -> 0 | AY9: =IF(Q9="","",P9/M9-Q9) -> 0 | AZ9: =IF(U9="","",T9*U9-O9) -> 0 | BA9: =IF(L9="","",L9-(J9+K9/10000)) -> 0.00056 | BB9: =IF(OR(R9="",R9=0,L9="",H9=""),"",N9*L9*H9/360/R9-1) | BC9: =IF(Z9="","",1-(1-Z9/(X9-Y9))^4) | BD9: =IF(Z9="","",1-(1-(Z9+AA9)/(X9-Y9))^4) | BE9: =IF(Y9="","",O9/(Y9+Z9+AA9)) | BG9: =IF(BF9="","",Q9-BF9) | BI9: =IF(BH9="","",O9-BH9) | BJ9: =IF(AS9="","",AS9-O9-AT9)
A10: XS0222684655 | B10: Magellan Mortgages No. 3 | C10: A | D10: 2019-05 | E10: 43600 | F10: 43511 | G10: 43600 | H10: 89 | I10: Act/360 | J10: -0.00308 | K10: 26 | L10: 0 | M10: 1413750000 | N10: 2.9122543e+08 | O10: 7970722.5 | P10: 2.8325471e+08 | Q10: 0.200357 | R10: 0 | T10: 141375 | U10: 56.38 | V10: 2059.95 | W10: 2003.57 | X10: 3.3015223e+08 | AL10: 9206191.7 | AP10: https://ind.millenniumbcp.pt/pt/Institucional/investidores/securitizacoes/Documents/Magellan3-InvestorReport/Investor_Report_16052019.pdf | AQ10: Sec.1 Denomination / New Denomination / Accrual Rate; Sec.2 beginning balance & principal redemption | AR10: ok: issuer report Sec.1 (balances = denomination x 141,375; interest computed) | AX10: =IF(N10="","",N10-O10-P10) -> 0 | AY10: =IF(Q10="","",P10/M10-Q10) -> 0 | AZ10: =IF(U10="","",T10*U10-O10) -> 0 | BA10: =IF(L10="","",L10-(J10+K10/10000)) -> 0.00048 | BB10: =IF(OR(R10="",R10=0,L10="",H10=""),"",N10*L10*H10/360/R10-1) | BC10: =IF(Z10="","",1-(1-Z10/(X10-Y10))^4) | BD10: =IF(Z10="","",1-(1-(Z10+AA10)/(X10-Y10))^4) | BE10: =IF(Y10="","",O10/(Y10+Z10+AA10)) | BG10: =IF(BF10="","",Q10-BF10) | BI10: =IF(BH10="","",O10-BH10) | BJ10: =IF(AS10="","",AS10-O10-AT10)
A11: XS0222684655 | B11: Magellan Mortgages No. 3 | C11: A | D11: 2019-08 | E11: 43693 | F11: 43600 | G11: 43693 | H11: 93 | I11: Act/360 | J11: -0.00311 | K11: 26 | L11: 0 | M11: 1413750000 | N11: 2.8325471e+08 | O11: 7441980 | P11: 2.7581273e+08 | Q11: 0.195093 | R11: 0 | T11: 141375 | U11: 52.64 | V11: 2003.57 | W11: 1950.93 | X11: 3.2094604e+08 | AL11: 8347958.2 | AP11: https://ind.millenniumbcp.pt/pt/Institucional/investidores/securitizacoes/Documents/Magellan3-InvestorReport/Investor_Report_2019_08.pdf | AQ11: Sec.1 Denomination / New Denomination / Accrual Rate; Sec.2 beginning balance & principal redemption | AR11: ok: issuer report Sec.1 (balances = denomination x 141,375; interest computed) | AX11: =IF(N11="","",N11-O11-P11) -> 0 | AY11: =IF(Q11="","",P11/M11-Q11) -> 0 | AZ11: =IF(U11="","",T11*U11-O11) -> 0 | BA11: =IF(L11="","",L11-(J11+K11/10000)) -> 0.00051 | BB11: =IF(OR(R11="",R11=0,L11="",H11=""),"",N11*L11*H11/360/R11-1) | BC11: =IF(Z11="","",1-(1-Z11/(X11-Y11))^4) | BD11: =IF(Z11="","",1-(1-(Z11+AA11)/(X11-Y11))^4) | BE11: =IF(Y11="","",O11/(Y11+Z11+AA11)) | BG11: =IF(BF11="","",Q11-BF11) | BI11: =IF(BH11="","",O11-BH11) | BJ11: =IF(AS11="","",AS11-O11-AT11)
A12: XS0222684655 | B12: Magellan Mortgages No. 3 | C12: A | D12: 2020-11 | E12: 44151 | F12: 44060 | G12: 44151 | H12: 91 | I12: Act/360 | J12: -0.00481 | K12: 26 | L12: 0 | M12: 1413750000 | N12: 2.4941802e+08 | O12: 5879786.2 | P12: 243538230 | Q12: 0.172264 | R12: 0 | T12: 141375 | U12: 41.59 | V12: 1764.23 | W12: 1722.64 | X12: 2.8195947e+08 | AL12: 6580273.8 | AP12: https://ind.millenniumbcp.pt/pt/Institucional/investidores/securitizacoes/Documents/Magellan3-InvestorReport/Investor_Report_2020_11_12112020.pdf | AQ12: Sec.1 Denomination / New Denomination / Accrual Rate; Sec.2 beginning balance & principal redemption | AR12: ok: issuer report Sec.1 (balances = denomination x 141,375; interest computed) | AX12: =IF(N12="","",N12-O12-P12) -> 0 | AY12: =IF(Q12="","",P12/M12-Q12) -> 0 | AZ12: =IF(U12="","",T12*U12-O12) -> 0 | BA12: =IF(L12="","",L12-(J12+K12/10000)) -> 0.00221 | BB12: =IF(OR(R12="",R12=0,L12="",H12=""),"",N12*L12*H12/360/R12-1) | BC12: =IF(Z12="","",1-(1-Z12/(X12-Y12))^4) | BD12: =IF(Z12="","",1-(1-(Z12+AA12)/(X12-Y12))^4) | BE12: =IF(Y12="","",O12/(Y12+Z12+AA12)) | BG12: =IF(BF12="","",Q12-BF12) | BI12: =IF(BH12="","",O12-BH12) | BJ12: =IF(AS12="","",AS12-O12-AT12)
A13: XS0222684655 | B13: Magellan Mortgages No. 3 | C13: A | D13: 2021-02 | E13: 44242 | F13: 44151 | G13: 44242 | H13: 91 | I13: Act/360 | J13: -0.00513 | K13: 26 | L13: 0 | M13: 1413750000 | N13: 243538230 | O13: 6942926.2 | P13: 2.365953e+08 | Q13: 0.167353 | R13: 0 | T13: 141375 | U13: 49.11 | V13: 1722.64 | W13: 1673.53 | X13: 2.753792e+08 | AL13: 8134725.3 | AP13: https://ind.millenniumbcp.pt/pt/Institucional/investidores/securitizacoes/Documents/Magellan3-InvestorReport/Investor_Report_15022021.pdf | AQ13: Sec.1 Denomination / New Denomination / Accrual Rate; Sec.2 beginning balance & principal redemption | AR13: ok: issuer report Sec.1 (balances = denomination x 141,375; interest computed) | AX13: =IF(N13="","",N13-O13-P13) -> 0 | AY13: =IF(Q13="","",P13/M13-Q13) -> 0 | AZ13: =IF(U13="","",T13*U13-O13) -> 0 | BA13: =IF(L13="","",L13-(J13+K13/10000)) -> 0.00253 | BB13: =IF(OR(R13="",R13=0,L13="",H13=""),"",N13*L13*H13/360/R13-1) | BC13: =IF(Z13="","",1-(1-Z13/(X13-Y13))^4) | BD13: =IF(Z13="","",1-(1-(Z13+AA13)/(X13-Y13))^4) | BE13: =IF(Y13="","",O13/(Y13+Z13+AA13)) | BG13: =IF(BF13="","",Q13-BF13) | BI13: =IF(BH13="","",O13-BH13) | BJ13: =IF(AS13="","",AS13-O13-AT13)
A14: XS0222684655 | B14: Magellan Mortgages No. 3 | C14: A | D14: 2022-05 | E14: 44697 | F14: 44607 | G14: 44697 | H14: 90 | I14: Act/360 | J14: -0.00523 | K14: 26 | L14: 0 | M14: 1413750000 | N14: 210903225 | O14: 5951887.5 | P14: 2.0495134e+08 | Q14: 0.14497 | R14: 0 | T14: 141375 | U14: 42.1 | V14: 1491.8 | W14: 1449.7 | X14: 2.3842492e+08 | AL14: 6770006.2 | AP14: https://ind.millenniumbcp.pt/pt/Institucional/investidores/securitizacoes/Documents/Magellan3-InvestorReport/InvestorReport_202205.pdf | AQ14: Sec.1 Denomination / New Denomination / Accrual Rate; Sec.2 beginning balance & principal redemption | AR14: ok: issuer report Sec.1 (balances = denomination x 141,375; interest computed) | AX14: =IF(N14="","",N14-O14-P14) -> 0 | AY14: =IF(Q14="","",P14/M14-Q14) -> 0 | AZ14: =IF(U14="","",T14*U14-O14) -> 0 | BA14: =IF(L14="","",L14-(J14+K14/10000)) -> 0.00263 | BB14: =IF(OR(R14="",R14=0,L14="",H14=""),"",N14*L14*H14/360/R14-1) | BC14: =IF(Z14="","",1-(1-Z14/(X14-Y14))^4) | BD14: =IF(Z14="","",1-(1-(Z14+AA14)/(X14-Y14))^4) | BE14: =IF(Y14="","",O14/(Y14+Z14+AA14)) | BG14: =IF(BF14="","",Q14-BF14) | BI14: =IF(BH14="","",O14-BH14) | BJ14: =IF(AS14="","",AS14-O14-AT14)
A15: XS0222684655 | B15: Magellan Mortgages No. 3 | C15: A | D15: 2023-05 | E15: 45061 | F15: 44972 | G15: 45061 | H15: 89 | I15: Act/360 | J15: 0.02654 | K15: 26 | L15: 0.02914 | M15: 1413750000 | N15: 1.8379174e+08 | O15: 7393912.5 | P15: 1.7639783e+08 | Q15: 0.124773 | R15: 1324045.9 | T15: 141375 | U15: 52.3 | V15: 1300.03 | W15: 1247.73 | X15: 2.0855501e+08 | AL15: 8123854.8 | AP15: https://ind.millenniumbcp.pt/pt/Institucional/investidores/securitizacoes/Documents/Magellan3-InvestorReport/InvestorReport_2023-05.pdf | AQ15: Sec.1 Denomination / New Denomination / Accrual Rate; Sec.2 beginning balance & principal redemption | AR15: ok: issuer report Sec.1 (balances = denomination x 141,375; interest computed) | AX15: =IF(N15="","",N15-O15-P15) -> 0 | AY15: =IF(Q15="","",P15/M15-Q15) -> 0 | AZ15: =IF(U15="","",T15*U15-O15) -> 0 | BA15: =IF(L15="","",L15-(J15+K15/10000)) -> 0 | BB15: =IF(OR(R15="",R15=0,L15="",H15=""),"",N15*L15*H15/360/R15-1) -> 3.4872596e-09 | BC15: =IF(Z15="","",1-(1-Z15/(X15-Y15))^4) | BD15: =IF(Z15="","",1-(1-(Z15+AA15)/(X15-Y15))^4) | BE15: =IF(Y15="","",O15/(Y15+Z15+AA15)) | BG15: =IF(BF15="","",Q15-BF15) | BI15: =IF(BH15="","",O15-BH15) | BJ15: =IF(AS15="","",AS15-O15-AT15)
A16: XS0222684655 | B16: Magellan Mortgages No. 3 | C16: A | D16: 2023-08 | E16: 45154 | F16: 45061 | G16: 45154 | I16: Act/360 | K16: 26 | M16: 1413750000 | N16: 1.7639783e+08 | O16: 5915130 | P16: 1.704827e+08 | Q16: 0.120589 | T16: 141375 | U16: 41.84 | V16: 1247.73 | W16: 1205.89 | AP16: derived: denomination chain between neighbouring reports | AQ16: denomination chain | AR16: DERIVED (principal exact; coupon not available) | AX16: =IF(N16="","",N16-O16-P16) -> 0 | AY16: =IF(Q16="","",P16/M16-Q16) -> 0 | AZ16: =IF(U16="","",T16*U16-O16) -> 0 | BA16: =IF(L16="","",L16-(J16+K16/10000)) | BB16: =IF(OR(R16="",R16=0,L16="",H16=""),"",N16*L16*H16/360/R16-1) | BC16: =IF(Z16="","",1-(1-Z16/(X16-Y16))^4) | BD16: =IF(Z16="","",1-(1-(Z16+AA16)/(X16-Y16))^4) | BE16: =IF(Y16="","",O16/(Y16+Z16+AA16)) | BG16: =IF(BF16="","",Q16-BF16) | BI16: =IF(BH16="","",O16-BH16) | BJ16: =IF(AS16="","",AS16-O16-AT16)
A17: XS0222684655 | B17: Magellan Mortgages No. 3 | C17: A | D17: 2023-11 | E17: 45245 | F17: 45154 | G17: 45245 | H17: 91 | I17: Act/360 | J17: 0.03781 | K17: 26 | L17: 0.04041 | M17: 1413750000 | N17: 1.704827e+08 | O17: 6275636.2 | P17: 1.6420706e+08 | Q17: 0.11615 | R17: 1741438.1 | T17: 141375 | U17: 44.39 | V17: 1205.89 | W17: 1161.5 | X17: 1.9391906e+08 | AL17: 6891967.8 | AP17: https://ind.millenniumbcp.pt/pt/Institucional/investidores/securitizacoes/Documents/Magellan3-InvestorReport/Magellan3_InvestorReport_202311.pdf | AQ17: Sec.1 Denomination / New Denomination / Accrual Rate; Sec.2 beginning balance & principal redemption | AR17: ok: issuer report Sec.1 (balances = denomination x 141,375; interest computed) | AX17: =IF(N17="","",N17-O17-P17) -> 0 | AY17: =IF(Q17="","",P17/M17-Q17) -> 0 | AZ17: =IF(U17="","",T17*U17-O17) -> 0 | BA17: =IF(L17="","",L17-(J17+K17/10000)) -> 0 | BB17: =IF(OR(R17="",R17=0,L17="",H17=""),"",N17*L17*H17/360/R17-1) -> -1.6902336e-09 | BC17: =IF(Z17="","",1-(1-Z17/(X17-Y17))^4) | BD17: =IF(Z17="","",1-(1-(Z17+AA17)/(X17-Y17))^4) | BE17: =IF(Y17="","",O17/(Y17+Z17+AA17)) | BG17: =IF(BF17="","",Q17-BF17) | BI17: =IF(BH17="","",O17-BH17) | BJ17: =IF(AS17="","",AS17-O17-AT17)
A18: XS0222684655 | B18: Magellan Mortgages No. 3 | C18: A | D18: 2024-02 | E18: 45337 | F18: 45245 | G18: 45337 | I18: Act/360 | K18: 26 | M18: 1413750000 | N18: 1.6420706e+08 | O18: 6429735 | P18: 1.5777733e+08 | Q18: 0.111602 | T18: 141375 | U18: 45.48 | V18: 1161.5 | W18: 1116.02 | AP18: derived: denomination chain between neighbouring reports | AQ18: denomination chain | AR18: DERIVED (principal exact; coupon not available) | AX18: =IF(N18="","",N18-O18-P18) -> 0 | AY18: =IF(Q18="","",P18/M18-Q18) -> 0 | AZ18: =IF(U18="","",T18*U18-O18) -> 0 | BA18: =IF(L18="","",L18-(J18+K18/10000)) | BB18: =IF(OR(R18="",R18=0,L18="",H18=""),"",N18*L18*H18/360/R18-1) | BC18: =IF(Z18="","",1-(1-Z18/(X18-Y18))^4) | BD18: =IF(Z18="","",1-(1-(Z18+AA18)/(X18-Y18))^4) | BE18: =IF(Y18="","",O18/(Y18+Z18+AA18)) | BG18: =IF(BF18="","",Q18-BF18) | BI18: =IF(BH18="","",O18-BH18) | BJ18: =IF(AS18="","",AS18-O18-AT18)
A19: XS0222684655 | B19: Magellan Mortgages No. 3 | C19: A | D19: 2024-05 | E19: 45427 | F19: 45337 | G19: 45427 | H19: 90 | I19: Act/360 | J19: 0.03912 | K19: 26 | L19: 0.04172 | M19: 1413750000 | N19: 1.5777733e+08 | O19: 5003261.2 | P19: 1.5277407e+08 | Q19: 0.108063 | R19: 1645617.5 | T19: 141375 | U19: 35.39 | V19: 1116.02 | W19: 1080.63 | X19: 1.8005011e+08 | AL19: 5555546.8 | AP19: https://ind.millenniumbcp.pt/pt/Institucional/investidores/securitizacoes/Documents/Magellan3-InvestorReport/InvestorReport_202405.pdf | AQ19: Sec.1 Denomination / New Denomination / Accrual Rate; Sec.2 beginning balance & principal redemption | AR19: ok: issuer report Sec.1 (balances = denomination x 141,375; interest computed) | AX19: =IF(N19="","",N19-O19-P19) -> 0 | AY19: =IF(Q19="","",P19/M19-Q19) -> 0 | AZ19: =IF(U19="","",T19*U19-O19) -> 0 | BA19: =IF(L19="","",L19-(J19+K19/10000)) -> 0 | BB19: =IF(OR(R19="",R19=0,L19="",H19=""),"",N19*L19*H19/360/R19-1) -> -2.5370416e-09 | BC19: =IF(Z19="","",1-(1-Z19/(X19-Y19))^4) | BD19: =IF(Z19="","",1-(1-(Z19+AA19)/(X19-Y19))^4) | BE19: =IF(Y19="","",O19/(Y19+Z19+AA19)) | BG19: =IF(BF19="","",Q19-BF19) | BI19: =IF(BH19="","",O19-BH19) | BJ19: =IF(AS19="","",AS19-O19-AT19)
A20: XS0222684655 | B20: Magellan Mortgages No. 3 | C20: A | D20: 2025-02 | E20: 45705 | F20: 45611 | G20: 45705 | H20: 94 | I20: Act/360 | J20: 0.03023 | K20: 26 | L20: 0.03283 | M20: 1413750000 | N20: 1.4319308e+08 | O20: 5684688.8 | P20: 1.3750839e+08 | Q20: 0.097265 | R20: 1227490.9 | T20: 141375 | U20: 40.21 | V20: 1012.86 | W20: 972.65 | X20: 1.6398539e+08 | AL20: 6203280.7 | AP20: https://ind.millenniumbcp.pt/pt/Institucional/investidores/securitizacoes/Documents/Magellan3-InvestorReport/InvestorReport_202502.pdf | AQ20: Sec.1 Denomination / New Denomination / Accrual Rate; Sec.2 beginning balance & principal redemption | AR20: ok: issuer report Sec.1 (balances = denomination x 141,375; interest computed) | AX20: =IF(N20="","",N20-O20-P20) -> 0 | AY20: =IF(Q20="","",P20/M20-Q20) -> 0 | AZ20: =IF(U20="","",T20*U20-O20) -> 0 | BA20: =IF(L20="","",L20-(J20+K20/10000)) -> 0 | BB20: =IF(OR(R20="",R20=0,L20="",H20=""),"",N20*L20*H20/360/R20-1) -> -7.7699147e-10 | BC20: =IF(Z20="","",1-(1-Z20/(X20-Y20))^4) | BD20: =IF(Z20="","",1-(1-(Z20+AA20)/(X20-Y20))^4) | BE20: =IF(Y20="","",O20/(Y20+Z20+AA20)) | BG20: =IF(BF20="","",Q20-BF20) | BI20: =IF(BH20="","",O20-BH20) | BJ20: =IF(AS20="","",AS20-O20-AT20)
A21: XS0222684655 | B21: Magellan Mortgages No. 3 | C21: A | D21: 2025-05 | E21: 45792 | F21: 45705 | G21: 45792 | I21: Act/360 | K21: 26 | M21: 1413750000 | N21: 1.3750839e+08 | O21: 5195531.2 | P21: 1.3231286e+08 | Q21: 0.09359 | T21: 141375 | U21: 36.75 | V21: 972.65 | W21: 935.9 | AP21: derived: denomination chain between neighbouring reports | AQ21: denomination chain | AR21: DERIVED (principal exact; coupon not available) | AX21: =IF(N21="","",N21-O21-P21) -> 0 | AY21: =IF(Q21="","",P21/M21-Q21) -> 0 | AZ21: =IF(U21="","",T21*U21-O21) -> 0 | BA21: =IF(L21="","",L21-(J21+K21/10000)) | BB21: =IF(OR(R21="",R21=0,L21="",H21=""),"",N21*L21*H21/360/R21-1) | BC21: =IF(Z21="","",1-(1-Z21/(X21-Y21))^4) | BD21: =IF(Z21="","",1-(1-(Z21+AA21)/(X21-Y21))^4) | BE21: =IF(Y21="","",O21/(Y21+Z21+AA21)) | BG21: =IF(BF21="","",Q21-BF21) | BI21: =IF(BH21="","",O21-BH21) | BJ21: =IF(AS21="","",AS21-O21-AT21)
A22: XS0222684655 | B22: Magellan Mortgages No. 3 | C22: A | D22: 2025-08 | E22: 45887 | F22: 45792 | G22: 45887 | H22: 95 | I22: Act/360 | J22: 0.02143 | K22: 26 | L22: 0.02403 | M22: 1413750000 | N22: 1.3231286e+08 | O22: 4686581.2 | P22: 1.2762628e+08 | Q22: 0.090275 | R22: 839028.94 | T22: 141375 | U22: 33.15 | V22: 935.9 | W22: 902.75 | X22: 1.518534e+08 | AL22: 5076114.6 | AP22: https://ind.millenniumbcp.pt/pt/Institucional/investidores/securitizacoes/Documents/Magellan3-InvestorReport/InvestorReport_202508.pdf | AQ22: Sec.1 Denomination / New Denomination / Accrual Rate; Sec.2 beginning balance & principal redemption | AR22: ok: issuer report Sec.1 (balances = denomination x 141,375; interest computed) | AX22: =IF(N22="","",N22-O22-P22) -> 0 | AY22: =IF(Q22="","",P22/M22-Q22) -> 0 | AZ22: =IF(U22="","",T22*U22-O22) -> 0 | BA22: =IF(L22="","",L22-(J22+K22/10000)) -> 0 | BB22: =IF(OR(R22="",R22=0,L22="",H22=""),"",N22*L22*H22/360/R22-1) -> -8.0077689e-10 | BC22: =IF(Z22="","",1-(1-Z22/(X22-Y22))^4) | BD22: =IF(Z22="","",1-(1-(Z22+AA22)/(X22-Y22))^4) | BE22: =IF(Y22="","",O22/(Y22+Z22+AA22)) | BG22: =IF(BF22="","",Q22-BF22) | BI22: =IF(BH22="","",O22-BH22) | BJ22: =IF(AS22="","",AS22-O22-AT22)
A23: XS0222684655 | B23: Magellan Mortgages No. 3 | C23: A | D23: 2025-11 | E23: 45978 | F23: 45887 | G23: 45978 | H23: 91 | I23: Act/360 | J23: 0.02036 | K23: 26 | L23: 0.02296 | M23: 1413750000 | N23: 1.2762628e+08 | O23: 4075841.2 | P23: 123550440 | Q23: 0.087392 | R23: 740714.57 | S23: 0 | T23: 141375 | U23: 28.83 | V23: 902.75 | W23: 873.92 | X23: 1.4677728e+08 | Y23: 2403945.5 | Z23: 1797131.6 | AA23: 278990.85 | AB23: 0.049 | AC23: 3297.38 | AD23: 95781.59 | AE23: 1.4229722e+08 | AF23: 1.3303703e+08 | AG23: 0.03078 | AH23: 385037.22 | AI23: 0.0056 | AJ23: PASS | AK23: 9000000 | AP23: https://ind.millenniumbcp.pt/pt/Institucional/investidores/securitizacoes/Documents/Magellan3-InvestorReport/Investor-Report-2025-11.pdf | AQ23: Sec.1/2/3/6 | AR23: ok: issuer report, 6 identities pass | AU23: 9795930 | AV23: 9483101.2 | AW23: 1.3742461e+08 | AX23: =IF(N23="","",N23-O23-P23) -> 0 | AY23: =IF(Q23="","",P23/M23-Q23) -> 0 | AZ23: =IF(U23="","",T23*U23-O23) -> 0 | BA23: =IF(L23="","",L23-(J23+K23/10000)) -> 0 | BB23: =IF(OR(R23="",R23=0,L23="",H23=""),"",N23*L23*H23/360/R23-1) -> 6.7221126e-09 | BC23: =IF(Z23="","",1-(1-Z23/(X23-Y23))^4) -> 0.048869236 | BD23: =IF(Z23="","",1-(1-(Z23+AA23)/(X23-Y23))^4) -> 0.056292043 | BE23: =IF(Y23="","",O23/(Y23+Z23+AA23)) -> 0.90977219 | BG23: =IF(BF23="","",Q23-BF23) | BI23: =IF(BH23="","",O23-BH23) | BJ23: =IF(AS23="","",AS23-O23-AT23)
A24: XS0222684655 | B24: Magellan Mortgages No. 3 | C24: A | D24: 2026-02 | E24: 46069 | F24: 45978 | G24: 46069 | H24: 91 | I24: Act/360 | K24: 26 | M24: 1413750000 | N24: 123550440 | O24: 5025881.2 | P24: 1.1852456e+08 | Q24: 0.083837 | T24: 141375 | U24: 35.55 | V24: 873.92 | W24: 838.37 | AP24: derived: Nov-2025 'New Denomination' 873.92 and May-2026 'Denomination' 838.37 | AQ24: denomination chain | AR24: DERIVED (principal exact; interest/collateral not available) | AX24: =IF(N24="","",N24-O24-P24) -> 0 | AY24: =IF(Q24="","",P24/M24-Q24) -> 0 | AZ24: =IF(U24="","",T24*U24-O24) -> 0 | BA24: =IF(L24="","",L24-(J24+K24/10000)) | BB24: =IF(OR(R24="",R24=0,L24="",H24=""),"",N24*L24*H24/360/R24-1) | BC24: =IF(Z24="","",1-(1-Z24/(X24-Y24))^4) | BD24: =IF(Z24="","",1-(1-(Z24+AA24)/(X24-Y24))^4) | BE24: =IF(Y24="","",O24/(Y24+Z24+AA24)) | BG24: =IF(BF24="","",Q24-BF24) | BI24: =IF(BH24="","",O24-BH24) | BJ24: =IF(AS24="","",AS24-O24-AT24)
A25: XS0222684655 | B25: Magellan Mortgages No. 3 | C25: A | D25: 2026-05 | E25: 46157 | F25: 46069 | G25: 46157 | H25: 88 | I25: Act/360 | J25: 0.01984 | K25: 26 | L25: 0.02244 | M25: 1413750000 | N25: 1.1852456e+08 | O25: 3925983.8 | P25: 114598575 | Q25: 0.08106 | R25: 650146.71 | S25: 0 | T25: 141375 | U25: 27.77 | V25: 838.37 | W25: 810.6 | X25: 1.3684063e+08 | Y25: 2305832 | Z25: 1864443.6 | AA25: 76689.39 | AB25: 0.0543 | AC25: 3747.9 | AD25: 24537.2 | AE25: 1.3259366e+08 | AF25: 1.2339789e+08 | AG25: 0.02994 | AH25: 331571.96 | AI25: 0.0056 | AJ25: PASS | AK25: 9000000 | AP25: https://ind.millenniumbcp.pt/pt/Institucional/investidores/securitizacoes/Documents/Magellan3-InvestorReport/InvestorReport_202605.pdf | AQ25: Sec.1/2/3/6 | AR25: ok: issuer report, 6 identities pass | AU25: 9097305 | AV25: 8795947.5 | AW25: 1.2762407e+08 | AX25: =IF(N25="","",N25-O25-P25) -> 0 | AY25: =IF(Q25="","",P25/M25-Q25) -> 0 | AZ25: =IF(U25="","",T25*U25-O25) -> 0 | BA25: =IF(L25="","",L25-(J25+K25/10000)) -> 0 | BB25: =IF(OR(R25="",R25=0,L25="",H25=""),"",N25*L25*H25/360/R25-1) -> 4.5066753e-09 | BC25: =IF(Z25="","",1-(1-Z25/(X25-Y25))^4) -> 0.054292066 | BD25: =IF(Z25="","",1-(1-(Z25+AA25)/(X25-Y25))^4) -> 0.056476817 | BE25: =IF(Y25="","",O25/(Y25+Z25+AA25)) -> 0.92442103 | BG25: =IF(BF25="","",Q25-BF25) | BI25: =IF(BH25="","",O25-BH25) | BJ25: =IF(AS25="","",AS25-O25-AT25)
A26: XS0222684655 | B26: Magellan Mortgages No. 3 | C26: A | D26: 2026-08 | E26: 46251 | F26: 46157 | G26: 46251 | H26: 94 | I26: Act/360 | J26: 0.02252 | K26: 26 | L26: 0.02512 | M26: 1413750000 | N26: 114598575 | O26: 3753506.2 | P26: 1.1084507e+08 | Q26: 0.078405 | R26: 751664.79 | S26: 0 | T26: 141375 | U26: 26.55 | V26: 810.6 | W26: 784.05 | X26: 1.3259366e+08 | Y26: 2257065.1 | Z26: 1398727.6 | AA26: 560398.5 | AB26: 0.0424 | AC26: 1577.53 | AD26: 176256.67 | AE26: 1.2837747e+08 | AF26: 1.1935638e+08 | AG26: 0.03174 | AH26: 79543.27 | AI26: 0.0056 | AJ26: PASS | AK26: 9000000 | AP26: https://ind.millenniumbcp.pt/pt/Institucional/investidores/securitizacoes/Documents/Magellan3-InvestorReport/Investor-Report-202608.pdf | AQ26: Sec.1/2/3/6 | AR26: ok: issuer report, 6 identities pass | AU26: 8795947.5 | AV26: 8507872.5 | AW26: 1.2339789e+08 | AX26: =IF(N26="","",N26-O26-P26) -> 0 | AY26: =IF(Q26="","",P26/M26-Q26) -> 0 | AZ26: =IF(U26="","",T26*U26-O26) -> 0 | BA26: =IF(L26="","",L26-(J26+K26/10000)) -> 0 | BB26: =IF(OR(R26="",R26=0,L26="",H26=""),"",N26*L26*H26/360/R26-1) -> -4.523293e-09 | BC26: =IF(Z26="","",1-(1-Z26/(X26-Y26))^4) -> 0.042240547 | BD26: =IF(Z26="","",1-(1-(Z26+AA26)/(X26-Y26))^4) -> 0.058783025 | BE26: =IF(Y26="","",O26/(Y26+Z26+AA26)) -> 0.89025997 | BG26: =IF(BF26="","",Q26-BF26) | BI26: =IF(BH26="","",O26-BH26) | BJ26: =IF(AS26="","",AS26-O26-AT26)
A27: XS0260784318 | B27: Magellan Mortgages No. 4 | C27: A | D27: 2010-01 | E27: 40198 | F27: 40106 | G27: 40198 | H27: 92 | I27: Act/360 | J27: 0.00739 | K27: 14 | L27: 0.00879 | M27: 1413750000 | N27: 8.0148739e+08 | O27: 33987964 | P27: 7.6749943e+08 | Q27: 0.542882 | R27: 1800407.8 | T27: 141375 | U27: 240.41 | V27: 5669.23 | W27: 5428.82 | X27: 8.6593612e+08 | AL27: 36238567 | AP27: https://ind.millenniumbcp.pt/pt/Institucional/investidores/securitizacoes/Documents/Magellan4-InvestorReport/201001Magellan4_InvestorReport.pdf | AQ27: Sec.1 Denomination / New Denomination / Accrual Rate; Sec.2 beginning balance & principal redemption | AR27: ok: issuer report Sec.1 (balances = denomination x 141,375; interest computed) | AX27: =IF(N27="","",N27-O27-P27) -> 0 | AY27: =IF(Q27="","",P27/M27-Q27) -> 0 | AZ27: =IF(U27="","",T27*U27-O27) -> 0 | BA27: =IF(L27="","",L27-(J27+K27/10000)) -> 0 | BB27: =IF(OR(R27="",R27=0,L27="",H27=""),"",N27*L27*H27/360/R27-1) -> 1.7836235e-09 | BC27: =IF(Z27="","",1-(1-Z27/(X27-Y27))^4) | BD27: =IF(Z27="","",1-(1-(Z27+AA27)/(X27-Y27))^4) | BE27: =IF(Y27="","",O27/(Y27+Z27+AA27)) | BG27: =IF(BF27="","",Q27-BF27) | BI27: =IF(BH27="","",O27-BH27) | BJ27: =IF(AS27="","",AS27-O27-AT27)
A28: XS0260784318 | B28: Magellan Mortgages No. 4 | C28: A | D28: 2012-04 | E28: 41019 | F28: 40928 | G28: 41019 | H28: 91 | I28: Act/360 | J28: 0.01204 | K28: 14 | L28: 0.01344 | M28: 1413750000 | N28: 6.4252817e+08 | O28: 14637968 | P28: 6.278902e+08 | Q28: 0.444131 | R28: 2182882.4 | T28: 141375 | U28: 103.54 | V28: 4544.85 | W28: 4441.31 | X28: 7.0067712e+08 | AL28: 14378658 | AP28: https://ind.millenniumbcp.pt/pt/Institucional/investidores/securitizacoes/Documents/Magellan4-InvestorReport/201204Magellan4_InvestorReport.pdf | AQ28: Sec.1 Denomination / New Denomination / Accrual Rate; Sec.2 beginning balance & principal redemption | AR28: ok: issuer report Sec.1 (balances = denomination x 141,375; interest computed) | AX28: =IF(N28="","",N28-O28-P28) -> 0 | AY28: =IF(Q28="","",P28/M28-Q28) -> 0 | AZ28: =IF(U28="","",T28*U28-O28) -> 0 | BA28: =IF(L28="","",L28-(J28+K28/10000)) -> 0 | BB28: =IF(OR(R28="",R28=0,L28="",H28=""),"",N28*L28*H28/360/R28-1) -> -2.1531167e-09 | BC28: =IF(Z28="","",1-(1-Z28/(X28-Y28))^4) | BD28: =IF(Z28="","",1-(1-(Z28+AA28)/(X28-Y28))^4) | BE28: =IF(Y28="","",O28/(Y28+Z28+AA28)) | BG28: =IF(BF28="","",Q28-BF28) | BI28: =IF(BH28="","",O28-BH28) | BJ28: =IF(AS28="","",AS28-O28-AT28)
A29: XS0260784318 | B29: Magellan Mortgages No. 4 | C29: A | D29: 2013-04 | E29: 41386 | F29: 41295 | G29: 41386 | H29: 91 | I29: Act/360 | J29: 0.00204 | K29: 14 | L29: 0.00344 | M29: 1413750000 | N29: 5.8284813e+08 | O29: 15654454 | P29: 5.6719367e+08 | Q29: 0.401198 | R29: 506818.83 | T29: 141375 | U29: 110.73 | V29: 4122.71 | W29: 4011.98 | X29: 6.3919792e+08 | AL29: 16292520 | AP29: https://ind.millenniumbcp.pt/pt/Institucional/investidores/securitizacoes/Documents/Magellan4-InvestorReport/201304Magellan4_InvestorReport.pdf | AQ29: Sec.1 Denomination / New Denomination / Accrual Rate; Sec.2 beginning balance & principal redemption | AR29: ok: issuer report Sec.1 (balances = denomination x 141,375; interest computed) | AX29: =IF(N29="","",N29-O29-P29) -> 0 | AY29: =IF(Q29="","",P29/M29-Q29) -> 0 | AZ29: =IF(U29="","",T29*U29-O29) -> 0 | BA29: =IF(L29="","",L29-(J29+K29/10000)) -> 0 | BB29: =IF(OR(R29="",R29=0,L29="",H29=""),"",N29*L29*H29/360/R29-1) -> -7.4467768e-09 | BC29: =IF(Z29="","",1-(1-Z29/(X29-Y29))^4) | BD29: =IF(Z29="","",1-(1-(Z29+AA29)/(X29-Y29))^4) | BE29: =IF(Y29="","",O29/(Y29+Z29+AA29)) | BG29: =IF(BF29="","",Q29-BF29) | BI29: =IF(BH29="","",O29-BH29) | BJ29: =IF(AS29="","",AS29-O29-AT29)
A30: XS0260784318 | B30: Magellan Mortgages No. 4 | C30: A | D30: 2015-07 | E30: 42205 | F30: 42114 | G30: 42205 | H30: 91 | I30: Act/360 | J30: 2e-05 | K30: 14 | L30: 0.00142 | M30: 1413750000 | N30: 4.7738096e+08 | O30: 9316612.5 | P30: 468064350 | Q30: 0.33108 | R30: 171353.24 | T30: 141375 | U30: 65.9 | V30: 3376.7 | W30: 3310.8 | X30: 5.2971029e+08 | AL30: 9501622.6 | AP30: https://ind.millenniumbcp.pt/pt/Institucional/investidores/securitizacoes/Documents/Magellan4-InvestorReport/201507Magellan4_InvestorReport.pdf | AQ30: Sec.1 Denomination / New Denomination / Accrual Rate; Sec.2 beginning balance & principal redemption | AR30: ok: issuer report Sec.1 (balances = denomination x 141,375; interest computed) | AX30: =IF(N30="","",N30-O30-P30) -> 0 | AY30: =IF(Q30="","",P30/M30-Q30) -> 0 | AZ30: =IF(U30="","",T30*U30-O30) -> 0 | BA30: =IF(L30="","",L30-(J30+K30/10000)) -> 0 | BB30: =IF(OR(R30="",R30=0,L30="",H30=""),"",N30*L30*H30/360/R30-1) -> 2.5519895e-08 | BC30: =IF(Z30="","",1-(1-Z30/(X30-Y30))^4) | BD30: =IF(Z30="","",1-(1-(Z30+AA30)/(X30-Y30))^4) | BE30: =IF(Y30="","",O30/(Y30+Z30+AA30)) | BG30: =IF(BF30="","",Q30-BF30) | BI30: =IF(BH30="","",O30-BH30) | BJ30: =IF(AS30="","",AS30-O30-AT30)
A31: XS0260784318 | B31: Magellan Mortgages No. 4 | C31: A | D31: 2017-04 | E31: 42845 | F31: 42755 | G31: 42845 | H31: 90 | I31: Act/360 | J31: -0.00329 | K31: 28 | L31: 0 | M31: 1413750000 | N31: 4.0540978e+08 | O31: 9535743.8 | P31: 3.9587403e+08 | Q31: 0.280017 | R31: 0 | T31: 141375 | U31: 67.45 | V31: 2867.62 | W31: 2800.17 | X31: 4.533691e+08 | AL31: 10752518 | AP31: https://ind.millenniumbcp.pt/pt/Institucional/investidores/securitizacoes/Documents/Magellan4-InvestorReport/201704Magellan4_InvestorReport.pdf | AQ31: Sec.1 Denomination / New Denomination / Accrual Rate; Sec.2 beginning balance & principal redemption | AR31: ok: issuer report Sec.1 (balances = denomination x 141,375; | AX31: =IF(N31="","",N31-O31-P31) -> 0 | AY31: =IF(Q31="","",P31/M31-Q31) -> 0 | AZ31: =IF(U31="","",T31*U31-O31) -> 0 | BA31: =IF(L31="","",L31-(J31+K31/10000)) -> 0.00049 | BB31: =IF(OR(R31="",R31=0,L31="",H31=""),"",N31*L31*H31/360/R31-1) | BC31: =IF(Z31="","",1-(1-Z31/(X31-Y31))^4) | BD31: =IF(Z31="","",1-(1-(Z31+AA31)/(X31-Y31))^4) | BE31: =IF(Y31="","",O31/(Y31+Z31+AA31)) | BG31: =IF(BF31="","",Q31-BF31) | BI31: =IF(BH31="","",O31-BH31) | BJ31: =IF(AS31="","",AS31-O31-AT31)
A32: XS0260784318 | B32: Magellan Mortgages No. 4 | C32: A | D32: 2018-04 | E32: 43210 | F32: 43122 | G32: 43210 | H32: 88 | I32: Act/360 | J32: -0.00328 | K32: 28 | L32: 0 | M32: 1413750000 | N32: 3.6710988e+08 | O32: 8793525 | P32: 3.5831635e+08 | Q32: 0.253451 | R32: 0 | T32: 141375 | U32: 62.2 | V32: 2596.71 | W32: 2534.51 | X32: 4.1001465e+08 | AL32: 9765179.3 | AP32: https://ind.millenniumbcp.pt/pt/Institucional/investidores/securitizacoes/Documents/Magellan4-InvestorReport/201804Magellan4_InvestorReport.pdf | AQ32: Sec.1 Denomination / New Denomination / Accrual Rate; Sec.2 beginning balance & principal redemption | AR32: ok: issuer report Sec.1 (balances = denomination x 141,375; interest computed) | AX32: =IF(N32="","",N32-O32-P32) -> 0 | AY32: =IF(Q32="","",P32/M32-Q32) -> 0 | AZ32: =IF(U32="","",T32*U32-O32) -> 0 | BA32: =IF(L32="","",L32-(J32+K32/10000)) -> 0.00048 | BB32: =IF(OR(R32="",R32=0,L32="",H32=""),"",N32*L32*H32/360/R32-1) | BC32: =IF(Z32="","",1-(1-Z32/(X32-Y32))^4) | BD32: =IF(Z32="","",1-(1-(Z32+AA32)/(X32-Y32))^4) | BE32: =IF(Y32="","",O32/(Y32+Z32+AA32)) | BG32: =IF(BF32="","",Q32-BF32) | BI32: =IF(BH32="","",O32-BH32) | BJ32: =IF(AS32="","",AS32-O32-AT32)
A33: XS0260784318 | B33: Magellan Mortgages No. 4 | C33: A | D33: 2025-01 | E33: 45677 | F33: 45586 | G33: 45677 | H33: 91 | I33: Act/360 | J33: 0.03219 | K33: 28 | L33: 0.03499 | M33: 1413750000 | N33: 1.7005009e+08 | O33: 5424558.8 | P33: 1.6462553e+08 | Q33: 0.116446 | R33: 1504041.1 | T33: 141375 | U33: 38.37 | V33: 1202.83 | W33: 1164.46 | X33: 1.8956581e+08 | AL33: 5879318.2 | AP33: https://ind.millenniumbcp.pt/pt/Institucional/investidores/securitizacoes/Documents/Magellan4-InvestorReport/202501_Magellan4_InvestorReport.pdf | AQ33: Sec.1 Denomination / New Denomination / Accrual Rate; Sec.2 beginning balance & principal redemption | AR33: ok: issuer report Sec.1 (balances = denomination x 141,375; interest computed) | AX33: =IF(N33="","",N33-O33-P33) -> 0 | AY33: =IF(Q33="","",P33/M33-Q33) -> 0 | AZ33: =IF(U33="","",T33*U33-O33) -> 0 | BA33: =IF(L33="","",L33-(J33+K33/10000)) -> 0 | BB33: =IF(OR(R33="",R33=0,L33="",H33=""),"",N33*L33*H33/360/R33-1) -> -1.7578337e-09 | BC33: =IF(Z33="","",1-(1-Z33/(X33-Y33))^4) | BD33: =IF(Z33="","",1-(1-(Z33+AA33)/(X33-Y33))^4) | BE33: =IF(Y33="","",O33/(Y33+Z33+AA33)) | BG33: =IF(BF33="","",Q33-BF33) | BI33: =IF(BH33="","",O33-BH33) | BJ33: =IF(AS33="","",AS33-O33-AT33)
A34: XS0260784318 | B34: Magellan Mortgages No. 4 | C34: A | D34: 2026-01 | E34: 46042 | F34: 45950 | G34: 46042 | H34: 92 | I34: Act/360 | J34: 0.02004 | K34: 28 | L34: 0.02284 | M34: 1413750000 | N34: 1.4995788e+08 | O34: 5915130 | P34: 1.4404275e+08 | Q34: 0.101887 | R34: 875287.46 | S34: 0 | T34: 141375 | U34: 41.84 | V34: 1060.71 | W34: 1018.87 | X34: 1.6768555e+08 | Y34: 2525885.3 | Z34: 3731073.6 | AA34: 183051.94 | AB34: 0.0906 | AC34: 34539.67 | AD34: 94508.64 | AE34: 1.6124554e+08 | AF34: 1.5538171e+08 | AG34: 0.02869 | AH34: 163238.33 | AI34: 0.0037 | AJ34: PASS | AK34: 9000000 | AP34: https://ind.millenniumbcp.pt/pt/Institucional/investidores/securitizacoes/Documents/Magellan4-InvestorReport/Magellan-Mortgages-No4-plc_16012026.pdf | AQ34: Sec.1/2/3/6 | AR34: ok: issuer report, 6 identities pass | AU34: 11804951 | AV34: 11339374 | AW34: 1.6176176e+08 | AX34: =IF(N34="","",N34-O34-P34) -> 0 | AY34: =IF(Q34="","",P34/M34-Q34) -> 0 | AZ34: =IF(U34="","",T34*U34-O34) -> 0 | BA34: =IF(L34="","",L34-(J34+K34/10000)) -> 0 | BB34: =IF(OR(R34="",R34=0,L34="",H34=""),"",N34*L34*H34/360/R34-1) -> 1.9250816e-09 | BC34: =IF(Z34="","",1-(1-Z34/(X34-Y34))^4) -> 0.087346645 | BD34: =IF(Z34="","",1-(1-(Z34+AA34)/(X34-Y34))^4) -> 0.091479222 | BE34: =IF(Y34="","",O34/(Y34+Z34+AA34)) -> 0.9184969 | BG34: =IF(BF34="","",Q34-BF34) | BI34: =IF(BH34="","",O34-BH34) | BJ34: =IF(AS34="","",AS34-O34-AT34)
A35: XS0260784318 | B35: Magellan Mortgages No. 4 | C35: A | D35: 2026-04 | E35: 46132 | F35: 46042 | G35: 46132 | H35: 90 | I35: Act/360 | K35: 28 | M35: 1413750000 | N35: 1.4404275e+08 | O35: 4709201.2 | P35: 139333545 | Q35: 0.0985563 | T35: 141375 | U35: 33.31 | V35: 1018.87 | W35: 985.56 | AP35: derived: Jan-2026 'New Denomination' 1,018.87 and Jul-2026 'Denomination' 985.56 | AQ35: denomination chain | AR35: DERIVED (principal exact; interest/collateral not available) | AX35: =IF(N35="","",N35-O35-P35) -> 0 | AY35: =IF(Q35="","",P35/M35-Q35) -> -3e-07 | AZ35: =IF(U35="","",T35*U35-O35) -> 0 | BA35: =IF(L35="","",L35-(J35+K35/10000)) | BB35: =IF(OR(R35="",R35=0,L35="",H35=""),"",N35*L35*H35/360/R35-1) | BC35: =IF(Z35="","",1-(1-Z35/(X35-Y35))^4) | BD35: =IF(Z35="","",1-(1-(Z35+AA35)/(X35-Y35))^4) | BE35: =IF(Y35="","",O35/(Y35+Z35+AA35)) | BG35: =IF(BF35="","",Q35-BF35) | BI35: =IF(BH35="","",O35-BH35) | BJ35: =IF(AS35="","",AS35-O35-AT35)
A36: XS0260784318 | B36: Magellan Mortgages No. 4 | C36: A | D36: 2026-07 | E36: 46223 | F36: 46132 | G36: 46223 | H36: 91 | I36: Act/360 | J36: 0.02238 | K36: 28 | L36: 0.02518 | M36: 1413750000 | N36: 139333545 | O36: 4089978.8 | P36: 1.3524357e+08 | Q36: 0.095663 | R36: 886850.27 | S36: 0 | T36: 141375 | U36: 28.93 | V36: 985.56 | W36: 956.63 | X36: 1.5603571e+08 | Y36: 2411455.1 | Z36: 1967231.3 | AA36: 115717.72 | AB36: 0.0522 | AC36: 2446.68 | AD36: 84634.26 | AE36: 1.5154131e+08 | AF36: 1.4588906e+08 | AG36: 0.02996 | AH36: 84628.09 | AI36: 0.0036 | AJ36: PASS | AK36: 9000000 | AP36: https://ind.millenniumbcp.pt/pt/Institucional/investidores/securitizacoes/Documents/Magellan4-InvestorReport/InvestorReport_202607.pdf | AQ36: Sec.1/2/3/6 | AR36: ok: issuer report, 6 identities pass | AU36: 10968671 | AV36: 10646700 | AW36: 1.5030128e+08 | AX36: =IF(N36="","",N36-O36-P36) -> 0 | AY36: =IF(Q36="","",P36/M36-Q36) -> 0 | AZ36: =IF(U36="","",T36*U36-O36) -> 0 | BA36: =IF(L36="","",L36-(J36+K36/10000)) -> 0 | BB36: =IF(OR(R36="",R36=0,L36="",H36=""),"",N36*L36*H36/360/R36-1) -> 3.5772669e-09 | BC36: =IF(Z36="","",1-(1-Z36/(X36-Y36))^4) -> 0.050246385 | BD36: =IF(Z36="","",1-(1-(Z36+AA36)/(X36-Y36))^4) -> 0.053141802 | BE36: =IF(Y36="","",O36/(Y36+Z36+AA36)) -> 0.91001581 | BG36: =IF(BF36="","",Q36-BF36) | BI36: =IF(BH36="","",O36-BH36) | BJ36: =IF(AS36="","",AS36-O36-AT36)
A37: ES0377992005 | B37: TDA CAM 5, FTA | C37: A | D37: 2021-01 | E37: 44223 | I37: Act/360 | K37: 12 | M37: 1944000000 | N37: 302596000 | O37: 12509000 | P37: 290087000 | Q37: 0.14922171 | R37: 0 | T37: 19440 | AP37: https://internet.cnmv.es/AUDITA/2022/19794.pdf | AQ37: Cuentas Anuales - Liquidaciones intermedias (kEUR) | AR37: ok: annual accounts (kEUR); chain balances from 'Saldo inicial'; ties to 31/12/21 255,424 and 31/12/22 210,062 kEUR; coupon floored 0% until Apr-2022 | AX37: =IF(N37="","",N37-O37-P37) -> 0 | AY37: =IF(Q37="","",P37/M37-Q37) -> -2.18107e-09 | AZ37: =IF(U37="","",T37*U37-O37) | BA37: =IF(L37="","",L37-(J37+K37/10000)) | BB37: =IF(OR(R37="",R37=0,L37="",H37=""),"",N37*L37*H37/360/R37-1) | BC37: =IF(Z37="","",1-(1-Z37/(X37-Y37))^4) | BD37: =IF(Z37="","",1-(1-(Z37+AA37)/(X37-Y37))^4) | BE37: =IF(Y37="","",O37/(Y37+Z37+AA37)) | BG37: =IF(BF37="","",Q37-BF37) | BI37: =IF(BH37="","",O37-BH37) | BJ37: =IF(AS37="","",AS37-O37-AT37)
A38: ES0377992005 | B38: TDA CAM 5, FTA | C38: A | D38: 2021-04 | E38: 44313 | I38: Act/360 | K38: 12 | M38: 1944000000 | N38: 290087000 | O38: 11835000 | P38: 278252000 | Q38: 0.14313374 | R38: 0 | T38: 19440 | AP38: https://internet.cnmv.es/AUDITA/2022/19794.pdf | AQ38: Cuentas Anuales - Liquidaciones intermedias (kEUR) | AR38: ok: annual accounts (kEUR); chain balances from 'Saldo inicial'; ties to 31/12/21 255,424 and 31/12/22 210,062 kEUR; coupon floored 0% until Apr-2022 | AX38: =IF(N38="","",N38-O38-P38) -> 0 | AY38: =IF(Q38="","",P38/M38-Q38) -> 4.8559671e-09 | AZ38: =IF(U38="","",T38*U38-O38) | BA38: =IF(L38="","",L38-(J38+K38/10000)) | BB38: =IF(OR(R38="",R38=0,L38="",H38=""),"",N38*L38*H38/360/R38-1) | BC38: =IF(Z38="","",1-(1-Z38/(X38-Y38))^4) | BD38: =IF(Z38="","",1-(1-(Z38+AA38)/(X38-Y38))^4) | BE38: =IF(Y38="","",O38/(Y38+Z38+AA38)) | BG38: =IF(BF38="","",Q38-BF38) | BI38: =IF(BH38="","",O38-BH38) | BJ38: =IF(AS38="","",AS38-O38-AT38)
A39: ES0377992005 | B39: TDA CAM 5, FTA | C39: A | D39: 2021-07 | E39: 44404 | I39: Act/360 | K39: 12 | M39: 1944000000 | N39: 278252000 | O39: 11382000 | P39: 266870000 | Q39: 0.13727881 | R39: 0 | T39: 19440 | AP39: https://internet.cnmv.es/AUDITA/2022/19794.pdf | AQ39: Cuentas Anuales - Liquidaciones intermedias (kEUR) | AR39: ok: annual accounts (kEUR); chain balances from 'Saldo inicial'; ties to 31/12/21 255,424 and 31/12/22 210,062 kEUR; coupon floored 0% until Apr-2022 | AX39: =IF(N39="","",N39-O39-P39) -> 0 | AY39: =IF(Q39="","",P39/M39-Q39) -> -3.4156379e-09 | AZ39: =IF(U39="","",T39*U39-O39) | BA39: =IF(L39="","",L39-(J39+K39/10000)) | BB39: =IF(OR(R39="",R39=0,L39="",H39=""),"",N39*L39*H39/360/R39-1) | BC39: =IF(Z39="","",1-(1-Z39/(X39-Y39))^4) | BD39: =IF(Z39="","",1-(1-(Z39+AA39)/(X39-Y39))^4) | BE39: =IF(Y39="","",O39/(Y39+Z39+AA39)) | BG39: =IF(BF39="","",Q39-BF39) | BI39: =IF(BH39="","",O39-BH39) | BJ39: =IF(AS39="","",AS39-O39-AT39)
A40: ES0377992005 | B40: TDA CAM 5, FTA | C40: A | D40: 2021-10 | E40: 44495 | I40: Act/360 | K40: 12 | M40: 1944000000 | N40: 266870000 | O40: 11445000 | P40: 255425000 | Q40: 0.13139146 | R40: 0 | T40: 19440 | AP40: https://internet.cnmv.es/AUDITA/2022/19794.pdf | AQ40: Cuentas Anuales - Liquidaciones intermedias (kEUR) | AR40: ok: annual accounts (kEUR); chain balances from 'Saldo inicial'; ties to 31/12/21 255,424 and 31/12/22 210,062 kEUR; coupon floored 0% until Apr-2022 | AX40: =IF(N40="","",N40-O40-P40) -> 0 | AY40: =IF(Q40="","",P40/M40-Q40) -> 9.053498e-10 | AZ40: =IF(U40="","",T40*U40-O40) | BA40: =IF(L40="","",L40-(J40+K40/10000)) | BB40: =IF(OR(R40="",R40=0,L40="",H40=""),"",N40*L40*H40/360/R40-1) | BC40: =IF(Z40="","",1-(1-Z40/(X40-Y40))^4) | BD40: =IF(Z40="","",1-(1-(Z40+AA40)/(X40-Y40))^4) | BE40: =IF(Y40="","",O40/(Y40+Z40+AA40)) | BG40: =IF(BF40="","",Q40-BF40) | BI40: =IF(BH40="","",O40-BH40) | BJ40: =IF(AS40="","",AS40-O40-AT40)
A41: ES0377992005 | B41: TDA CAM 5, FTA | C41: A | D41: 2022-01 | E41: 44587 | I41: Act/360 | K41: 12 | M41: 1944000000 | N41: 255425000 | O41: 12077000 | P41: 243348000 | Q41: 0.12517901 | R41: 0 | T41: 19440 | AP41: https://internet.cnmv.es/AUDITA/2022/19794.pdf | AQ41: Cuentas Anuales - Liquidaciones intermedias (kEUR) | AR41: ok: annual accounts (kEUR); chain balances from 'Saldo inicial'; ties to 31/12/21 255,424 and 31/12/22 210,062 kEUR; coupon floored 0% until Apr-2022 | AX41: =IF(N41="","",N41-O41-P41) -> 0 | AY41: =IF(Q41="","",P41/M41-Q41) -> 2.345679e-09 | AZ41: =IF(U41="","",T41*U41-O41) | BA41: =IF(L41="","",L41-(J41+K41/10000)) | BB41: =IF(OR(R41="",R41=0,L41="",H41=""),"",N41*L41*H41/360/R41-1) | BC41: =IF(Z41="","",1-(1-Z41/(X41-Y41))^4) | BD41: =IF(Z41="","",1-(1-(Z41+AA41)/(X41-Y41))^4) | BE41: =IF(Y41="","",O41/(Y41+Z41+AA41)) | BG41: =IF(BF41="","",Q41-BF41) | BI41: =IF(BH41="","",O41-BH41) | BJ41: =IF(AS41="","",AS41-O41-AT41)
A42: ES0377992005 | B42: TDA CAM 5, FTA | C42: A | D42: 2022-04 | E42: 44677 | I42: Act/360 | K42: 12 | M42: 1944000000 | N42: 243348000 | O42: 11449000 | P42: 231899000 | Q42: 0.11928961 | R42: 0 | T42: 19440 | AP42: https://internet.cnmv.es/AUDITA/2022/19794.pdf | AQ42: Cuentas Anuales - Liquidaciones intermedias (kEUR) | AR42: ok: annual accounts (kEUR); chain balances from 'Saldo inicial'; ties to 31/12/21 255,424 and 31/12/22 210,062 kEUR; coupon floored 0% until Apr-2022 | AX42: =IF(N42="","",N42-O42-P42) -> 0 | AY42: =IF(Q42="","",P42/M42-Q42) -> -9.4650206e-10 | AZ42: =IF(U42="","",T42*U42-O42) | BA42: =IF(L42="","",L42-(J42+K42/10000)) | BB42: =IF(OR(R42="",R42=0,L42="",H42=""),"",N42*L42*H42/360/R42-1) | BC42: =IF(Z42="","",1-(1-Z42/(X42-Y42))^4) | BD42: =IF(Z42="","",1-(1-(Z42+AA42)/(X42-Y42))^4) | BE42: =IF(Y42="","",O42/(Y42+Z42+AA42)) | BG42: =IF(BF42="","",Q42-BF42) | BI42: =IF(BH42="","",O42-BH42) | BJ42: =IF(AS42="","",AS42-O42-AT42)
A43: ES0377992005 | B43: TDA CAM 5, FTA | C43: A | D43: 2022-07 | E43: 44768 | I43: Act/360 | K43: 12 | M43: 1944000000 | N43: 231899000 | O43: 11678000 | P43: 220221000 | Q43: 0.11328241 | R43: 0 | T43: 19440 | AP43: https://internet.cnmv.es/AUDITA/2022/19794.pdf | AQ43: Cuentas Anuales - Liquidaciones intermedias (kEUR) | AR43: ok: annual accounts (kEUR); chain balances from 'Saldo inicial'; ties to 31/12/21 255,424 and 31/12/22 210,062 kEUR; coupon floored 0% until Apr-2022 | AX43: =IF(N43="","",N43-O43-P43) -> 0 | AY43: =IF(Q43="","",P43/M43-Q43) -> -2.5925926e-09 | AZ43: =IF(U43="","",T43*U43-O43) | BA43: =IF(L43="","",L43-(J43+K43/10000)) | BB43: =IF(OR(R43="",R43=0,L43="",H43=""),"",N43*L43*H43/360/R43-1) | BC43: =IF(Z43="","",1-(1-Z43/(X43-Y43))^4) | BD43: =IF(Z43="","",1-(1-(Z43+AA43)/(X43-Y43))^4) | BE43: =IF(Y43="","",O43/(Y43+Z43+AA43)) | BG43: =IF(BF43="","",Q43-BF43) | BI43: =IF(BH43="","",O43-BH43) | BJ43: =IF(AS43="","",AS43-O43-AT43)
A44: ES0377992005 | B44: TDA CAM 5, FTA | C44: A | D44: 2022-10 | E44: 44860 | I44: Act/360 | K44: 12 | M44: 1944000000 | N44: 220221000 | O44: 10157000 | P44: 210064000 | Q44: 0.10805761 | R44: 149000 | T44: 19440 | AP44: https://internet.cnmv.es/AUDITA/2022/19794.pdf | AQ44: Cuentas Anuales - Liquidaciones intermedias (kEUR) | AR44: ok: annual accounts (kEUR); chain balances from 'Saldo inicial'; ties to 31/12/21 255,424 and 31/12/22 210,062 kEUR; coupon floored 0% until Apr-2022 | AX44: =IF(N44="","",N44-O44-P44) -> 0 | AY44: =IF(Q44="","",P44/M44-Q44) -> 3.1687243e-09 | AZ44: =IF(U44="","",T44*U44-O44) | BA44: =IF(L44="","",L44-(J44+K44/10000)) | BB44: =IF(OR(R44="",R44=0,L44="",H44=""),"",N44*L44*H44/360/R44-1) | BC44: =IF(Z44="","",1-(1-Z44/(X44-Y44))^4) | BD44: =IF(Z44="","",1-(1-(Z44+AA44)/(X44-Y44))^4) | BE44: =IF(Y44="","",O44/(Y44+Z44+AA44)) | BG44: =IF(BF44="","",Q44-BF44) | BI44: =IF(BH44="","",O44-BH44) | BJ44: =IF(AS44="","",AS44-O44-AT44)
A45: ES0377966009 | B45: TDA CAM 8, FTA | C45: A | D45: 2020-08 | E45: 44069 | M45: 1635400000 | P45: 3.065554e+08 | Q45: 0.1874498 | T45: 16354 | AP45: https://www.cnmv.es/webservices/verdocumento/ver?t=%7B7507a87b-f1ec-46d7-8e5d-e690d38a9b8f%7D | AQ45: TdA 'INFORMACION A LOS INVERSORES - FECHA DE PAGO 26/11/2020', I. BONOS A, line 2 'Pendiente de vencimiento en la anterior Fecha de Pago' | AR45: PARTIAL: text from CNMV notice as indexed; full PDF not retrievable from this environment (CNMV blocks automated fetch) | AX45: =IF(N45="","",N45-O45-P45) | AY45: =IF(Q45="","",P45/M45-Q45) -> 0 | AZ45: =IF(U45="","",T45*U45-O45) | BA45: =IF(L45="","",L45-(J45+K45/10000)) | BB45: =IF(OR(R45="",R45=0,L45="",H45=""),"",N45*L45*H45/360/R45-1) | BC45: =IF(Z45="","",1-(1-Z45/(X45-Y45))^4) | BD45: =IF(Z45="","",1-(1-(Z45+AA45)/(X45-Y45))^4) | BE45: =IF(Y45="","",O45/(Y45+Z45+AA45)) | BG45: =IF(BF45="","",Q45-BF45) | BI45: =IF(BH45="","",O45-BH45) | BJ45: =IF(AS45="","",AS45-O45-AT45)
A46: ES0377966009 | D46: 2020-11 | E46: 44161 | M46: 1635400000 | N46: 3.065554e+08 | T46: 16354 | AP46: https://www.cnmv.es/webservices/verdocumento/ver?t=%7B7507a87b-f1ec-46d7-8e5d-e690d38a9b8f%7D | AQ46: I. BONOS <series> block | AR46: PARTIAL: TdA notice, balance identity not closed (fields missing in text) | AX46: =IF(N46="","",N46-O46-P46) -> 3.065554e+08 | AY46: =IF(Q46="","",P46/M46-Q46) | AZ46: =IF(U46="","",T46*U46-O46) | BA46: =IF(L46="","",L46-(J46+K46/10000)) | BB46: =IF(OR(R46="",R46=0,L46="",H46=""),"",N46*L46*H46/360/R46-1) | BC46: =IF(Z46="","",1-(1-Z46/(X46-Y46))^4) | BD46: =IF(Z46="","",1-(1-(Z46+AA46)/(X46-Y46))^4) | BE46: =IF(Y46="","",O46/(Y46+Z46+AA46)) | BG46: =IF(BF46="","",Q46-BF46) | BI46: =IF(BH46="","",O46-BH46) | BJ46: =IF(AS46="","",AS46-O46-AT46)
A47: ES0380957003 | B47: F.T.A. UCI 15 | C47: A | D47: 2007-06 | E47: 39251 | K47: 14 | M47: 1340600000 | N47: 1.1148436e+09 | O47: 61282714 | P47: 1.0535609e+09 | Q47: 0.7858876 | T47: 13406 | AP47: https://assets.santandermedia.com/adobe/assets/urn:aaid:aem:6cf79a51-1822-4af5-81b5-110fc7db6094/original/as/ES-U.C.I._15_June07-Archive_Quarterly_Reports-UCI_15-EN.pdf | AQ47: Bonds PRINCIPAL: previous balance 1,225,843,630.30 / amortised 61,282,713.74 / outstanding 1,164,560,916.56 (all classes) | AR47: PARTIAL: total-bond figures; Class A = total - B,C,D at par (B 32.9m, C 56.5m, D 21.6m; subordinates untouched in 2007) | AX47: =IF(N47="","",N47-O47-P47) -> 0 | AY47: =IF(Q47="","",P47/M47-Q47) -> 0 | AZ47: =IF(U47="","",T47*U47-O47) | BA47: =IF(L47="","",L47-(J47+K47/10000)) | BB47: =IF(OR(R47="",R47=0,L47="",H47=""),"",N47*L47*H47/360/R47-1) | BC47: =IF(Z47="","",1-(1-Z47/(X47-Y47))^4) | BD47: =IF(Z47="","",1-(1-(Z47+AA47)/(X47-Y47))^4) | BE47: =IF(Y47="","",O47/(Y47+Z47+AA47)) | BG47: =IF(BF47="","",Q47-BF47) | BI47: =IF(BH47="","",O47-BH47) | BJ47: =IF(AS47="","",AS47-O47-AT47)
A48: ES0380957003 | B48: F.T.A. UCI 15 | C48: A | D48: 2012-06 | E48: 41078 | F48: 40988 | G48: 41078 | H48: 90 | J48: 0.00862 | K48: 14 | L48: 0.01002 | M48: 1340600000 | N48: 6.4979445e+08 | O48: 8444305.3 | P48: 6.4135015e+08 | Q48: 0.4784053 | R48: 1627756.5 | T48: 13406 | U48: 629.89 | V48: 48470.42 | W48: 47840.53 | X48: 7.8526141e+08 | AB48: 0.0421 | AE48: 7.750606e+08 | AG48: 0.0299 | AH48: 89918330 | AJ48: FAIL (B,C not amortised) | AL48: 10200809 | AM48: 0.0312 | AN48: 0.00803 | AO48: 0.00663 | AP48: https://assets.santandermedia.com/adobe/assets/urn:aaid:aem:5654f363-cc34-4260-92cc-88cb02900ab9/original/as/ES-U.C.I._15_Junio12-Informaci%C3%B3n_Peri%C3%B3dica-UCI_15.pdf | AQ48: p.2 II. VALORES EMITIDOS; p.3 BONOS PRINCIPAL; p.4 DERECHOS | AR48: ok: issuer report; beg balance cross-checked vs trigger page (Serie A saldo) | AX48: =IF(N48="","",N48-O48-P48) -> 0 | AY48: =IF(Q48="","",P48/M48-Q48) -> 0 | AZ48: =IF(U48="","",T48*U48-O48) -> 0 | BA48: =IF(L48="","",L48-(J48+K48/10000)) -> 0 | BB48: =IF(OR(R48="",R48=0,L48="",H48=""),"",N48*L48*H48/360/R48-1) -> -1.3160105e-05 | BC48: =IF(Z48="","",1-(1-Z48/(X48-Y48))^4) | BD48: =IF(Z48="","",1-(1-(Z48+AA48)/(X48-Y48))^4) | BE48: =IF(Y48="","",O48/(Y48+Z48+AA48)) | BG48: =IF(BF48="","",Q48-BF48) | BI48: =IF(BH48="","",O48-BH48) | BJ48: =IF(AS48="","",AS48-O48-AT48)
A49: ES0380957003 | B49: F.T.A. UCI 15 | C49: A | D49: 2026-06 | E49: 46191 | F49: 46099 | G49: 46191 | H49: 92 | J49: 0.021571 | K49: 14 | L49: 0.022971 | M49: 1340600000 | N49: 88627468 | O49: 6827005.5 | P49: 81800463 | Q49: 0.0610178 | R49: 520286.86 | T49: 13406 | U49: 509.25 | V49: 6611.03 | W49: 6101.78 | X49: 1.87982e+08 | AB49: 0.088 | AE49: 180964103 | AG49: 0.0326 | AH49: 16277028 | AJ49: FAIL (B,C not amortised) | AL49: 7017894.2 | AM49: 0.0745 | AN49: 0.02548 | AO49: 0.02408 | AP49: https://assets.santandermedia.com/adobe/assets/urn:aaid:aem:51f2945f-4fa2-4b4e-9757-af0f49e01ebf/original/as/ES-U.C.I._15_Junio26-Informacion_Periodica-UCI_15.pdf | AQ49: p.2 II. VALORES EMITIDOS; p.3 BONOS PRINCIPAL; p.4 DERECHOS | AR49: ok: issuer report; beg balance cross-checked vs trigger page (Serie A saldo) | AX49: =IF(N49="","",N49-O49-P49) -> 0 | AY49: =IF(Q49="","",P49/M49-Q49) -> 0 | AZ49: =IF(U49="","",T49*U49-O49) -> 0 | BA49: =IF(L49="","",L49-(J49+K49/10000)) -> 0 | BB49: =IF(OR(R49="",R49=0,L49="",H49=""),"",N49*L49*H49/360/R49-1) -> -2.1382522e-05 | BC49: =IF(Z49="","",1-(1-Z49/(X49-Y49))^4) | BD49: =IF(Z49="","",1-(1-(Z49+AA49)/(X49-Y49))^4) | BE49: =IF(Y49="","",O49/(Y49+Z49+AA49)) | BG49: =IF(BF49="","",Q49-BF49) | BI49: =IF(BH49="","",O49-BH49) | BJ49: =IF(AS49="","",AS49-O49-AT49)
A50: ES0345672010 | B50: HIPOCAT 11, FTA | C50: A2 | D50: 2015-01 | E50: 42027 | I50: Act/360 | K50: 13 | M50: 1083200000 | N50: 385608000 | O50: 15196000 | P50: 370412000 | Q50: 0.34196086 | T50: 10832 | AP50: https://edt-sg.com/intranet/fondos/FGH11/MFGH11C01161231.pdf | AQ50: Cuentas Anuales 2016, Nota 8 'movimiento de los Bonos', Serie A2 (kEUR; dates as printed) | AR50: ok: annual accounts, kEUR rounding; ties to balance sheet 31/12/15 & 31/12/16 and to trigger annex 06/10/16 | AX50: =IF(N50="","",N50-O50-P50) -> 0 | AY50: =IF(Q50="","",P50/M50-Q50) -> -3.2791728e-09 | AZ50: =IF(U50="","",T50*U50-O50) | BA50: =IF(L50="","",L50-(J50+K50/10000)) | BB50: =IF(OR(R50="",R50=0,L50="",H50=""),"",N50*L50*H50/360/R50-1) | BC50: =IF(Z50="","",1-(1-Z50/(X50-Y50))^4) | BD50: =IF(Z50="","",1-(1-(Z50+AA50)/(X50-Y50))^4) | BE50: =IF(Y50="","",O50/(Y50+Z50+AA50)) | BG50: =IF(BF50="","",Q50-BF50) | BI50: =IF(BH50="","",O50-BH50) | BJ50: =IF(AS50="","",AS50-O50-AT50)
A51: ES0345672010 | B51: HIPOCAT 11, FTA | C51: A2 | D51: 2015-04 | E51: 42117 | I51: Act/360 | K51: 13 | M51: 1083200000 | N51: 370412000 | O51: 9195000 | P51: 361217000 | Q51: 0.33347212 | T51: 10832 | AP51: https://edt-sg.com/intranet/fondos/FGH11/MFGH11C01161231.pdf | AQ51: Cuentas Anuales 2016, Nota 8 'movimiento de los Bonos', Serie A2 (kEUR; dates as printed) | AR51: ok: annual accounts, kEUR rounding; ties to balance sheet 31/12/15 & 31/12/16 and to trigger annex 06/10/16 | AX51: =IF(N51="","",N51-O51-P51) -> 0 | AY51: =IF(Q51="","",P51/M51-Q51) -> -3.5450515e-10 | AZ51: =IF(U51="","",T51*U51-O51) | BA51: =IF(L51="","",L51-(J51+K51/10000)) | BB51: =IF(OR(R51="",R51=0,L51="",H51=""),"",N51*L51*H51/360/R51-1) | BC51: =IF(Z51="","",1-(1-Z51/(X51-Y51))^4) | BD51: =IF(Z51="","",1-(1-(Z51+AA51)/(X51-Y51))^4) | BE51: =IF(Y51="","",O51/(Y51+Z51+AA51)) | BG51: =IF(BF51="","",Q51-BF51) | BI51: =IF(BH51="","",O51-BH51) | BJ51: =IF(AS51="","",AS51-O51-AT51)
A52: ES0345672010 | B52: HIPOCAT 11, FTA | C52: A2 | D52: 2015-07 | E52: 42208 | I52: Act/360 | K52: 13 | M52: 1083200000 | N52: 361217000 | O52: 14481000 | P52: 346736000 | Q52: 0.3201034 | T52: 10832 | AP52: https://edt-sg.com/intranet/fondos/FGH11/MFGH11C01161231.pdf | AQ52: Cuentas Anuales 2016, Nota 8 'movimiento de los Bonos', Serie A2 (kEUR; dates as printed) | AR52: ok: annual accounts, kEUR rounding; ties to balance sheet 31/12/15 & 31/12/16 and to trigger annex 06/10/16 | AX52: =IF(N52="","",N52-O52-P52) -> 0 | AY52: =IF(Q52="","",P52/M52-Q52) -> -2.6587887e-09 | AZ52: =IF(U52="","",T52*U52-O52) | BA52: =IF(L52="","",L52-(J52+K52/10000)) | BB52: =IF(OR(R52="",R52=0,L52="",H52=""),"",N52*L52*H52/360/R52-1) | BC52: =IF(Z52="","",1-(1-Z52/(X52-Y52))^4) | BD52: =IF(Z52="","",1-(1-(Z52+AA52)/(X52-Y52))^4) | BE52: =IF(Y52="","",O52/(Y52+Z52+AA52)) | BG52: =IF(BF52="","",Q52-BF52) | BI52: =IF(BH52="","",O52-BH52) | BJ52: =IF(AS52="","",AS52-O52-AT52)
A53: ES0345672010 | B53: HIPOCAT 11, FTA | C53: A2 | D53: 2015-10 | E53: 42299 | I53: Act/360 | K53: 13 | M53: 1083200000 | N53: 346736000 | O53: 8079000 | P53: 338657000 | Q53: 0.31264494 | T53: 10832 | AP53: https://edt-sg.com/intranet/fondos/FGH11/MFGH11C01161231.pdf | AQ53: Cuentas Anuales 2016, Nota 8 'movimiento de los Bonos', Serie A2 (kEUR; dates as printed) | AR53: ok: annual accounts, kEUR rounding; ties to balance sheet 31/12/15 & 31/12/16 and to trigger annex 06/10/16 | AX53: =IF(N53="","",N53-O53-P53) -> 0 | AY53: =IF(Q53="","",P53/M53-Q53) -> 9.1580504e-10 | AZ53: =IF(U53="","",T53*U53-O53) | BA53: =IF(L53="","",L53-(J53+K53/10000)) | BB53: =IF(OR(R53="",R53=0,L53="",H53=""),"",N53*L53*H53/360/R53-1) | BC53: =IF(Z53="","",1-(1-Z53/(X53-Y53))^4) | BD53: =IF(Z53="","",1-(1-(Z53+AA53)/(X53-Y53))^4) | BE53: =IF(Y53="","",O53/(Y53+Z53+AA53)) | BG53: =IF(BF53="","",Q53-BF53) | BI53: =IF(BH53="","",O53-BH53) | BJ53: =IF(AS53="","",AS53-O53-AT53)
A54: ES0345672010 | B54: HIPOCAT 11, FTA | C54: A2 | D54: 2016-01 | E54: 42390 | I54: Act/360 | K54: 13 | M54: 1083200000 | N54: 338657000 | O54: 11392000 | P54: 327265000 | Q54: 0.30212795 | T54: 10832 | AP54: https://edt-sg.com/intranet/fondos/FGH11/MFGH11C01161231.pdf | AQ54: Cuentas Anuales 2016, Nota 8 'movimiento de los Bonos', Serie A2 (kEUR; dates as printed) | AR54: ok: annual accounts, kEUR rounding; ties to balance sheet 31/12/15 & 31/12/16 and to trigger annex 06/10/16 | AX54: =IF(N54="","",N54-O54-P54) -> 0 | AY54: =IF(Q54="","",P54/M54-Q54) -> 4.2097489e-09 | AZ54: =IF(U54="","",T54*U54-O54) | BA54: =IF(L54="","",L54-(J54+K54/10000)) | BB54: =IF(OR(R54="",R54=0,L54="",H54=""),"",N54*L54*H54/360/R54-1) | BC54: =IF(Z54="","",1-(1-Z54/(X54-Y54))^4) | BD54: =IF(Z54="","",1-(1-(Z54+AA54)/(X54-Y54))^4) | BE54: =IF(Y54="","",O54/(Y54+Z54+AA54)) | BG54: =IF(BF54="","",Q54-BF54) | BI54: =IF(BH54="","",O54-BH54) | BJ54: =IF(AS54="","",AS54-O54-AT54)
A55: ES0345672010 | B55: HIPOCAT 11, FTA | C55: A2 | D55: 2016-04 | E55: 42482 | I55: Act/360 | K55: 13 | M55: 1083200000 | N55: 327265000 | O55: 9573000 | P55: 317692000 | Q55: 0.29329025 | T55: 10832 | AP55: https://edt-sg.com/intranet/fondos/FGH11/MFGH11C01161231.pdf | AQ55: Cuentas Anuales 2016, Nota 8 'movimiento de los Bonos', Serie A2 (kEUR; dates as printed) | AR55: ok: annual accounts, kEUR rounding; ties to balance sheet 31/12/15 & 31/12/16 and to trigger annex 06/10/16 | AX55: =IF(N55="","",N55-O55-P55) -> 0 | AY55: =IF(Q55="","",P55/M55-Q55) -> 1.1078287e-09 | AZ55: =IF(U55="","",T55*U55-O55) | BA55: =IF(L55="","",L55-(J55+K55/10000)) | BB55: =IF(OR(R55="",R55=0,L55="",H55=""),"",N55*L55*H55/360/R55-1) | BC55: =IF(Z55="","",1-(1-Z55/(X55-Y55))^4) | BD55: =IF(Z55="","",1-(1-(Z55+AA55)/(X55-Y55))^4) | BE55: =IF(Y55="","",O55/(Y55+Z55+AA55)) | BG55: =IF(BF55="","",Q55-BF55) | BI55: =IF(BH55="","",O55-BH55) | BJ55: =IF(AS55="","",AS55-O55-AT55)
A56: ES0345672010 | B56: HIPOCAT 11, FTA | C56: A2 | D56: 2016-07 | E56: 42573 | I56: Act/360 | K56: 13 | M56: 1083200000 | N56: 317692000 | O56: 8897000 | P56: 308795000 | Q56: 0.28507662 | T56: 10832 | AP56: https://edt-sg.com/intranet/fondos/FGH11/MFGH11C01161231.pdf | AQ56: Cuentas Anuales 2016, Nota 8 'movimiento de los Bonos', Serie A2 (kEUR; dates as printed) | AR56: ok: annual accounts, kEUR rounding; ties to balance sheet 31/12/15 & 31/12/16 and to trigger annex 06/10/16 | AX56: =IF(N56="","",N56-O56-P56) -> 0 | AY56: =IF(Q56="","",P56/M56-Q56) -> 4.8153619e-09 | AZ56: =IF(U56="","",T56*U56-O56) | BA56: =IF(L56="","",L56-(J56+K56/10000)) | BB56: =IF(OR(R56="",R56=0,L56="",H56=""),"",N56*L56*H56/360/R56-1) | BC56: =IF(Z56="","",1-(1-Z56/(X56-Y56))^4) | BD56: =IF(Z56="","",1-(1-(Z56+AA56)/(X56-Y56))^4) | BE56: =IF(Y56="","",O56/(Y56+Z56+AA56)) | BG56: =IF(BF56="","",Q56-BF56) | BI56: =IF(BH56="","",O56-BH56) | BJ56: =IF(AS56="","",AS56-O56-AT56)
A57: ES0345672010 | B57: HIPOCAT 11, FTA | C57: A2 | D57: 2016-10 | E57: 42665 | I57: Act/360 | K57: 13 | M57: 1083200000 | N57: 308795000 | O57: 6320000 | P57: 302475000 | Q57: 0.27924206 | T57: 10832 | AP57: https://edt-sg.com/intranet/fondos/FGH11/MFGH11C01161231.pdf | AQ57: Cuentas Anuales 2016, Nota 8 'movimiento de los Bonos', Serie A2 (kEUR; dates as printed) | AR57: ok: annual accounts, kEUR rounding; ties to balance sheet 31/12/15 & 31/12/16 and to trigger annex 06/10/16 | AX57: =IF(N57="","",N57-O57-P57) -> 0 | AY57: =IF(Q57="","",P57/M57-Q57) -> 5.6129984e-10 | AZ57: =IF(U57="","",T57*U57-O57) | BA57: =IF(L57="","",L57-(J57+K57/10000)) | BB57: =IF(OR(R57="",R57=0,L57="",H57=""),"",N57*L57*H57/360/R57-1) | BC57: =IF(Z57="","",1-(1-Z57/(X57-Y57))^4) | BD57: =IF(Z57="","",1-(1-(Z57+AA57)/(X57-Y57))^4) | BE57: =IF(Y57="","",O57/(Y57+Z57+AA57)) | BG57: =IF(BF57="","",Q57-BF57) | BI57: =IF(BH57="","",O57-BH57) | BJ57: =IF(AS57="","",AS57-O57-AT57)
A58: ES0345672010 | B58: HIPOCAT 11, FTA | C58: A2 | D58: 2018-01 | E58: 43115 | I58: Act/360 | K58: 13 | M58: 1083200000 | N58: 268325000 | O58: 18687000 | P58: 249638000 | Q58: 0.23046344 | T58: 10832 | AP58: https://internet.cnmv.es/AUDITA/2019/18634.pdf | AQ58: Cuentas Anuales 2019 (CNMV AUDITA), Nota 8 movimiento de los Bonos + Nota 17 pagos por fecha (kEUR) | AR58: ok: annual accounts kEUR; ties to 31/12/18 (230,507) and 31/12/19 (217,021) | AX58: =IF(N58="","",N58-O58-P58) -> 0 | AY58: =IF(Q58="","",P58/M58-Q58) -> 1.6543575e-09 | AZ58: =IF(U58="","",T58*U58-O58) | BA58: =IF(L58="","",L58-(J58+K58/10000)) | BB58: =IF(OR(R58="",R58=0,L58="",H58=""),"",N58*L58*H58/360/R58-1) | BC58: =IF(Z58="","",1-(1-Z58/(X58-Y58))^4) | BD58: =IF(Z58="","",1-(1-(Z58+AA58)/(X58-Y58))^4) | BE58: =IF(Y58="","",O58/(Y58+Z58+AA58)) | BG58: =IF(BF58="","",Q58-BF58) | BI58: =IF(BH58="","",O58-BH58) | BJ58: =IF(AS58="","",AS58-O58-AT58)
A59: ES0345672010 | B59: HIPOCAT 11, FTA | C59: A2 | D59: 2018-04 | E59: 43206 | I59: Act/360 | K59: 13 | M59: 1083200000 | N59: 249638000 | O59: 10083000 | P59: 239555000 | Q59: 0.22115491 | T59: 10832 | AP59: https://internet.cnmv.es/AUDITA/2019/18634.pdf | AQ59: Cuentas Anuales 2019 (CNMV AUDITA), Nota 8 movimiento de los Bonos + Nota 17 pagos por fecha (kEUR) | AR59: ok: annual accounts kEUR; ties to 31/12/18 (230,507) and 31/12/19 (217,021) | AX59: =IF(N59="","",N59-O59-P59) -> 0 | AY59: =IF(Q59="","",P59/M59-Q59) -> 1.3737075e-09 | AZ59: =IF(U59="","",T59*U59-O59) | BA59: =IF(L59="","",L59-(J59+K59/10000)) | BB59: =IF(OR(R59="",R59=0,L59="",H59=""),"",N59*L59*H59/360/R59-1) | BC59: =IF(Z59="","",1-(1-Z59/(X59-Y59))^4) | BD59: =IF(Z59="","",1-(1-(Z59+AA59)/(X59-Y59))^4) | BE59: =IF(Y59="","",O59/(Y59+Z59+AA59)) | BG59: =IF(BF59="","",Q59-BF59) | BI59: =IF(BH59="","",O59-BH59) | BJ59: =IF(AS59="","",AS59-O59-AT59)
A60: ES0345672010 | B60: HIPOCAT 11, FTA | C60: A2 | D60: 2018-07 | E60: 43297 | I60: Act/360 | K60: 13 | M60: 1083200000 | N60: 239555000 | O60: 4039000 | P60: 235516000 | Q60: 0.21742614 | T60: 10832 | AP60: https://internet.cnmv.es/AUDITA/2019/18634.pdf | AQ60: Cuentas Anuales 2019 (CNMV AUDITA), Nota 8 movimiento de los Bonos + Nota 17 pagos por fecha (kEUR) | AR60: ok: annual accounts kEUR; ties to 31/12/18 (230,507) and 31/12/19 (217,021) | AX60: =IF(N60="","",N60-O60-P60) -> 0 | AY60: =IF(Q60="","",P60/M60-Q60) -> 4.7562777e-09 | AZ60: =IF(U60="","",T60*U60-O60) | BA60: =IF(L60="","",L60-(J60+K60/10000)) | BB60: =IF(OR(R60="",R60=0,L60="",H60=""),"",N60*L60*H60/360/R60-1) | BC60: =IF(Z60="","",1-(1-Z60/(X60-Y60))^4) | BD60: =IF(Z60="","",1-(1-(Z60+AA60)/(X60-Y60))^4) | BE60: =IF(Y60="","",O60/(Y60+Z60+AA60)) | BG60: =IF(BF60="","",Q60-BF60) | BI60: =IF(BH60="","",O60-BH60) | BJ60: =IF(AS60="","",AS60-O60-AT60)
A61: ES0345672010 | B61: HIPOCAT 11, FTA | C61: A2 | D61: 2018-10 | E61: 43388 | I61: Act/360 | K61: 13 | M61: 1083200000 | N61: 235516000 | O61: 5009000 | P61: 230507000 | Q61: 0.21280188 | T61: 10832 | AP61: https://internet.cnmv.es/AUDITA/2019/18634.pdf | AQ61: Cuentas Anuales 2019 (CNMV AUDITA), Nota 8 movimiento de los Bonos + Nota 17 pagos por fecha (kEUR) | AR61: ok: annual accounts kEUR; ties to 31/12/18 (230,507) and 31/12/19 (217,021) | AX61: =IF(N61="","",N61-O61-P61) -> 0 | AY61: =IF(Q61="","",P61/M61-Q61) -> 3.3087149e-09 | AZ61: =IF(U61="","",T61*U61-O61) | BA61: =IF(L61="","",L61-(J61+K61/10000)) | BB61: =IF(OR(R61="",R61=0,L61="",H61=""),"",N61*L61*H61/360/R61-1) | BC61: =IF(Z61="","",1-(1-Z61/(X61-Y61))^4) | BD61: =IF(Z61="","",1-(1-(Z61+AA61)/(X61-Y61))^4) | BE61: =IF(Y61="","",O61/(Y61+Z61+AA61)) | BG61: =IF(BF61="","",Q61-BF61) | BI61: =IF(BH61="","",O61-BH61) | BJ61: =IF(AS61="","",AS61-O61-AT61)
A62: ES0345672010 | B62: HIPOCAT 11, FTA | C62: A2 | D62: 2019-01 | E62: 43480 | I62: Act/360 | K62: 13 | M62: 1083200000 | N62: 230507000 | O62: 2910000 | P62: 227597000 | Q62: 0.2101154 | T62: 10832 | AP62: https://internet.cnmv.es/AUDITA/2019/18634.pdf | AQ62: Cuentas Anuales 2019 (CNMV AUDITA), Nota 8 movimiento de los Bonos + Nota 17 pagos por fecha (kEUR); principal due/paid/insuficiencia: Nota 17 per-date table (kEUR) | AR62: ok: annual accounts kEUR; ties to 31/12/18 (230,507) and 31/12/19 (217,021); PRINCIPAL SHORTFALL: due 57491 kEUR vs paid 2910 kEUR | AS62: 57491000 | AT62: 54581000 | AX62: =IF(N62="","",N62-O62-P62) -> 0 | AY62: =IF(Q62="","",P62/M62-Q62) -> -1.1816839e-09 | AZ62: =IF(U62="","",T62*U62-O62) | BA62: =IF(L62="","",L62-(J62+K62/10000)) | BB62: =IF(OR(R62="",R62=0,L62="",H62=""),"",N62*L62*H62/360/R62-1) | BC62: =IF(Z62="","",1-(1-Z62/(X62-Y62))^4) | BD62: =IF(Z62="","",1-(1-(Z62+AA62)/(X62-Y62))^4) | BE62: =IF(Y62="","",O62/(Y62+Z62+AA62)) | BG62: =IF(BF62="","",Q62-BF62) | BI62: =IF(BH62="","",O62-BH62) | BJ62: =IF(AS62="","",AS62-O62-AT62) -> 0
A63: ES0345672010 | B63: HIPOCAT 11, FTA | C63: A2 | D63: 2019-04 | E63: 43570 | I63: Act/360 | K63: 13 | M63: 1083200000 | N63: 227597000 | O63: 2414000 | P63: 225183000 | Q63: 0.20788682 | T63: 10832 | AP63: https://internet.cnmv.es/AUDITA/2019/18634.pdf | AQ63: Cuentas Anuales 2019 (CNMV AUDITA), Nota 8 movimiento de los Bonos + Nota 17 pagos por fecha (kEUR); principal due/paid/insuficiencia: Nota 17 per-date table (kEUR) | AR63: ok: annual accounts kEUR; ties to 31/12/18 (230,507) and 31/12/19 (217,021); PRINCIPAL SHORTFALL: due 61380 kEUR vs paid 2414 kEUR | AS63: 61380000 | AT63: 58966000 | AX63: =IF(N63="","",N63-O63-P63) -> 0 | AY63: =IF(Q63="","",P63/M63-Q63) -> -3.1610044e-09 | AZ63: =IF(U63="","",T63*U63-O63) | BA63: =IF(L63="","",L63-(J63+K63/10000)) | BB63: =IF(OR(R63="",R63=0,L63="",H63=""),"",N63*L63*H63/360/R63-1) | BC63: =IF(Z63="","",1-(1-Z63/(X63-Y63))^4) | BD63: =IF(Z63="","",1-(1-(Z63+AA63)/(X63-Y63))^4) | BE63: =IF(Y63="","",O63/(Y63+Z63+AA63)) | BG63: =IF(BF63="","",Q63-BF63) | BI63: =IF(BH63="","",O63-BH63) | BJ63: =IF(AS63="","",AS63-O63-AT63) -> 0
A64: ES0345672010 | B64: HIPOCAT 11, FTA | C64: A2 | D64: 2019-07 | E64: 43661 | I64: Act/360 | K64: 13 | M64: 1083200000 | N64: 225183000 | O64: 6208000 | P64: 218975000 | Q64: 0.20215565 | T64: 10832 | AP64: https://internet.cnmv.es/AUDITA/2019/18634.pdf | AQ64: Cuentas Anuales 2019 (CNMV AUDITA), Nota 8 movimiento de los Bonos + Nota 17 pagos por fecha (kEUR); principal due/paid/insuficiencia: Nota 17 per-date table (kEUR) | AR64: ok: annual accounts kEUR; ties to 31/12/18 (230,507) and 31/12/19 (217,021); PRINCIPAL SHORTFALL: due 67072 kEUR vs paid 6208 kEUR | AS64: 67072000 | AT64: 60864000 | AX64: =IF(N64="","",N64-O64-P64) -> 0 | AY64: =IF(Q64="","",P64/M64-Q64) -> -7.3855227e-11 | AZ64: =IF(U64="","",T64*U64-O64) | BA64: =IF(L64="","",L64-(J64+K64/10000)) | BB64: =IF(OR(R64="",R64=0,L64="",H64=""),"",N64*L64*H64/360/R64-1) | BC64: =IF(Z64="","",1-(1-Z64/(X64-Y64))^4) | BD64: =IF(Z64="","",1-(1-(Z64+AA64)/(X64-Y64))^4) | BE64: =IF(Y64="","",O64/(Y64+Z64+AA64)) | BG64: =IF(BF64="","",Q64-BF64) | BI64: =IF(BH64="","",O64-BH64) | BJ64: =IF(AS64="","",AS64-O64-AT64) -> 0
A65: ES0345672010 | B65: HIPOCAT 11, FTA | C65: A2 | D65: 2019-10 | E65: 43753 | I65: Act/360 | K65: 13 | M65: 1083200000 | N65: 218975000 | O65: 1954000 | P65: 217021000 | Q65: 0.20035174 | T65: 10832 | AP65: https://internet.cnmv.es/AUDITA/2019/18634.pdf | AQ65: Cuentas Anuales 2019 (CNMV AUDITA), Nota 8 movimiento de los Bonos + Nota 17 pagos por fecha (kEUR); principal due/paid/insuficiencia: Nota 17 per-date table (kEUR) | AR65: ok: annual accounts kEUR; ties to 31/12/18 (230,507) and 31/12/19 (217,021); PRINCIPAL SHORTFALL: due 67545 kEUR vs paid 1954 kEUR | AS65: 67545000 | AT65: 65591000 | AX65: =IF(N65="","",N65-O65-P65) -> 0 | AY65: =IF(Q65="","",P65/M65-Q65) -> -4.4017725e-09 | AZ65: =IF(U65="","",T65*U65-O65) | BA65: =IF(L65="","",L65-(J65+K65/10000)) | BB65: =IF(OR(R65="",R65=0,L65="",H65=""),"",N65*L65*H65/360/R65-1) | BC65: =IF(Z65="","",1-(1-Z65/(X65-Y65))^4) | BD65: =IF(Z65="","",1-(1-(Z65+AA65)/(X65-Y65))^4) | BE65: =IF(Y65="","",O65/(Y65+Z65+AA65)) | BG65: =IF(BF65="","",Q65-BF65) | BI65: =IF(BH65="","",O65-BH65) | BJ65: =IF(AS65="","",AS65-O65-AT65) -> 0

Sheet Sources
A1: isin | B1: ticker | C1: deal | D1: doc_type | E1: period | F1: url | G1: status | H1: where_principal_is
A2: XS0222684655 | B2: MAGEL 3 A | C2: Magellan Mortgages No. 3 plc | D2: Index page | E2: - | F2: https://ind.millenniumbcp.pt/en/Institucional/investidores/securitizacoes/Pages/Magellan-Mortgages-No3-plc.aspx | G2: index (JS-rendered) | H2: lists all quarterly reports
A3: XS0222684655 | B3: MAGEL 3 A | C3: Magellan Mortgages No. 3 plc | D3: Quarterly investor report | E3: 2006-02 | F3: https://ind.millenniumbcp.pt/pt/Institucional/investidores/securitizacoes/Documents/Magellan3-InvestorReport/200602Magellan3_InvestorReport.pdf | G3: located | H3: Sec.1 'Security Level Information': Total Beginning/Ending Balance, Total Principal Distribution, Pool Factor, Denomination; Sec.6 'Principal Distribution' per note
A4: XS0222684655 | B4: MAGEL 3 A | C4: Magellan Mortgages No. 3 plc | D4: Quarterly investor report | E4: 2006-08 | F4: https://ind.millenniumbcp.pt/pt/Institucional/investidores/securitizacoes/Documents/Magellan3-InvestorReport/200608Magellan3_InvestorReport.pdf | G4: located | H4: Sec.1 'Security Level Information': Total Beginning/Ending Balance, Total Principal Distribution, Pool Factor, Denomination; Sec.6 'Principal Distribution' per note
A5: XS0222684655 | B5: MAGEL 3 A | C5: Magellan Mortgages No. 3 plc | D5: Quarterly investor report | E5: 2009-02 | F5: https://ind.millenniumbcp.pt/pt/Institucional/investidores/securitizacoes/Documents/Magellan3-InvestorReport/200902Magellan3_InvestorReport.pdf | G5: READ+PARSED | H5: Sec.1 'Security Level Information': Total Beginning/Ending Balance, Total Principal Distribution, Pool Factor, Denomination; Sec.6 'Principal Distribution' per note
A6: XS0222684655 | B6: MAGEL 3 A | C6: Magellan Mortgages No. 3 plc | D6: Quarterly investor report | E6: 2025-11 | F6: https://ind.millenniumbcp.pt/pt/Institucional/investidores/securitizacoes/Documents/Magellan3-InvestorReport/Investor-Report-2025-11.pdf | G6: READ+PARSED | H6: Sec.1 'Security Level Information': Total Beginning/Ending Balance, Total Principal Distribution, Pool Factor, Denomination; Sec.6 'Principal Distribution' per note
A7: XS0222684655 | B7: MAGEL 3 A | C7: Magellan Mortgages No. 3 plc | D7: Quarterly investor report | E7: 2026-05 | F7: https://ind.millenniumbcp.pt/pt/Institucional/investidores/securitizacoes/Documents/Magellan3-InvestorReport/InvestorReport_202605.pdf | G7: READ+PARSED | H7: Sec.1 'Security Level Information': Total Beginning/Ending Balance, Total Principal Distribution, Pool Factor, Denomination; Sec.6 'Principal Distribution' per note
A8: XS0222684655 | B8: MAGEL 3 A | C8: Magellan Mortgages No. 3 plc | D8: Quarterly investor report | E8: 2026-08 | F8: https://ind.millenniumbcp.pt/pt/Institucional/investidores/securitizacoes/Documents/Magellan3-InvestorReport/Investor-Report-202608.pdf | G8: READ+PARSED | H8: Sec.1 'Security Level Information': Total Beginning/Ending Balance, Total Principal Distribution, Pool Factor, Denomination; Sec.6 'Principal Distribution' per note
A9: XS0260784318 | B9: MAGEL 4 A | C9: Magellan Mortgages No. 4 plc | D9: Quarterly investor report | E9: 2026-01 | F9: https://ind.millenniumbcp.pt/pt/Institucional/investidores/securitizacoes/Documents/Magellan4-InvestorReport/Magellan-Mortgages-No4-plc_16012026.pdf | G9: READ+PARSED | H9: Sec.1 'Security Level Information': Total Beginning/Ending Balance, Total Principal Distribution, Pool Factor, Denomination; Sec.6 'Principal Distribution' per note
A10: XS0260784318 | B10: MAGEL 4 A | C10: Magellan Mortgages No. 4 plc | D10: Quarterly investor report | E10: 2026-07 | F10: https://ind.millenniumbcp.pt/pt/Institucional/investidores/securitizacoes/Documents/Magellan4-InvestorReport/InvestorReport_202607.pdf | G10: READ+PARSED | H10: Sec.1 'Security Level Information': Total Beginning/Ending Balance, Total Principal Distribution, Pool Factor, Denomination; Sec.6 'Principal Distribution' per note
A11: ES0380957003 | B11: UCI 15 A | C11: F.T.A. UCI 15 | D11: Fund page (full index) | E11: - | F11: https://www.santanderdetitulizacion.com/san/Home/Fondos-de-Titulizacion/uci-15 | G11: READ | H11: lists every report below; NIF V-84698067
A12: ES0380957003 | B12: UCI 15 A | C12: F.T.A. UCI 15 | D12: Información Periódica (quarterly) | E12: 2026-06 | F12: https://assets.santandermedia.com/adobe/assets/urn:aaid:aem:51f2945f-4fa2-4b4e-9757-af0f49e01ebf/original/as/ES-U.C.I._15_Junio26-Informacion_Periodica-UCI_15.pdf | G12: READ+PARSED | H12: p.2 'II. VALORES EMITIDOS' (Nominal actual, amortización por bono); p.3 'BONOS ... PRINCIPAL' (Saldo anterior, Amortizaciones); p.12+ monthly pool/CPR history
... A183: ES0345672010 | B183: HIPO 11 A2 | C183: HIPOCAT 11, FTA | D183: Cuentas Anuales (EdT) | E183: 2013 | F183: https://edt-sg.com/intranet/fondos/FGH11/MFGH11C01131231.pdf | G183: discovered (web search, medium; unvalidated - host blocked by egress policy) | H183: EdT: Nota 'movimiento de los Bonos' + per-date Devengado/Liquidado/Insuficiencia table

Sheet UCI15_Pool
A1: UCI 15 - monthly collateral balance and single-month CPR since closing (issuer table, Jun-2026 report)
A3: Month end | B3: Pool outstanding (EUR) | C3: Monthly CPR (annualised) | D3: 12m trailing mean
A4: 38868 | B4: 1.3800435e+09 | C4: 0.3356
A5: 38898 | B5: 1.35325e+09 | C5: 0.1953
A6: 38929 | B6: 1.3273912e+09 | C6: 0.1922
A7: 38960 | B7: 1.3155404e+09 | C7: 0.0856
A8: 38990 | B8: 1.2974909e+09 | C8: 0.1372
A9: 39021 | B9: 1.2754426e+09 | C9: 0.1708
A10: 39051 | B10: 1.2581467e+09 | C10: 0.1353
A11: 39082 | B11: 1.2376977e+09 | C11: 0.1632
A12: 39113 | B12: 1.2236289e+09 | C12: 0.1118
A13: 39141 | B13: 1.2042436e+09 | C13: 0.1588
A14: 39172 | B14: 1.1790245e+09 | C14: 0.2096
A15: 39202 | B15: 1.1614963e+09 | C15: 0.1486 | D15: =AVERAGE(C4:C15) -> 0.17033333
A16: 39233 | B16: 1.1429609e+09 | C16: 0.1598 | D16: =AVERAGE(C5:C16) -> 0.15568333
A17: 39263 | B17: 1.1230526e+09 | C17: 0.1745 | D17: =AVERAGE(C6:C17) -> 0.15395
A18: 39294 | B18: 1.1013963e+09 | C18: 0.1931 | D18: =AVERAGE(C7:C18) -> 0.154025
A19: 39325 | B19: 1.0914863e+09 | C19: 0.0853 | D19: =AVERAGE(C8:C19) -> 0.154
A20: 39355 | B20: 1.0753616e+09 | C20: 0.1472 | D20: =AVERAGE(C9:C20) -> 0.15483333
A21: 39386 | B21: 1.0644352e+09 | C21: 0.098 | D21: =AVERAGE(C10:C21) -> 0.14876667
A22: 39416 | B22: 1.0526391e+09 | C22: 0.1079 | D22: =AVERAGE(C11:C22) -> 0.14648333
A23: 39447 | B23: 1.0420567e+09 | C23: 0.0966 | D23: =AVERAGE(C12:C23) -> 0.14093333
A24: 39478 | B24: 1.0315696e+09 | C24: 0.0966 | D24: =AVERAGE(C13:C24) -> 0.13966667
A25: 39507 | B25: 1.022458e+09 | C25: 0.083 | D25: =AVERAGE(C14:C25) -> 0.13335
A26: 39538 | B26: 1.0141694e+09 | C26: 0.0748 | D26: =AVERAGE(C15:C26) -> 0.12211667
... A244: 46173 | B244: 1.7257288e+08 | C244: 0.088 | D244: =AVERAGE(C233:C244) -> 0.07445
